Workbook

Sheet Property options
A1: Area | B1: Community | C1: Status | D1: Price (R) | E1: Type | F1: Floor level | G1: Beds | H1: Parking | I1: Floor size m2 | J1: Levies (R/pm) | K1: Rates & taxes (R/pm) | L1: Pets allowed | M1: Furnished | N1: Notes / details | O1: Agent name | P1: Agent company | Q1: Agent phone | R1: WhatsApp link | S1: Agent profile URL | T1: Listing URL | U1: Listing date | V1: Scraped on | W1: Precinct (SAPS) | X1: Precinct confidence | Y1: Violent per 100k | Z1: Property per 100k | AA1: Murder per 100k | AB1: Total per 100k | AC1: Total crimes 25/26 | AD1: Murders 25/26 | AE1: Violent 25/26 | AF1: Property 25/26 | AG1: Change in total vs 24/25 | AH1: Rank (violent, 1 = best)
A2: Port Edward | B2: Port Edward | C2: Available | D2: 610000 | E2: Apartment / Flat | F2: First Floor | G2: 2 | H2: 1 parking | I2: 84 | J2: 1800 | K2: 950 | L2: No | M2: NOT STATED | N2: PRICE REDUCED *** Well located and priced to sell, this two-bedroom, two-bathroom, main en suite, first floor apartment is move in ready, and only a f | No Pets Allowed, Garden | O2: Angelique Marran | P2: RE/MAX Coast and Country Southbroom | Q2: NOT CAPTURED (reCAPTCHA) | R2: NOT AVAILABLE (needs phone) | S2: Agent profile | T2: Open listing | U2: 03 December 2024 | V2: 2026-10-08 | W2: =IFERROR(INDEX('Area safety'!$C$23:$C$41,MATCH($B2,'Area safety'!$A$23:$A$41,0)),"n/a") -> Port Edward | X2: =IFERROR(INDEX('Area safety'!$D$23:$D$41,MATCH($B2,'Area safety'!$A$23:$A$41,0)),"n/a") -> CONFIRMED | Y2: =IFERROR(INDEX('Area safety'!$F$23:$F$41,MATCH($B2,'Area safety'!$A$23:$A$41,0)),"n/a") -> 571.8582 | Z2: =IFERROR(INDEX('Area safety'!$G$23:$G$41,MATCH($B2,'Area safety'!$A$23:$A$41,0)),"n/a") -> 596.91971 | AA2: =IFERROR(INDEX('Area safety'!$H$23:$H$41,MATCH($B2,'Area safety'!$A$23:$A$41,0)),"n/a") -> 27.339834 | AB2: =IFERROR(INDEX('Area safety'!$I$23:$I$41,MATCH($B2,'Area safety'!$A$23:$A$41,0)),"n/a") -> 2039.096 | AC2: =IFERROR(INDEX('Area safety'!$F$5:$F$18,MATCH($W2,'Area safety'!$A$5:$A$18,0)),"n/a") -> 895 | AD2: =IFERROR(INDEX('Area safety'!$G$5:$G$18,MATCH($W2,'Area safety'!$A$5:$A$18,0)),"n/a") -> 12 | AE2: =IFERROR(INDEX('Area safety'!$H$5:$H$18,MATCH($W2,'Area safety'!$A$5:$A$18,0)),"n/a") -> 251 | AF2: =IFERROR(INDEX('Area safety'!$I$5:$I$18,MATCH($W2,'Area safety'!$A$5:$A$18,0)),"n/a") -> 262 | AG2: =IFERROR(INDEX('Area safety'!$K$23:$K$41,MATCH($B2,'Area safety'!$A$23:$A$41,0)),"n/a") -> 0.083535109 | AH2: =IFERROR(INDEX('Area safety'!$J$23:$J$41,MATCH($B2,'Area safety'!$A$23:$A$41,0)),"n/a") -> 1
A3: Port Edward | B3: Port Edward | C3: Available | D3: 650000 | E3: Apartment / Flat | F3: Single Storey, Top Floor | G3: 2 | H3: 1 garage | I3: 73 | J3: 2700 | K3: 1000 | L3: No | M3: Yes | N3: Urgent sale – 2-bedroom, 2-bathroom apartment in port edward! | No Pets Allowed, Fibre Internet | O3: Mandy Cope | P3: EXP South Africa | Q3: NOT CAPTURED (reCAPTCHA) | R3: NOT AVAILABLE (needs phone) | S3: Agent profile | T3: Open listing | U3: 23 September 2026 | V3: 2026-10-08 | W3: =IFERROR(INDEX('Area safety'!$C$23:$C$41,MATCH($B3,'Area safety'!$A$23:$A$41,0)),"n/a") -> Port Edward | X3: =IFERROR(INDEX('Area safety'!$D$23:$D$41,MATCH($B3,'Area safety'!$A$23:$A$41,0)),"n/a") -> CONFIRMED | Y3: =IFERROR(INDEX('Area safety'!$F$23:$F$41,MATCH($B3,'Area safety'!$A$23:$A$41,0)),"n/a") -> 571.8582 | Z3: =IFERROR(INDEX('Area safety'!$G$23:$G$41,MATCH($B3,'Area safety'!$A$23:$A$41,0)),"n/a") -> 596.91971 | AA3: =IFERROR(INDEX('Area safety'!$H$23:$H$41,MATCH($B3,'Area safety'!$A$23:$A$41,0)),"n/a") -> 27.339834 | AB3: =IFERROR(INDEX('Area safety'!$I$23:$I$41,MATCH($B3,'Area safety'!$A$23:$A$41,0)),"n/a") -> 2039.096 | AC3: =IFERROR(INDEX('Area safety'!$F$5:$F$18,MATCH($W3,'Area safety'!$A$5:$A$18,0)),"n/a") -> 895 | AD3: =IFERROR(INDEX('Area safety'!$G$5:$G$18,MATCH($W3,'Area safety'!$A$5:$A$18,0)),"n/a") -> 12 | AE3: =IFERROR(INDEX('Area safety'!$H$5:$H$18,MATCH($W3,'Area safety'!$A$5:$A$18,0)),"n/a") -> 251 | AF3: =IFERROR(INDEX('Area safety'!$I$5:$I$18,MATCH($W3,'Area safety'!$A$5:$A$18,0)),"n/a") -> 262 | AG3: =IFERROR(INDEX('Area safety'!$K$23:$K$41,MATCH($B3,'Area safety'!$A$23:$A$41,0)),"n/a") -> 0.083535109 | AH3: =IFERROR(INDEX('Area safety'!$J$23:$J$41,MATCH($B3,'Area safety'!$A$23:$A$41,0)),"n/a") -> 1
A4: Port Edward | B4: Port Edward | C4: Available | D4: 650000 | E4: Apartment / Flat | F4: NOT STATED | G4: 2 | H4: 1 garage | I4: 18 | J4: 1830 | K4: NOT STATED | L4: NOT STATED | M4: NOT STATED | N4: This charming and secure apartment is situated in a very neat and well managed complex in the coastal town of Port Edward. | Pool, Garden | O4: Annette Mentz | P4: Chas Everitt KZN South Coast | Q4: NOT CAPTURED (reCAPTCHA) | R4: NOT AVAILABLE (needs phone) | S4: Agent profile | T4: Open listing | U4: 09 June 2026 | V4: 2026-10-08 | W4: =IFERROR(INDEX('Area safety'!$C$23:$C$41,MATCH($B4,'Area safety'!$A$23:$A$41,0)),"n/a") -> Port Edward | X4: =IFERROR(INDEX('Area safety'!$D$23:$D$41,MATCH($B4,'Area safety'!$A$23:$A$41,0)),"n/a") -> CONFIRMED | Y4: =IFERROR(INDEX('Area safety'!$F$23:$F$41,MATCH($B4,'Area safety'!$A$23:$A$41,0)),"n/a") -> 571.8582 | Z4: =IFERROR(INDEX('Area safety'!$G$23:$G$41,MATCH($B4,'Area safety'!$A$23:$A$41,0)),"n/a") -> 596.91971 | AA4: =IFERROR(INDEX('Area safety'!$H$23:$H$41,MATCH($B4,'Area safety'!$A$23:$A$41,0)),"n/a") -> 27.339834 | AB4: =IFERROR(INDEX('Area safety'!$I$23:$I$41,MATCH($B4,'Area safety'!$A$23:$A$41,0)),"n/a") -> 2039.096 | AC4: =IFERROR(INDEX('Area safety'!$F$5:$F$18,MATCH($W4,'Area safety'!$A$5:$A$18,0)),"n/a") -> 895 | AD4: =IFERROR(INDEX('Area safety'!$G$5:$G$18,MATCH($W4,'Area safety'!$A$5:$A$18,0)),"n/a") -> 12 | AE4: =IFERROR(INDEX('Area safety'!$H$5:$H$18,MATCH($W4,'Area safety'!$A$5:$A$18,0)),"n/a") -> 251 | AF4: =IFERROR(INDEX('Area safety'!$I$5:$I$18,MATCH($W4,'Area safety'!$A$5:$A$18,0)),"n/a") -> 262 | AG4: =IFERROR(INDEX('Area safety'!$K$23:$K$41,MATCH($B4,'Area safety'!$A$23:$A$41,0)),"n/a") -> 0.083535109 | AH4: =IFERROR(INDEX('Area safety'!$J$23:$J$41,MATCH($B4,'Area safety'!$A$23:$A$41,0)),"n/a") -> 1
A5: Port Edward | B5: Port Edward | C5: Available | D5: 650000 | E5: Apartment / Flat | F5: Top Floor | G5: 2 | H5: 1 parking | I5: 84 | J5: 3300 | K5: 645 | L5: NOT STATED | M5: NOT STATED | N5: Escape to a peaceful coastal retreat where comfort, relaxation, and outdoor adventure come together. | Pool, Garden | O5: Tertia Sterley | P5: Property Port | Q5: NOT CAPTURED (reCAPTCHA) | R5: NOT AVAILABLE (needs phone) | S5: Agent profile | T5: Open listing | U5: 12 March 2025 | V5: 2026-10-08 | W5: =IFERROR(INDEX('Area safety'!$C$23:$C$41,MATCH($B5,'Area safety'!$A$23:$A$41,0)),"n/a") -> Port Edward | X5: =IFERROR(INDEX('Area safety'!$D$23:$D$41,MATCH($B5,'Area safety'!$A$23:$A$41,0)),"n/a") -> CONFIRMED | Y5: =IFERROR(INDEX('Area safety'!$F$23:$F$41,MATCH($B5,'Area safety'!$A$23:$A$41,0)),"n/a") -> 571.8582 | Z5: =IFERROR(INDEX('Area safety'!$G$23:$G$41,MATCH($B5,'Area safety'!$A$23:$A$41,0)),"n/a") -> 596.91971 | AA5: =IFERROR(INDEX('Area safety'!$H$23:$H$41,MATCH($B5,'Area safety'!$A$23:$A$41,0)),"n/a") -> 27.339834 | AB5: =IFERROR(INDEX('Area safety'!$I$23:$I$41,MATCH($B5,'Area safety'!$A$23:$A$41,0)),"n/a") -> 2039.096 | AC5: =IFERROR(INDEX('Area safety'!$F$5:$F$18,MATCH($W5,'Area safety'!$A$5:$A$18,0)),"n/a") -> 895 | AD5: =IFERROR(INDEX('Area safety'!$G$5:$G$18,MATCH($W5,'Area safety'!$A$5:$A$18,0)),"n/a") -> 12 | AE5: =IFERROR(INDEX('Area safety'!$H$5:$H$18,MATCH($W5,'Area safety'!$A$5:$A$18,0)),"n/a") -> 251 | AF5: =IFERROR(INDEX('Area safety'!$I$5:$I$18,MATCH($W5,'Area safety'!$A$5:$A$18,0)),"n/a") -> 262 | AG5: =IFERROR(INDEX('Area safety'!$K$23:$K$41,MATCH($B5,'Area safety'!$A$23:$A$41,0)),"n/a") -> 0.083535109 | AH5: =IFERROR(INDEX('Area safety'!$J$23:$J$41,MATCH($B5,'Area safety'!$A$23:$A$41,0)),"n/a") -> 1
A6: Port Edward | B6: Port Edward | C6: Available | D6: 650000 | E6: Apartment / Flat | F6: NOT STATED | G6: 2 | H6: NOT STATED | I6: 76 | J6: 1000 | K6: 850 | L6: NOT STATED | M6: NOT STATED | N6: A very good for investment unit be it for long term tenants or holiday letting. | Pool | O6: Cath Molyneaux | P6: Pam Golding Properties - Port Edward | Q6: NOT CAPTURED (reCAPTCHA) | R6: NOT AVAILABLE (needs phone) | S6: Agent profile | T6: Open listing | U6: 22 August 2023 | V6: 2026-10-08 | W6: =IFERROR(INDEX('Area safety'!$C$23:$C$41,MATCH($B6,'Area safety'!$A$23:$A$41,0)),"n/a") -> Port Edward | X6: =IFERROR(INDEX('Area safety'!$D$23:$D$41,MATCH($B6,'Area safety'!$A$23:$A$41,0)),"n/a") -> CONFIRMED | Y6: =IFERROR(INDEX('Area safety'!$F$23:$F$41,MATCH($B6,'Area safety'!$A$23:$A$41,0)),"n/a") -> 571.8582 | Z6: =IFERROR(INDEX('Area safety'!$G$23:$G$41,MATCH($B6,'Area safety'!$A$23:$A$41,0)),"n/a") -> 596.91971 | AA6: =IFERROR(INDEX('Area safety'!$H$23:$H$41,MATCH($B6,'Area safety'!$A$23:$A$41,0)),"n/a") -> 27.339834 | AB6: =IFERROR(INDEX('Area safety'!$I$23:$I$41,MATCH($B6,'Area safety'!$A$23:$A$41,0)),"n/a") -> 2039.096 | AC6: =IFERROR(INDEX('Area safety'!$F$5:$F$18,MATCH($W6,'Area safety'!$A$5:$A$18,0)),"n/a") -> 895 | AD6: =IFERROR(INDEX('Area safety'!$G$5:$G$18,MATCH($W6,'Area safety'!$A$5:$A$18,0)),"n/a") -> 12 | AE6: =IFERROR(INDEX('Area safety'!$H$5:$H$18,MATCH($W6,'Area safety'!$A$5:$A$18,0)),"n/a") -> 251 | AF6: =IFERROR(INDEX('Area safety'!$I$5:$I$18,MATCH($W6,'Area safety'!$A$5:$A$18,0)),"n/a") -> 262 | AG6: =IFERROR(INDEX('Area safety'!$K$23:$K$41,MATCH($B6,'Area safety'!$A$23:$A$41,0)),"n/a") -> 0.083535109 | AH6: =IFERROR(INDEX('Area safety'!$J$23:$J$41,MATCH($B6,'Area safety'!$A$23:$A$41,0)),"n/a") -> 1
A7: Port Edward | B7: Port Edward | C7: Available | D7: 654000 | E7: Apartment / Flat | F7: Second floor and above | G7: 2 | H7: NOT STATED | I7: 84 | J7: NOT STATED | K7: NOT STATED | L7: No | M7: Yes | N7: SOLE MANDATE** This fully furnished 2-bedroom flat in Port Edward is designed for comfortable coastal living. | No Pets Allowed, Fibre Internet | O7: Janine Viljoen | P7: iProperty Investment | Q7: NOT CAPTURED (reCAPTCHA) | R7: NOT AVAILABLE (needs phone) | S7: Agent profile | T7: Open listing | U7: 09 November 2024 | V7: 2026-10-08 | W7: =IFERROR(INDEX('Area safety'!$C$23:$C$41,MATCH($B7,'Area safety'!$A$23:$A$41,0)),"n/a") -> Port Edward | X7: =IFERROR(INDEX('Area safety'!$D$23:$D$41,MATCH($B7,'Area safety'!$A$23:$A$41,0)),"n/a") -> CONFIRMED | Y7: =IFERROR(INDEX('Area safety'!$F$23:$F$41,MATCH($B7,'Area safety'!$A$23:$A$41,0)),"n/a") -> 571.8582 | Z7: =IFERROR(INDEX('Area safety'!$G$23:$G$41,MATCH($B7,'Area safety'!$A$23:$A$41,0)),"n/a") -> 596.91971 | AA7: =IFERROR(INDEX('Area safety'!$H$23:$H$41,MATCH($B7,'Area safety'!$A$23:$A$41,0)),"n/a") -> 27.339834 | AB7: =IFERROR(INDEX('Area safety'!$I$23:$I$41,MATCH($B7,'Area safety'!$A$23:$A$41,0)),"n/a") -> 2039.096 | AC7: =IFERROR(INDEX('Area safety'!$F$5:$F$18,MATCH($W7,'Area safety'!$A$5:$A$18,0)),"n/a") -> 895 | AD7: =IFERROR(INDEX('Area safety'!$G$5:$G$18,MATCH($W7,'Area safety'!$A$5:$A$18,0)),"n/a") -> 12 | AE7: =IFERROR(INDEX('Area safety'!$H$5:$H$18,MATCH($W7,'Area safety'!$A$5:$A$18,0)),"n/a") -> 251 | AF7: =IFERROR(INDEX('Area safety'!$I$5:$I$18,MATCH($W7,'Area safety'!$A$5:$A$18,0)),"n/a") -> 262 | AG7: =IFERROR(INDEX('Area safety'!$K$23:$K$41,MATCH($B7,'Area safety'!$A$23:$A$41,0)),"n/a") -> 0.083535109 | AH7: =IFERROR(INDEX('Area safety'!$J$23:$J$41,MATCH($B7,'Area safety'!$A$23:$A$41,0)),"n/a") -> 1
A8: Port Edward | B8: Port Edward | C8: Available | D8: 690000 | E8: Apartment / Flat | F8: NOT STATED | G8: 2 | H8: 2 parking | I8: 84 | J8: 2375 | K8: NOT STATED | L8: NOT STATED | M8: Yes | N8: Located in the peaceful coastal area of Rennies Beach, Port Edward, this well-maintained fully furnished 2-bedroom unit offers comfortable living surr | Garden | O8: Jessica Pretorius | P8: Real & Proper T | Q8: NOT CAPTURED (reCAPTCHA) | R8: NOT AVAILABLE (needs phone) | S8: Agent profile | T8: Open listing | U8: 20 May 2026 | V8: 2026-10-08 | W8: =IFERROR(INDEX('Area safety'!$C$23:$C$41,MATCH($B8,'Area safety'!$A$23:$A$41,0)),"n/a") -> Port Edward | X8: =IFERROR(INDEX('Area safety'!$D$23:$D$41,MATCH($B8,'Area safety'!$A$23:$A$41,0)),"n/a") -> CONFIRMED | Y8: =IFERROR(INDEX('Area safety'!$F$23:$F$41,MATCH($B8,'Area safety'!$A$23:$A$41,0)),"n/a") -> 571.8582 | Z8: =IFERROR(INDEX('Area safety'!$G$23:$G$41,MATCH($B8,'Area safety'!$A$23:$A$41,0)),"n/a") -> 596.91971 | AA8: =IFERROR(INDEX('Area safety'!$H$23:$H$41,MATCH($B8,'Area safety'!$A$23:$A$41,0)),"n/a") -> 27.339834 | AB8: =IFERROR(INDEX('Area safety'!$I$23:$I$41,MATCH($B8,'Area safety'!$A$23:$A$41,0)),"n/a") -> 2039.096 | AC8: =IFERROR(INDEX('Area safety'!$F$5:$F$18,MATCH($W8,'Area safety'!$A$5:$A$18,0)),"n/a") -> 895 | AD8: =IFERROR(INDEX('Area safety'!$G$5:$G$18,MATCH($W8,'Area safety'!$A$5:$A$18,0)),"n/a") -> 12 | AE8: =IFERROR(INDEX('Area safety'!$H$5:$H$18,MATCH($W8,'Area safety'!$A$5:$A$18,0)),"n/a") -> 251 | AF8: =IFERROR(INDEX('Area safety'!$I$5:$I$18,MATCH($W8,'Area safety'!$A$5:$A$18,0)),"n/a") -> 262 | AG8: =IFERROR(INDEX('Area safety'!$K$23:$K$41,MATCH($B8,'Area safety'!$A$23:$A$41,0)),"n/a") -> 0.083535109 | AH8: =IFERROR(INDEX('Area safety'!$J$23:$J$41,MATCH($B8,'Area safety'!$A$23:$A$41,0)),"n/a") -> 1
A9: Port Edward | B9: Port Edward | C9: Available | D9: 700000 | E9: Apartment / Flat | F9: First floor (per description) | G9: 2 | H9: NOT STATED | I9: 84 | J9: NOT STATED | K9: NOT STATED | L9: NOT STATED | M9: NOT STATED | N9: A beautifully furnished first-floor apartment situated in a secure estate, offering a peaceful lifestyle surrounded by nature and beautiful views. | Pool | O9: Drienie Cilliers | P9: Pam Golding Properties - Port Edward | Q9: NOT CAPTURED (reCAPTCHA) | R9: NOT AVAILABLE (needs phone) | S9: Agent profile | T9: Open listing | U9: 09 September 2026 | V9: 2026-10-08 | W9: =IFERROR(INDEX('Area safety'!$C$23:$C$41,MATCH($B9,'Area safety'!$A$23:$A$41,0)),"n/a") -> Port Edward | X9: =IFERROR(INDEX('Area safety'!$D$23:$D$41,MATCH($B9,'Area safety'!$A$23:$A$41,0)),"n/a") -> CONFIRMED | Y9: =IFERROR(INDEX('Area safety'!$F$23:$F$41,MATCH($B9,'Area safety'!$A$23:$A$41,0)),"n/a") -> 571.8582 | Z9: =IFERROR(INDEX('Area safety'!$G$23:$G$41,MATCH($B9,'Area safety'!$A$23:$A$41,0)),"n/a") -> 596.91971 | AA9: =IFERROR(INDEX('Area safety'!$H$23:$H$41,MATCH($B9,'Area safety'!$A$23:$A$41,0)),"n/a") -> 27.339834 | AB9: =IFERROR(INDEX('Area safety'!$I$23:$I$41,MATCH($B9,'Area safety'!$A$23:$A$41,0)),"n/a") -> 2039.096 | AC9: =IFERROR(INDEX('Area safety'!$F$5:$F$18,MATCH($W9,'Area safety'!$A$5:$A$18,0)),"n/a") -> 895 | AD9: =IFERROR(INDEX('Area safety'!$G$5:$G$18,MATCH($W9,'Area safety'!$A$5:$A$18,0)),"n/a") -> 12 | AE9: =IFERROR(INDEX('Area safety'!$H$5:$H$18,MATCH($W9,'Area safety'!$A$5:$A$18,0)),"n/a") -> 251 | AF9: =IFERROR(INDEX('Area safety'!$I$5:$I$18,MATCH($W9,'Area safety'!$A$5:$A$18,0)),"n/a") -> 262 | AG9: =IFERROR(INDEX('Area safety'!$K$23:$K$41,MATCH($B9,'Area safety'!$A$23:$A$41,0)),"n/a") -> 0.083535109 | AH9: =IFERROR(INDEX('Area safety'!$J$23:$J$41,MATCH($B9,'Area safety'!$A$23:$A$41,0)),"n/a") -> 1
A10: Port Edward | B10: Port Edward | C10: Available | D10: 700000 | E10: Apartment / Flat | F10: First Floor | G10: 2 | H10: 1 parking | I10: 84 | J10: 2500 | K10: 550 | L10: No | M10: NOT STATED | N10: SOLE MANDATE *** Nestled on the banks of the Umtamvuna river and surrounded by the serene beauty of nature, this upmarket and exclusive two-bedroom, o | No Pets Allowed, Pool, Garden | O10: Angelique Marran | P10: RE/MAX Coast and Country Southbroom | Q10: NOT CAPTURED (reCAPTCHA) | R10: NOT AVAILABLE (needs phone) | S10: Agent profile | T10: Open listing | U10: 13 October 2024 | V10: 2026-10-08 | W10: =IFERROR(INDEX('Area safety'!$C$23:$C$41,MATCH($B10,'Area safety'!$A$23:$A$41,0)),"n/a") -> Port Edward | X10: =IFERROR(INDEX('Area safety'!$D$23:$D$41,MATCH($B10,'Area safety'!$A$23:$A$41,0)),"n/a") -> CONFIRMED | Y10: =IFERROR(INDEX('Area safety'!$F$23:$F$41,MATCH($B10,'Area safety'!$A$23:$A$41,0)),"n/a") -> 571.8582 | Z10: =IFERROR(INDEX('Area safety'!$G$23:$G$41,MATCH($B10,'Area safety'!$A$23:$A$41,0)),"n/a") -> 596.91971 | AA10: =IFERROR(INDEX('Area safety'!$H$23:$H$41,MATCH($B10,'Area safety'!$A$23:$A$41,0)),"n/a") -> 27.339834 | AB10: =IFERROR(INDEX('Area safety'!$I$23:$I$41,MATCH($B10,'Area safety'!$A$23:$A$41,0)),"n/a") -> 2039.096 | AC10: =IFERROR(INDEX('Area safety'!$F$5:$F$18,MATCH($W10,'Area safety'!$A$5:$A$18,0)),"n/a") -> 895 | AD10: =IFERROR(INDEX('Area safety'!$G$5:$G$18,MATCH($W10,'Area safety'!$A$5:$A$18,0)),"n/a") -> 12 | AE10: =IFERROR(INDEX('Area safety'!$H$5:$H$18,MATCH($W10,'Area safety'!$A$5:$A$18,0)),"n/a") -> 251 | AF10: =IFERROR(INDEX('Area safety'!$I$5:$I$18,MATCH($W10,'Area safety'!$A$5:$A$18,0)),"n/a") -> 262 | AG10: =IFERROR(INDEX('Area safety'!$K$23:$K$41,MATCH($B10,'Area safety'!$A$23:$A$41,0)),"n/a") -> 0.083535109 | AH10: =IFERROR(INDEX('Area safety'!$J$23:$J$41,MATCH($B10,'Area safety'!$A$23:$A$41,0)),"n/a") -> 1
A11: Port Edward | B11: Port Edward | C11: Available | D11: 720000 | E11: Apartment / Flat | F11: NOT STATED | G11: 2 | H11: 1 garage | I11: 111 | J11: 1895 | K11: 800 | L11: Yes | M11: NOT STATED | N11: Lovely 2 bedroom duplex unit situated in a very secure complex close to all major amenities. | Pet Friendly, Pool, Garden, Fibre Internet | O11: Jean Du Toit | P11: Shoreline Properties Leisure Bay | Q11: NOT CAPTURED (reCAPTCHA) | R11: NOT AVAILABLE (needs phone) | S11: Agent profile | T11: Open listing | U11: 12 September 2024 | V11: 2026-10-08 | W11: =IFERROR(INDEX('Area safety'!$C$23:$C$41,MATCH($B11,'Area safety'!$A$23:$A$41,0)),"n/a") -> Port Edward | X11: =IFERROR(INDEX('Area safety'!$D$23:$D$41,MATCH($B11,'Area safety'!$A$23:$A$41,0)),"n/a") -> CONFIRMED | Y11: =IFERROR(INDEX('Area safety'!$F$23:$F$41,MATCH($B11,'Area safety'!$A$23:$A$41,0)),"n/a") -> 571.8582 | Z11: =IFERROR(INDEX('Area safety'!$G$23:$G$41,MATCH($B11,'Area safety'!$A$23:$A$41,0)),"n/a") -> 596.91971 | AA11: =IFERROR(INDEX('Area safety'!$H$23:$H$41,MATCH($B11,'Area safety'!$A$23:$A$41,0)),"n/a") -> 27.339834 | AB11: =IFERROR(INDEX('Area safety'!$I$23:$I$41,MATCH($B11,'Area safety'!$A$23:$A$41,0)),"n/a") -> 2039.096 | AC11: =IFERROR(INDEX('Area safety'!$F$5:$F$18,MATCH($W11,'Area safety'!$A$5:$A$18,0)),"n/a") -> 895 | AD11: =IFERROR(INDEX('Area safety'!$G$5:$G$18,MATCH($W11,'Area safety'!$A$5:$A$18,0)),"n/a") -> 12 | AE11: =IFERROR(INDEX('Area safety'!$H$5:$H$18,MATCH($W11,'Area safety'!$A$5:$A$18,0)),"n/a") -> 251 | AF11: =IFERROR(INDEX('Area safety'!$I$5:$I$18,MATCH($W11,'Area safety'!$A$5:$A$18,0)),"n/a") -> 262 | AG11: =IFERROR(INDEX('Area safety'!$K$23:$K$41,MATCH($B11,'Area safety'!$A$23:$A$41,0)),"n/a") -> 0.083535109 | AH11: =IFERROR(INDEX('Area safety'!$J$23:$J$41,MATCH($B11,'Area safety'!$A$23:$A$41,0)),"n/a") -> 1
A12: Port Edward | B12: Glenmore | C12: Available | D12: 620000 | E12: Apartment / Flat | F12: NOT STATED | G12: 2 | H12: 1 parking | I12: 85 | J12: 2200 | K12: 650 | L12: Yes | M12: NOT STATED | N12: Ideal 2 Bedroom Retirement/Holiday unit in secure complex close to all amenities. | Pet Friendly, Pool, Garden, Fibre Internet | O12: NOT STATED | P12: Realty1 Munster | Q12: NOT CAPTURED (reCAPTCHA) | R12: NOT AVAILABLE (needs phone) | S12: NOT STATED | T12: Open listing | U12: 20 July 2026 | V12: 2026-10-08 | W12: =IFERROR(INDEX('Area safety'!$C$23:$C$41,MATCH($B12,'Area safety'!$A$23:$A$41,0)),"n/a") -> Port Edward | X12: =IFERROR(INDEX('Area safety'!$D$23:$D$41,MATCH($B12,'Area safety'!$A$23:$A$41,0)),"n/a") -> UNCONFIRMED - provisional (assumed Port Edward precinct) | Y12: =IFERROR(INDEX('Area safety'!$F$23:$F$41,MATCH($B12,'Area safety'!$A$23:$A$41,0)),"n/a") -> 571.8582 | Z12: =IFERROR(INDEX('Area safety'!$G$23:$G$41,MATCH($B12,'Area safety'!$A$23:$A$41,0)),"n/a") -> 596.91971 | AA12: =IFERROR(INDEX('Area safety'!$H$23:$H$41,MATCH($B12,'Area safety'!$A$23:$A$41,0)),"n/a") -> 27.339834 | AB12: =IFERROR(INDEX('Area safety'!$I$23:$I$41,MATCH($B12,'Area safety'!$A$23:$A$41,0)),"n/a") -> 2039.096 | AC12: =IFERROR(INDEX('Area safety'!$F$5:$F$18,MATCH($W12,'Area safety'!$A$5:$A$18,0)),"n/a") -> 895 | AD12: =IFERROR(INDEX('Area safety'!$G$5:$G$18,MATCH($W12,'Area safety'!$A$5:$A$18,0)),"n/a") -> 12 | AE12: =IFERROR(INDEX('Area safety'!$H$5:$H$18,MATCH($W12,'Area safety'!$A$5:$A$18,0)),"n/a") -> 251 | AF12: =IFERROR(INDEX('Area safety'!$I$5:$I$18,MATCH($W12,'Area safety'!$A$5:$A$18,0)),"n/a") -> 262 | AG12: =IFERROR(INDEX('Area safety'!$K$23:$K$41,MATCH($B12,'Area safety'!$A$23:$A$41,0)),"n/a") -> 0.083535109 | AH12: =IFERROR(INDEX('Area safety'!$J$23:$J$41,MATCH($B12,'Area safety'!$A$23:$A$41,0)),"n/a") -> 1
A13: Port Edward | B13: Glenmore | C13: Available | D13: 620000 | E13: Apartment / Flat | F13: NOT STATED | G13: 2 | H13: 2 parking | I13: 85 | J13: 2200 | K13: 700 | L13: Yes | M13: NOT STATED | N13: Priced to sell fast! This neat and spacious 2-bedroom, 1-bathroom unit is perfect for retirees or holidaymakers looking for comfort and convenience. | Pet Friendly, Pool | O13: Keith Roger Nkala | P13: EXP South Africa | Q13: NOT CAPTURED (reCAPTCHA) | R13: NOT AVAILABLE (needs phone) | S13: Agent profile | T13: Open listing | U13: 22 July 2026 | V13: 2026-10-08 | W13: =IFERROR(INDEX('Area safety'!$C$23:$C$41,MATCH($B13,'Area safety'!$A$23:$A$41,0)),"n/a") -> Port Edward | X13: =IFERROR(INDEX('Area safety'!$D$23:$D$41,MATCH($B13,'Area safety'!$A$23:$A$41,0)),"n/a") -> UNCONFIRMED - provisional (assumed Port Edward precinct) | Y13: =IFERROR(INDEX('Area safety'!$F$23:$F$41,MATCH($B13,'Area safety'!$A$23:$A$41,0)),"n/a") -> 571.8582 | Z13: =IFERROR(INDEX('Area safety'!$G$23:$G$41,MATCH($B13,'Area safety'!$A$23:$A$41,0)),"n/a") -> 596.91971 | AA13: =IFERROR(INDEX('Area safety'!$H$23:$H$41,MATCH($B13,'Area safety'!$A$23:$A$41,0)),"n/a") -> 27.339834 | AB13: =IFERROR(INDEX('Area safety'!$I$23:$I$41,MATCH($B13,'Area safety'!$A$23:$A$41,0)),"n/a") -> 2039.096 | AC13: =IFERROR(INDEX('Area safety'!$F$5:$F$18,MATCH($W13,'Area safety'!$A$5:$A$18,0)),"n/a") -> 895 | AD13: =IFERROR(INDEX('Area safety'!$G$5:$G$18,MATCH($W13,'Area safety'!$A$5:$A$18,0)),"n/a") -> 12 | AE13: =IFERROR(INDEX('Area safety'!$H$5:$H$18,MATCH($W13,'Area safety'!$A$5:$A$18,0)),"n/a") -> 251 | AF13: =IFERROR(INDEX('Area safety'!$I$5:$I$18,MATCH($W13,'Area safety'!$A$5:$A$18,0)),"n/a") -> 262 | AG13: =IFERROR(INDEX('Area safety'!$K$23:$K$41,MATCH($B13,'Area safety'!$A$23:$A$41,0)),"n/a") -> 0.083535109 | AH13: =IFERROR(INDEX('Area safety'!$J$23:$J$41,MATCH($B13,'Area safety'!$A$23:$A$41,0)),"n/a") -> 1
A14: Port Edward | B14: Glenmore | C14: Available | D14: 650000 | E14: Apartment / Flat | F14: First floor (per description) | G14: 2 | H14: 1 parking | I14: 60 | J14: 1600 | K14: 850 | L14: NOT STATED | M14: NOT STATED | N14: Charming Coastal Apartment in a Peaceful Setting Enjoy comfortable coastal living in this lovely apartment, situated within a short walking distance o | Pool, Garden | O14: Sylvia Mc Donald | P14: Real Estate Services | Q14: NOT CAPTURED (reCAPTCHA) | R14: NOT AVAILABLE (needs phone) | S14: Agent profile | T14: Open listing | U14: 04 September 2026 | V14: 2026-10-08 | W14: =IFERROR(INDEX('Area safety'!$C$23:$C$41,MATCH($B14,'Area safety'!$A$23:$A$41,0)),"n/a") -> Port Edward | X14: =IFERROR(INDEX('Area safety'!$D$23:$D$41,MATCH($B14,'Area safety'!$A$23:$A$41,0)),"n/a") -> UNCONFIRMED - provisional (assumed Port Edward precinct) | Y14: =IFERROR(INDEX('Area safety'!$F$23:$F$41,MATCH($B14,'Area safety'!$A$23:$A$41,0)),"n/a") -> 571.8582 | Z14: =IFERROR(INDEX('Area safety'!$G$23:$G$41,MATCH($B14,'Area safety'!$A$23:$A$41,0)),"n/a") -> 596.91971 | AA14: =IFERROR(INDEX('Area safety'!$H$23:$H$41,MATCH($B14,'Area safety'!$A$23:$A$41,0)),"n/a") -> 27.339834 | AB14: =IFERROR(INDEX('Area safety'!$I$23:$I$41,MATCH($B14,'Area safety'!$A$23:$A$41,0)),"n/a") -> 2039.096 | AC14: =IFERROR(INDEX('Area safety'!$F$5:$F$18,MATCH($W14,'Area safety'!$A$5:$A$18,0)),"n/a") -> 895 | AD14: =IFERROR(INDEX('Area safety'!$G$5:$G$18,MATCH($W14,'Area safety'!$A$5:$A$18,0)),"n/a") -> 12 | AE14: =IFERROR(INDEX('Area safety'!$H$5:$H$18,MATCH($W14,'Area safety'!$A$5:$A$18,0)),"n/a") -> 251 | AF14: =IFERROR(INDEX('Area safety'!$I$5:$I$18,MATCH($W14,'Area safety'!$A$5:$A$18,0)),"n/a") -> 262 | AG14: =IFERROR(INDEX('Area safety'!$K$23:$K$41,MATCH($B14,'Area safety'!$A$23:$A$41,0)),"n/a") -> 0.083535109 | AH14: =IFERROR(INDEX('Area safety'!$J$23:$J$41,MATCH($B14,'Area safety'!$A$23:$A$41,0)),"n/a") -> 1
A15: Port Edward | B15: Glenmore | C15: Available | D15: 695000 | E15: Apartment / Flat | F15: Mixed: description mentions ground AND second floor [CHECK floor] | G15: 2 | H15: 1 parking | I15: 58 | J15: 2000 | K15: 450 | L15: No | M15: Yes | N15: Prime investment opportunities like this don't come around too often. | No Pets Allowed, Pool, Solar Panels | O15: NOT STATED | P15: Realty1 Munster | Q15: NOT CAPTURED (reCAPTCHA) | R15: NOT AVAILABLE (needs phone) | S15: NOT STATED | T15: Open listing | U15: 23 September 2026 | V15: 2026-10-08 | W15: =IFERROR(INDEX('Area safety'!$C$23:$C$41,MATCH($B15,'Area safety'!$A$23:$A$41,0)),"n/a") -> Port Edward | X15: =IFERROR(INDEX('Area safety'!$D$23:$D$41,MATCH($B15,'Area safety'!$A$23:$A$41,0)),"n/a") -> UNCONFIRMED - provisional (assumed Port Edward precinct) | Y15: =IFERROR(INDEX('Area safety'!$F$23:$F$41,MATCH($B15,'Area safety'!$A$23:$A$41,0)),"n/a") -> 571.8582 | Z15: =IFERROR(INDEX('Area safety'!$G$23:$G$41,MATCH($B15,'Area safety'!$A$23:$A$41,0)),"n/a") -> 596.91971 | AA15: =IFERROR(INDEX('Area safety'!$H$23:$H$41,MATCH($B15,'Area safety'!$A$23:$A$41,0)),"n/a") -> 27.339834 | AB15: =IFERROR(INDEX('Area safety'!$I$23:$I$41,MATCH($B15,'Area safety'!$A$23:$A$41,0)),"n/a") -> 2039.096 | AC15: =IFERROR(INDEX('Area safety'!$F$5:$F$18,MATCH($W15,'Area safety'!$A$5:$A$18,0)),"n/a") -> 895 | AD15: =IFERROR(INDEX('Area safety'!$G$5:$G$18,MATCH($W15,'Area safety'!$A$5:$A$18,0)),"n/a") -> 12 | AE15: =IFERROR(INDEX('Area safety'!$H$5:$H$18,MATCH($W15,'Area safety'!$A$5:$A$18,0)),"n/a") -> 251 | AF15: =IFERROR(INDEX('Area safety'!$I$5:$I$18,MATCH($W15,'Area safety'!$A$5:$A$18,0)),"n/a") -> 262 | AG15: =IFERROR(INDEX('Area safety'!$K$23:$K$41,MATCH($B15,'Area safety'!$A$23:$A$41,0)),"n/a") -> 0.083535109 | AH15: =IFERROR(INDEX('Area safety'!$J$23:$J$41,MATCH($B15,'Area safety'!$A$23:$A$41,0)),"n/a") -> 1
A16: Port Edward | B16: Glenmore | C16: Available | D16: 695000 | E16: Apartment / Flat | F16: Floor 1 | G16: 2 | H16: 1 parking | I16: 74 | J16: 2133 | K16: 1200 | L16: No | M16: NOT STATED | N16: This well-positioned 2-bedroom apartment offers comfortable and secure living, ideal for both homeowners and investors. | No Pets Allowed | O16: Snyanie Tshobonga | P16: Just Property Living | Q16: NOT CAPTURED (reCAPTCHA) | R16: NOT AVAILABLE (needs phone) | S16: Agent profile | T16: Open listing | U16: 08 April 2026 | V16: 2026-10-08 | W16: =IFERROR(INDEX('Area safety'!$C$23:$C$41,MATCH($B16,'Area safety'!$A$23:$A$41,0)),"n/a") -> Port Edward | X16: =IFERROR(INDEX('Area safety'!$D$23:$D$41,MATCH($B16,'Area safety'!$A$23:$A$41,0)),"n/a") -> UNCONFIRMED - provisional (assumed Port Edward precinct) | Y16: =IFERROR(INDEX('Area safety'!$F$23:$F$41,MATCH($B16,'Area safety'!$A$23:$A$41,0)),"n/a") -> 571.8582 | Z16: =IFERROR(INDEX('Area safety'!$G$23:$G$41,MATCH($B16,'Area safety'!$A$23:$A$41,0)),"n/a") -> 596.91971 | AA16: =IFERROR(INDEX('Area safety'!$H$23:$H$41,MATCH($B16,'Area safety'!$A$23:$A$41,0)),"n/a") -> 27.339834 | AB16: =IFERROR(INDEX('Area safety'!$I$23:$I$41,MATCH($B16,'Area safety'!$A$23:$A$41,0)),"n/a") -> 2039.096 | AC16: =IFERROR(INDEX('Area safety'!$F$5:$F$18,MATCH($W16,'Area safety'!$A$5:$A$18,0)),"n/a") -> 895 | AD16: =IFERROR(INDEX('Area safety'!$G$5:$G$18,MATCH($W16,'Area safety'!$A$5:$A$18,0)),"n/a") -> 12 | AE16: =IFERROR(INDEX('Area safety'!$H$5:$H$18,MATCH($W16,'Area safety'!$A$5:$A$18,0)),"n/a") -> 251 | AF16: =IFERROR(INDEX('Area safety'!$I$5:$I$18,MATCH($W16,'Area safety'!$A$5:$A$18,0)),"n/a") -> 262 | AG16: =IFERROR(INDEX('Area safety'!$K$23:$K$41,MATCH($B16,'Area safety'!$A$23:$A$41,0)),"n/a") -> 0.083535109 | AH16: =IFERROR(INDEX('Area safety'!$J$23:$J$41,MATCH($B16,'Area safety'!$A$23:$A$41,0)),"n/a") -> 1
A17: Port Edward | B17: Glenmore | C17: Available | D17: 750000 | E17: Apartment / Flat | F17: NOT STATED | G17: 2 | H17: 1 parking | I17: NOT STATED | J17: 1700 | K17: 750 | L17: Yes | M17: Yes | N17: Have you been dreaming of living on the south coast. | Pet Friendly, Pool, Garden | O17: Annette Mentz | P17: Chas Everitt KZN South Coast | Q17: NOT CAPTURED (reCAPTCHA) | R17: NOT AVAILABLE (needs phone) | S17: Agent profile | T17: Open listing | U17: 04 July 2023 | V17: 2026-10-08 | W17: =IFERROR(INDEX('Area safety'!$C$23:$C$41,MATCH($B17,'Area safety'!$A$23:$A$41,0)),"n/a") -> Port Edward | X17: =IFERROR(INDEX('Area safety'!$D$23:$D$41,MATCH($B17,'Area safety'!$A$23:$A$41,0)),"n/a") -> UNCONFIRMED - provisional (assumed Port Edward precinct) | Y17: =IFERROR(INDEX('Area safety'!$F$23:$F$41,MATCH($B17,'Area safety'!$A$23:$A$41,0)),"n/a") -> 571.8582 | Z17: =IFERROR(INDEX('Area safety'!$G$23:$G$41,MATCH($B17,'Area safety'!$A$23:$A$41,0)),"n/a") -> 596.91971 | AA17: =IFERROR(INDEX('Area safety'!$H$23:$H$41,MATCH($B17,'Area safety'!$A$23:$A$41,0)),"n/a") -> 27.339834 | AB17: =IFERROR(INDEX('Area safety'!$I$23:$I$41,MATCH($B17,'Area safety'!$A$23:$A$41,0)),"n/a") -> 2039.096 | AC17: =IFERROR(INDEX('Area safety'!$F$5:$F$18,MATCH($W17,'Area safety'!$A$5:$A$18,0)),"n/a") -> 895 | AD17: =IFERROR(INDEX('Area safety'!$G$5:$G$18,MATCH($W17,'Area safety'!$A$5:$A$18,0)),"n/a") -> 12 | AE17: =IFERROR(INDEX('Area safety'!$H$5:$H$18,MATCH($W17,'Area safety'!$A$5:$A$18,0)),"n/a") -> 251 | AF17: =IFERROR(INDEX('Area safety'!$I$5:$I$18,MATCH($W17,'Area safety'!$A$5:$A$18,0)),"n/a") -> 262 | AG17: =IFERROR(INDEX('Area safety'!$K$23:$K$41,MATCH($B17,'Area safety'!$A$23:$A$41,0)),"n/a") -> 0.083535109 | AH17: =IFERROR(INDEX('Area safety'!$J$23:$J$41,MATCH($B17,'Area safety'!$A$23:$A$41,0)),"n/a") -> 1
A18: Port Edward | B18: Leisure Bay | C18: Available | D18: 570000 | E18: Apartment / Flat | F18: NOT STATED | G18: 2 | H18: 1 parking | I18: 83 | J18: NOT STATED | K18: NOT STATED | L18: NOT STATED | M18: NOT STATED | N18: Hello, my name is Steven, your dedicated South Coast Property Practitioner. | O18: Steven Plint | P18: Real & Proper T | Q18: NOT CAPTURED (reCAPTCHA) | R18: NOT AVAILABLE (needs phone) | S18: Agent profile | T18: Open listing | U18: 01 July 2026 | V18: 2026-10-08 | W18: =IFERROR(INDEX('Area safety'!$C$23:$C$41,MATCH($B18,'Area safety'!$A$23:$A$41,0)),"n/a") -> Port Edward | X18: =IFERROR(INDEX('Area safety'!$D$23:$D$41,MATCH($B18,'Area safety'!$A$23:$A$41,0)),"n/a") -> CONFIRMED | Y18: =IFERROR(INDEX('Area safety'!$F$23:$F$41,MATCH($B18,'Area safety'!$A$23:$A$41,0)),"n/a") -> 571.8582 | Z18: =IFERROR(INDEX('Area safety'!$G$23:$G$41,MATCH($B18,'Area safety'!$A$23:$A$41,0)),"n/a") -> 596.91971 | AA18: =IFERROR(INDEX('Area safety'!$H$23:$H$41,MATCH($B18,'Area safety'!$A$23:$A$41,0)),"n/a") -> 27.339834 | AB18: =IFERROR(INDEX('Area safety'!$I$23:$I$41,MATCH($B18,'Area safety'!$A$23:$A$41,0)),"n/a") -> 2039.096 | AC18: =IFERROR(INDEX('Area safety'!$F$5:$F$18,MATCH($W18,'Area safety'!$A$5:$A$18,0)),"n/a") -> 895 | AD18: =IFERROR(INDEX('Area safety'!$G$5:$G$18,MATCH($W18,'Area safety'!$A$5:$A$18,0)),"n/a") -> 12 | AE18: =IFERROR(INDEX('Area safety'!$H$5:$H$18,MATCH($W18,'Area safety'!$A$5:$A$18,0)),"n/a") -> 251 | AF18: =IFERROR(INDEX('Area safety'!$I$5:$I$18,MATCH($W18,'Area safety'!$A$5:$A$18,0)),"n/a") -> 262 | AG18: =IFERROR(INDEX('Area safety'!$K$23:$K$41,MATCH($B18,'Area safety'!$A$23:$A$41,0)),"n/a") -> 0.083535109 | AH18: =IFERROR(INDEX('Area safety'!$J$23:$J$41,MATCH($B18,'Area safety'!$A$23:$A$41,0)),"n/a") -> 1
A19: Port Edward | B19: Leisure Bay | C19: Available | D19: 695000 | E19: Apartment / Flat | F19: NOT STATED | G19: 2 | H19: 1 parking | I19: 78 | J19: 3000 | K19: 700 | L19: No | M19: Optional | N19: Leisure Bay If you are looking for a neat and well run complex on the coast, then this is it!! | No Pets Allowed, Fibre Internet | O19: Jean Du Toit | P19: Shoreline Properties Leisure Bay | Q19: NOT CAPTURED (reCAPTCHA) | R19: NOT AVAILABLE (needs phone) | S19: Agent profile | T19: Open listing | U19: 16 April 2026 | V19: 2026-10-08 | W19: =IFERROR(INDEX('Area safety'!$C$23:$C$41,MATCH($B19,'Area safety'!$A$23:$A$41,0)),"n/a") -> Port Edward | X19: =IFERROR(INDEX('Area safety'!$D$23:$D$41,MATCH($B19,'Area safety'!$A$23:$A$41,0)),"n/a") -> CONFIRMED | Y19: =IFERROR(INDEX('Area safety'!$F$23:$F$41,MATCH($B19,'Area safety'!$A$23:$A$41,0)),"n/a") -> 571.8582 | Z19: =IFERROR(INDEX('Area safety'!$G$23:$G$41,MATCH($B19,'Area safety'!$A$23:$A$41,0)),"n/a") -> 596.91971 | AA19: =IFERROR(INDEX('Area safety'!$H$23:$H$41,MATCH($B19,'Area safety'!$A$23:$A$41,0)),"n/a") -> 27.339834 | AB19: =IFERROR(INDEX('Area safety'!$I$23:$I$41,MATCH($B19,'Area safety'!$A$23:$A$41,0)),"n/a") -> 2039.096 | AC19: =IFERROR(INDEX('Area safety'!$F$5:$F$18,MATCH($W19,'Area safety'!$A$5:$A$18,0)),"n/a") -> 895 | AD19: =IFERROR(INDEX('Area safety'!$G$5:$G$18,MATCH($W19,'Area safety'!$A$5:$A$18,0)),"n/a") -> 12 | AE19: =IFERROR(INDEX('Area safety'!$H$5:$H$18,MATCH($W19,'Area safety'!$A$5:$A$18,0)),"n/a") -> 251 | AF19: =IFERROR(INDEX('Area safety'!$I$5:$I$18,MATCH($W19,'Area safety'!$A$5:$A$18,0)),"n/a") -> 262 | AG19: =IFERROR(INDEX('Area safety'!$K$23:$K$41,MATCH($B19,'Area safety'!$A$23:$A$41,0)),"n/a") -> 0.083535109 | AH19: =IFERROR(INDEX('Area safety'!$J$23:$J$41,MATCH($B19,'Area safety'!$A$23:$A$41,0)),"n/a") -> 1
A20: Port Edward | B20: Banners Rest | C20: Available | D20: 540000 | E20: Apartment / Flat | F20: NOT STATED | G20: 2 | H20: NOT STATED | I20: 86 | J20: 1727 | K20: NOT STATED | L20: NOT STATED | M20: NOT STATED | N20: Experience the ultimate blend of natural beauty and modern comfort in this stunning 2-bedroom apartment. | Pool | O20: Drienie Cilliers | P20: Pam Golding Properties - Port Edward | Q20: NOT CAPTURED (reCAPTCHA) | R20: NOT AVAILABLE (needs phone) | S20: Agent profile | T20: Open listing | U20: 30 October 2024 | V20: 2026-10-08 | W20: =IFERROR(INDEX('Area safety'!$C$23:$C$41,MATCH($B20,'Area safety'!$A$23:$A$41,0)),"n/a") -> Port Edward | X20: =IFERROR(INDEX('Area safety'!$D$23:$D$41,MATCH($B20,'Area safety'!$A$23:$A$41,0)),"n/a") -> UNCONFIRMED - provisional (assumed Port Edward precinct) | Y20: =IFERROR(INDEX('Area safety'!$F$23:$F$41,MATCH($B20,'Area safety'!$A$23:$A$41,0)),"n/a") -> 571.8582 | Z20: =IFERROR(INDEX('Area safety'!$G$23:$G$41,MATCH($B20,'Area safety'!$A$23:$A$41,0)),"n/a") -> 596.91971 | AA20: =IFERROR(INDEX('Area safety'!$H$23:$H$41,MATCH($B20,'Area safety'!$A$23:$A$41,0)),"n/a") -> 27.339834 | AB20: =IFERROR(INDEX('Area safety'!$I$23:$I$41,MATCH($B20,'Area safety'!$A$23:$A$41,0)),"n/a") -> 2039.096 | AC20: =IFERROR(INDEX('Area safety'!$F$5:$F$18,MATCH($W20,'Area safety'!$A$5:$A$18,0)),"n/a") -> 895 | AD20: =IFERROR(INDEX('Area safety'!$G$5:$G$18,MATCH($W20,'Area safety'!$A$5:$A$18,0)),"n/a") -> 12 | AE20: =IFERROR(INDEX('Area safety'!$H$5:$H$18,MATCH($W20,'Area safety'!$A$5:$A$18,0)),"n/a") -> 251 | AF20: =IFERROR(INDEX('Area safety'!$I$5:$I$18,MATCH($W20,'Area safety'!$A$5:$A$18,0)),"n/a") -> 262 | AG20: =IFERROR(INDEX('Area safety'!$K$23:$K$41,MATCH($B20,'Area safety'!$A$23:$A$41,0)),"n/a") -> 0.083535109 | AH20: =IFERROR(INDEX('Area safety'!$J$23:$J$41,MATCH($B20,'Area safety'!$A$23:$A$41,0)),"n/a") -> 1
A21: Port Edward | B21: Banners Rest | C21: Available | D21: 545000 | E21: Apartment / Flat | F21: NOT STATED | G21: 2 | H21: 1 garage | I21: 86 | J21: 2765 | K21: 800 | L21: NOT STATED | M21: NOT STATED | N21: Discover relaxed coastal living in this beautiful 2-bedroom apartment perfectly positioned in the sought-after Banners Rest area. | Pool | O21: Cath Molyneaux | P21: Pam Golding Properties - Port Edward | Q21: NOT CAPTURED (reCAPTCHA) | R21: NOT AVAILABLE (needs phone) | S21: Agent profile | T21: Open listing | U21: 14 November 2025 | V21: 2026-10-08 | W21: =IFERROR(INDEX('Area safety'!$C$23:$C$41,MATCH($B21,'Area safety'!$A$23:$A$41,0)),"n/a") -> Port Edward | X21: =IFERROR(INDEX('Area safety'!$D$23:$D$41,MATCH($B21,'Area safety'!$A$23:$A$41,0)),"n/a") -> UNCONFIRMED - provisional (assumed Port Edward precinct) | Y21: =IFERROR(INDEX('Area safety'!$F$23:$F$41,MATCH($B21,'Area safety'!$A$23:$A$41,0)),"n/a") -> 571.8582 | Z21: =IFERROR(INDEX('Area safety'!$G$23:$G$41,MATCH($B21,'Area safety'!$A$23:$A$41,0)),"n/a") -> 596.91971 | AA21: =IFERROR(INDEX('Area safety'!$H$23:$H$41,MATCH($B21,'Area safety'!$A$23:$A$41,0)),"n/a") -> 27.339834 | AB21: =IFERROR(INDEX('Area safety'!$I$23:$I$41,MATCH($B21,'Area safety'!$A$23:$A$41,0)),"n/a") -> 2039.096 | AC21: =IFERROR(INDEX('Area safety'!$F$5:$F$18,MATCH($W21,'Area safety'!$A$5:$A$18,0)),"n/a") -> 895 | AD21: =IFERROR(INDEX('Area safety'!$G$5:$G$18,MATCH($W21,'Area safety'!$A$5:$A$18,0)),"n/a") -> 12 | AE21: =IFERROR(INDEX('Area safety'!$H$5:$H$18,MATCH($W21,'Area safety'!$A$5:$A$18,0)),"n/a") -> 251 | AF21: =IFERROR(INDEX('Area safety'!$I$5:$I$18,MATCH($W21,'Area safety'!$A$5:$A$18,0)),"n/a") -> 262 | AG21: =IFERROR(INDEX('Area safety'!$K$23:$K$41,MATCH($B21,'Area safety'!$A$23:$A$41,0)),"n/a") -> 0.083535109 | AH21: =IFERROR(INDEX('Area safety'!$J$23:$J$41,MATCH($B21,'Area safety'!$A$23:$A$41,0)),"n/a") -> 1
A22: Port Edward | B22: Banners Rest | C22: Available | D22: 550000 | E22: Apartment / Flat | F22: NOT STATED | G22: 2 | H22: 2 parking | I22: 84 | J22: 2300 | K22: 600 | L22: NOT STATED | M22: NOT STATED | N22: Discover an irresistible offer! | Pool | O22: Dennis Hammerschlag | P22: Pam Golding Properties - Port Edward | Q22: NOT CAPTURED (reCAPTCHA) | R22: NOT AVAILABLE (needs phone) | S22: Agent profile | T22: Open listing | U22: 04 June 2025 | V22: 2026-10-08 | W22: =IFERROR(INDEX('Area safety'!$C$23:$C$41,MATCH($B22,'Area safety'!$A$23:$A$41,0)),"n/a") -> Port Edward | X22: =IFERROR(INDEX('Area safety'!$D$23:$D$41,MATCH($B22,'Area safety'!$A$23:$A$41,0)),"n/a") -> UNCONFIRMED - provisional (assumed Port Edward precinct) | Y22: =IFERROR(INDEX('Area safety'!$F$23:$F$41,MATCH($B22,'Area safety'!$A$23:$A$41,0)),"n/a") -> 571.8582 | Z22: =IFERROR(INDEX('Area safety'!$G$23:$G$41,MATCH($B22,'Area safety'!$A$23:$A$41,0)),"n/a") -> 596.91971 | AA22: =IFERROR(INDEX('Area safety'!$H$23:$H$41,MATCH($B22,'Area safety'!$A$23:$A$41,0)),"n/a") -> 27.339834 | AB22: =IFERROR(INDEX('Area safety'!$I$23:$I$41,MATCH($B22,'Area safety'!$A$23:$A$41,0)),"n/a") -> 2039.096 | AC22: =IFERROR(INDEX('Area safety'!$F$5:$F$18,MATCH($W22,'Area safety'!$A$5:$A$18,0)),"n/a") -> 895 | AD22: =IFERROR(INDEX('Area safety'!$G$5:$G$18,MATCH($W22,'Area safety'!$A$5:$A$18,0)),"n/a") -> 12 | AE22: =IFERROR(INDEX('Area safety'!$H$5:$H$18,MATCH($W22,'Area safety'!$A$5:$A$18,0)),"n/a") -> 251 | AF22: =IFERROR(INDEX('Area safety'!$I$5:$I$18,MATCH($W22,'Area safety'!$A$5:$A$18,0)),"n/a") -> 262 | AG22: =IFERROR(INDEX('Area safety'!$K$23:$K$41,MATCH($B22,'Area safety'!$A$23:$A$41,0)),"n/a") -> 0.083535109 | AH22: =IFERROR(INDEX('Area safety'!$J$23:$J$41,MATCH($B22,'Area safety'!$A$23:$A$41,0)),"n/a") -> 1
A23: Port Edward | B23: Banners Rest | C23: Available | D23: 570000 | E23: Apartment / Flat | F23: NOT STATED | G23: 2 | H23: 1 parking | I23: 84 | J23: 2295 | K23: 500 | L23: NOT STATED | M23: Yes | N23: Delightful two bedroom one bathroom apartment situated in a large well maintained security complex. | Pool, Garden | O23: Annette Mentz | P23: Chas Everitt KZN South Coast | Q23: NOT CAPTURED (reCAPTCHA) | R23: NOT AVAILABLE (needs phone) | S23: Agent profile | T23: Open listing | U23: 15 September 2023 | V23: 2026-10-08 | W23: =IFERROR(INDEX('Area safety'!$C$23:$C$41,MATCH($B23,'Area safety'!$A$23:$A$41,0)),"n/a") -> Port Edward | X23: =IFERROR(INDEX('Area safety'!$D$23:$D$41,MATCH($B23,'Area safety'!$A$23:$A$41,0)),"n/a") -> UNCONFIRMED - provisional (assumed Port Edward precinct) | Y23: =IFERROR(INDEX('Area safety'!$F$23:$F$41,MATCH($B23,'Area safety'!$A$23:$A$41,0)),"n/a") -> 571.8582 | Z23: =IFERROR(INDEX('Area safety'!$G$23:$G$41,MATCH($B23,'Area safety'!$A$23:$A$41,0)),"n/a") -> 596.91971 | AA23: =IFERROR(INDEX('Area safety'!$H$23:$H$41,MATCH($B23,'Area safety'!$A$23:$A$41,0)),"n/a") -> 27.339834 | AB23: =IFERROR(INDEX('Area safety'!$I$23:$I$41,MATCH($B23,'Area safety'!$A$23:$A$41,0)),"n/a") -> 2039.096 | AC23: =IFERROR(INDEX('Area safety'!$F$5:$F$18,MATCH($W23,'Area safety'!$A$5:$A$18,0)),"n/a") -> 895 | AD23: =IFERROR(INDEX('Area safety'!$G$5:$G$18,MATCH($W23,'Area safety'!$A$5:$A$18,0)),"n/a") -> 12 | AE23: =IFERROR(INDEX('Area safety'!$H$5:$H$18,MATCH($W23,'Area safety'!$A$5:$A$18,0)),"n/a") -> 251 | AF23: =IFERROR(INDEX('Area safety'!$I$5:$I$18,MATCH($W23,'Area safety'!$A$5:$A$18,0)),"n/a") -> 262 | AG23: =IFERROR(INDEX('Area safety'!$K$23:$K$41,MATCH($B23,'Area safety'!$A$23:$A$41,0)),"n/a") -> 0.083535109 | AH23: =IFERROR(INDEX('Area safety'!$J$23:$J$41,MATCH($B23,'Area safety'!$A$23:$A$41,0)),"n/a") -> 1
A24: Port Edward | B24: Banners Rest | C24: Available | D24: 580000 | E24: Apartment / Flat | F24: NOT STATED | G24: 2 | H24: 1 parking | I24: 91 | J24: 2900 | K24: 722 | L24: NOT STATED | M24: Yes | N24: If you've been dreaming of a secure, lock-up-and-go lifestyle surrounded by nature and exceptional recreational amenities, this could be the perfect p | Pool | O24: Tertia Sterley | P24: Property Port | Q24: NOT CAPTURED (reCAPTCHA) | R24: NOT AVAILABLE (needs phone) | S24: Agent profile | T24: Open listing | U24: 29 July 2026 | V24: 2026-10-08 | W24: =IFERROR(INDEX('Area safety'!$C$23:$C$41,MATCH($B24,'Area safety'!$A$23:$A$41,0)),"n/a") -> Port Edward | X24: =IFERROR(INDEX('Area safety'!$D$23:$D$41,MATCH($B24,'Area safety'!$A$23:$A$41,0)),"n/a") -> UNCONFIRMED - provisional (assumed Port Edward precinct) | Y24: =IFERROR(INDEX('Area safety'!$F$23:$F$41,MATCH($B24,'Area safety'!$A$23:$A$41,0)),"n/a") -> 571.8582 | Z24: =IFERROR(INDEX('Area safety'!$G$23:$G$41,MATCH($B24,'Area safety'!$A$23:$A$41,0)),"n/a") -> 596.91971 | AA24: =IFERROR(INDEX('Area safety'!$H$23:$H$41,MATCH($B24,'Area safety'!$A$23:$A$41,0)),"n/a") -> 27.339834 | AB24: =IFERROR(INDEX('Area safety'!$I$23:$I$41,MATCH($B24,'Area safety'!$A$23:$A$41,0)),"n/a") -> 2039.096 | AC24: =IFERROR(INDEX('Area safety'!$F$5:$F$18,MATCH($W24,'Area safety'!$A$5:$A$18,0)),"n/a") -> 895 | AD24: =IFERROR(INDEX('Area safety'!$G$5:$G$18,MATCH($W24,'Area safety'!$A$5:$A$18,0)),"n/a") -> 12 | AE24: =IFERROR(INDEX('Area safety'!$H$5:$H$18,MATCH($W24,'Area safety'!$A$5:$A$18,0)),"n/a") -> 251 | AF24: =IFERROR(INDEX('Area safety'!$I$5:$I$18,MATCH($W24,'Area safety'!$A$5:$A$18,0)),"n/a") -> 262 | AG24: =IFERROR(INDEX('Area safety'!$K$23:$K$41,MATCH($B24,'Area safety'!$A$23:$A$41,0)),"n/a") -> 0.083535109 | AH24: =IFERROR(INDEX('Area safety'!$J$23:$J$41,MATCH($B24,'Area safety'!$A$23:$A$41,0)),"n/a") -> 1
A25: Port Edward | B25: Banners Rest | C25: Available | D25: 580000 | E25: Apartment / Flat | F25: NOT STATED | G25: 2 | H25: NOT STATED | I25: 84 | J25: 3200 | K25: 644 | L25: NOT STATED | M25: NOT STATED | N25: Nestled in the tranquil Banners Rest area along the banks of the magnificent Umtamvuna River, this delightful unit at Eden Wilds offers the perfect op | Pool, Garden | O25: Brenda McNeil | P25: PdH Properties | Q25: NOT CAPTURED (reCAPTCHA) | R25: NOT AVAILABLE (needs phone) | S25: Agent profile | T25: Open listing | U25: 05 November 2025 | V25: 2026-10-08 | W25: =IFERROR(INDEX('Area safety'!$C$23:$C$41,MATCH($B25,'Area safety'!$A$23:$A$41,0)),"n/a") -> Port Edward | X25: =IFERROR(INDEX('Area safety'!$D$23:$D$41,MATCH($B25,'Area safety'!$A$23:$A$41,0)),"n/a") -> UNCONFIRMED - provisional (assumed Port Edward precinct) | Y25: =IFERROR(INDEX('Area safety'!$F$23:$F$41,MATCH($B25,'Area safety'!$A$23:$A$41,0)),"n/a") -> 571.8582 | Z25: =IFERROR(INDEX('Area safety'!$G$23:$G$41,MATCH($B25,'Area safety'!$A$23:$A$41,0)),"n/a") -> 596.91971 | AA25: =IFERROR(INDEX('Area safety'!$H$23:$H$41,MATCH($B25,'Area safety'!$A$23:$A$41,0)),"n/a") -> 27.339834 | AB25: =IFERROR(INDEX('Area safety'!$I$23:$I$41,MATCH($B25,'Area safety'!$A$23:$A$41,0)),"n/a") -> 2039.096 | AC25: =IFERROR(INDEX('Area safety'!$F$5:$F$18,MATCH($W25,'Area safety'!$A$5:$A$18,0)),"n/a") -> 895 | AD25: =IFERROR(INDEX('Area safety'!$G$5:$G$18,MATCH($W25,'Area safety'!$A$5:$A$18,0)),"n/a") -> 12 | AE25: =IFERROR(INDEX('Area safety'!$H$5:$H$18,MATCH($W25,'Area safety'!$A$5:$A$18,0)),"n/a") -> 251 | AF25: =IFERROR(INDEX('Area safety'!$I$5:$I$18,MATCH($W25,'Area safety'!$A$5:$A$18,0)),"n/a") -> 262 | AG25: =IFERROR(INDEX('Area safety'!$K$23:$K$41,MATCH($B25,'Area safety'!$A$23:$A$41,0)),"n/a") -> 0.083535109 | AH25: =IFERROR(INDEX('Area safety'!$J$23:$J$41,MATCH($B25,'Area safety'!$A$23:$A$41,0)),"n/a") -> 1
A26: Port Edward | B26: Banners Rest | C26: Available | D26: 595000 | E26: Apartment / Flat | F26: NOT STATED | G26: 2 | H26: 1 garage | I26: 91 | J26: NOT STATED | K26: NOT STATED | L26: No | M26: NOT STATED | N26: SOLE MANDATE This lovely remarkable unit is situated in an immaculate well maintained block just minutes away from the beach close to schools, shoppin | No Pets Allowed, Pool | O26: Rene Houghton | P26: Property.CoZa - Communities | Q26: NOT CAPTURED (reCAPTCHA) | R26: NOT AVAILABLE (needs phone) | S26: Agent profile | T26: Open listing | U26: 13 July 2025 | V26: 2026-10-08 | W26: =IFERROR(INDEX('Area safety'!$C$23:$C$41,MATCH($B26,'Area safety'!$A$23:$A$41,0)),"n/a") -> Port Edward | X26: =IFERROR(INDEX('Area safety'!$D$23:$D$41,MATCH($B26,'Area safety'!$A$23:$A$41,0)),"n/a") -> UNCONFIRMED - provisional (assumed Port Edward precinct) | Y26: =IFERROR(INDEX('Area safety'!$F$23:$F$41,MATCH($B26,'Area safety'!$A$23:$A$41,0)),"n/a") -> 571.8582 | Z26: =IFERROR(INDEX('Area safety'!$G$23:$G$41,MATCH($B26,'Area safety'!$A$23:$A$41,0)),"n/a") -> 596.91971 | AA26: =IFERROR(INDEX('Area safety'!$H$23:$H$41,MATCH($B26,'Area safety'!$A$23:$A$41,0)),"n/a") -> 27.339834 | AB26: =IFERROR(INDEX('Area safety'!$I$23:$I$41,MATCH($B26,'Area safety'!$A$23:$A$41,0)),"n/a") -> 2039.096 | AC26: =IFERROR(INDEX('Area safety'!$F$5:$F$18,MATCH($W26,'Area safety'!$A$5:$A$18,0)),"n/a") -> 895 | AD26: =IFERROR(INDEX('Area safety'!$G$5:$G$18,MATCH($W26,'Area safety'!$A$5:$A$18,0)),"n/a") -> 12 | AE26: =IFERROR(INDEX('Area safety'!$H$5:$H$18,MATCH($W26,'Area safety'!$A$5:$A$18,0)),"n/a") -> 251 | AF26: =IFERROR(INDEX('Area safety'!$I$5:$I$18,MATCH($W26,'Area safety'!$A$5:$A$18,0)),"n/a") -> 262 | AG26: =IFERROR(INDEX('Area safety'!$K$23:$K$41,MATCH($B26,'Area safety'!$A$23:$A$41,0)),"n/a") -> 0.083535109 | AH26: =IFERROR(INDEX('Area safety'!$J$23:$J$41,MATCH($B26,'Area safety'!$A$23:$A$41,0)),"n/a") -> 1
A27: Port Edward | B27: Banners Rest | C27: Available | D27: 599000 | E27: Apartment / Flat | F27: NOT STATED | G27: 2 | H27: NOT STATED | I27: 84 | J27: 1977 | K27: 580 | L27: No | M27: Yes | N27: This Complex is an inviting Lush Tropical PARADISE, surrounded by picturesque mountain views and the Umthumvuna river. | No Pets Allowed, Pool | O27: Stephanie Harries | P27: Wakefields Estate Agents Shelly Beach | Q27: NOT CAPTURED (reCAPTCHA) | R27: NOT AVAILABLE (needs phone) | S27: Agent profile | T27: Open listing | U27: 13 January 2020 | V27: 2026-10-08 | W27: =IFERROR(INDEX('Area safety'!$C$23:$C$41,MATCH($B27,'Area safety'!$A$23:$A$41,0)),"n/a") -> Port Edward | X27: =IFERROR(INDEX('Area safety'!$D$23:$D$41,MATCH($B27,'Area safety'!$A$23:$A$41,0)),"n/a") -> UNCONFIRMED - provisional (assumed Port Edward precinct) | Y27: =IFERROR(INDEX('Area safety'!$F$23:$F$41,MATCH($B27,'Area safety'!$A$23:$A$41,0)),"n/a") -> 571.8582 | Z27: =IFERROR(INDEX('Area safety'!$G$23:$G$41,MATCH($B27,'Area safety'!$A$23:$A$41,0)),"n/a") -> 596.91971 | AA27: =IFERROR(INDEX('Area safety'!$H$23:$H$41,MATCH($B27,'Area safety'!$A$23:$A$41,0)),"n/a") -> 27.339834 | AB27: =IFERROR(INDEX('Area safety'!$I$23:$I$41,MATCH($B27,'Area safety'!$A$23:$A$41,0)),"n/a") -> 2039.096 | AC27: =IFERROR(INDEX('Area safety'!$F$5:$F$18,MATCH($W27,'Area safety'!$A$5:$A$18,0)),"n/a") -> 895 | AD27: =IFERROR(INDEX('Area safety'!$G$5:$G$18,MATCH($W27,'Area safety'!$A$5:$A$18,0)),"n/a") -> 12 | AE27: =IFERROR(INDEX('Area safety'!$H$5:$H$18,MATCH($W27,'Area safety'!$A$5:$A$18,0)),"n/a") -> 251 | AF27: =IFERROR(INDEX('Area safety'!$I$5:$I$18,MATCH($W27,'Area safety'!$A$5:$A$18,0)),"n/a") -> 262 | AG27: =IFERROR(INDEX('Area safety'!$K$23:$K$41,MATCH($B27,'Area safety'!$A$23:$A$41,0)),"n/a") -> 0.083535109 | AH27: =IFERROR(INDEX('Area safety'!$J$23:$J$41,MATCH($B27,'Area safety'!$A$23:$A$41,0)),"n/a") -> 1
A28: Port Edward | B28: Banners Rest | C28: Available | D28: 600000 | E28: Apartment / Flat | F28: NOT STATED | G28: 2 | H28: 1 garage | I28: 86 | J28: 1650 | K28: 629 | L28: Yes | M28: Optional | N28: Words and photos cannot fully capture the breathtaking views from this stunning upstairs 2-bedroom, 2-bathroom unit at Eden Crest – 24 Maurice Road, B | Pet Friendly, Pool, Garden | O28: Brenda McNeil | P28: PdH Properties | Q28: NOT CAPTURED (reCAPTCHA) | R28: NOT AVAILABLE (needs phone) | S28: Agent profile | T28: Open listing | U28: 22 February 2025 | V28: 2026-10-08 | W28: =IFERROR(INDEX('Area safety'!$C$23:$C$41,MATCH($B28,'Area safety'!$A$23:$A$41,0)),"n/a") -> Port Edward | X28: =IFERROR(INDEX('Area safety'!$D$23:$D$41,MATCH($B28,'Area safety'!$A$23:$A$41,0)),"n/a") -> UNCONFIRMED - provisional (assumed Port Edward precinct) | Y28: =IFERROR(INDEX('Area safety'!$F$23:$F$41,MATCH($B28,'Area safety'!$A$23:$A$41,0)),"n/a") -> 571.8582 | Z28: =IFERROR(INDEX('Area safety'!$G$23:$G$41,MATCH($B28,'Area safety'!$A$23:$A$41,0)),"n/a") -> 596.91971 | AA28: =IFERROR(INDEX('Area safety'!$H$23:$H$41,MATCH($B28,'Area safety'!$A$23:$A$41,0)),"n/a") -> 27.339834 | AB28: =IFERROR(INDEX('Area safety'!$I$23:$I$41,MATCH($B28,'Area safety'!$A$23:$A$41,0)),"n/a") -> 2039.096 | AC28: =IFERROR(INDEX('Area safety'!$F$5:$F$18,MATCH($W28,'Area safety'!$A$5:$A$18,0)),"n/a") -> 895 | AD28: =IFERROR(INDEX('Area safety'!$G$5:$G$18,MATCH($W28,'Area safety'!$A$5:$A$18,0)),"n/a") -> 12 | AE28: =IFERROR(INDEX('Area safety'!$H$5:$H$18,MATCH($W28,'Area safety'!$A$5:$A$18,0)),"n/a") -> 251 | AF28: =IFERROR(INDEX('Area safety'!$I$5:$I$18,MATCH($W28,'Area safety'!$A$5:$A$18,0)),"n/a") -> 262 | AG28: =IFERROR(INDEX('Area safety'!$K$23:$K$41,MATCH($B28,'Area safety'!$A$23:$A$41,0)),"n/a") -> 0.083535109 | AH28: =IFERROR(INDEX('Area safety'!$J$23:$J$41,MATCH($B28,'Area safety'!$A$23:$A$41,0)),"n/a") -> 1
A29: Port Edward | B29: Banners Rest | C29: Available | D29: 600000 | E29: Apartment / Flat | F29: NOT STATED | G29: 2 | H29: 1 garage | I29: 97 | J29: 680 | K29: 1600 | L29: Yes | M29: NOT STATED | N29: Nestled in the heart of Banners Rest, this charming 2-bedroom, 2-bathroom apartment offers the perfect blend of comfort, convenience, and natural beauty. | Pet Friendly, Pool | O29: Stephanie Harries | P29: Wakefields Estate Agents Shelly Beach | Q29: NOT CAPTURED (reCAPTCHA) | R29: NOT AVAILABLE (needs phone) | S29: Agent profile | T29: Open listing | U29: 02 April 2025 | V29: 2026-10-08 | W29: =IFERROR(INDEX('Area safety'!$C$23:$C$41,MATCH($B29,'Area safety'!$A$23:$A$41,0)),"n/a") -> Port Edward | X29: =IFERROR(INDEX('Area safety'!$D$23:$D$41,MATCH($B29,'Area safety'!$A$23:$A$41,0)),"n/a") -> UNCONFIRMED - provisional (assumed Port Edward precinct) | Y29: =IFERROR(INDEX('Area safety'!$F$23:$F$41,MATCH($B29,'Area safety'!$A$23:$A$41,0)),"n/a") -> 571.8582 | Z29: =IFERROR(INDEX('Area safety'!$G$23:$G$41,MATCH($B29,'Area safety'!$A$23:$A$41,0)),"n/a") -> 596.91971 | AA29: =IFERROR(INDEX('Area safety'!$H$23:$H$41,MATCH($B29,'Area safety'!$A$23:$A$41,0)),"n/a") -> 27.339834 | AB29: =IFERROR(INDEX('Area safety'!$I$23:$I$41,MATCH($B29,'Area safety'!$A$23:$A$41,0)),"n/a") -> 2039.096 | AC29: =IFERROR(INDEX('Area safety'!$F$5:$F$18,MATCH($W29,'Area safety'!$A$5:$A$18,0)),"n/a") -> 895 | AD29: =IFERROR(INDEX('Area safety'!$G$5:$G$18,MATCH($W29,'Area safety'!$A$5:$A$18,0)),"n/a") -> 12 | AE29: =IFERROR(INDEX('Area safety'!$H$5:$H$18,MATCH($W29,'Area safety'!$A$5:$A$18,0)),"n/a") -> 251 | AF29: =IFERROR(INDEX('Area safety'!$I$5:$I$18,MATCH($W29,'Area safety'!$A$5:$A$18,0)),"n/a") -> 262 | AG29: =IFERROR(INDEX('Area safety'!$K$23:$K$41,MATCH($B29,'Area safety'!$A$23:$A$41,0)),"n/a") -> 0.083535109 | AH29: =IFERROR(INDEX('Area safety'!$J$23:$J$41,MATCH($B29,'Area safety'!$A$23:$A$41,0)),"n/a") -> 1
A30: Port Edward | B30: Banners Rest | C30: Available | D30: 620000 | E30: Apartment / Flat | F30: NOT STATED | G30: 2 | H30: NOT STATED | I30: 84 | J30: 2200 | K30: 630 | L30: No | M30: Yes | N30: This is a beautiful well maintained 2-bedroom unit on the Umtumvuna River. | No Pets Allowed, Pool, Garden | O30: Belinda Jamieson | P30: Seeff Hibiscus Coast | Q30: NOT CAPTURED (reCAPTCHA) | R30: NOT AVAILABLE (needs phone) | S30: Agent profile | T30: Open listing | U30: 11 May 2022 | V30: 2026-10-08 | W30: =IFERROR(INDEX('Area safety'!$C$23:$C$41,MATCH($B30,'Area safety'!$A$23:$A$41,0)),"n/a") -> Port Edward | X30: =IFERROR(INDEX('Area safety'!$D$23:$D$41,MATCH($B30,'Area safety'!$A$23:$A$41,0)),"n/a") -> UNCONFIRMED - provisional (assumed Port Edward precinct) | Y30: =IFERROR(INDEX('Area safety'!$F$23:$F$41,MATCH($B30,'Area safety'!$A$23:$A$41,0)),"n/a") -> 571.8582 | Z30: =IFERROR(INDEX('Area safety'!$G$23:$G$41,MATCH($B30,'Area safety'!$A$23:$A$41,0)),"n/a") -> 596.91971 | AA30: =IFERROR(INDEX('Area safety'!$H$23:$H$41,MATCH($B30,'Area safety'!$A$23:$A$41,0)),"n/a") -> 27.339834 | AB30: =IFERROR(INDEX('Area safety'!$I$23:$I$41,MATCH($B30,'Area safety'!$A$23:$A$41,0)),"n/a") -> 2039.096 | AC30: =IFERROR(INDEX('Area safety'!$F$5:$F$18,MATCH($W30,'Area safety'!$A$5:$A$18,0)),"n/a") -> 895 | AD30: =IFERROR(INDEX('Area safety'!$G$5:$G$18,MATCH($W30,'Area safety'!$A$5:$A$18,0)),"n/a") -> 12 | AE30: =IFERROR(INDEX('Area safety'!$H$5:$H$18,MATCH($W30,'Area safety'!$A$5:$A$18,0)),"n/a") -> 251 | AF30: =IFERROR(INDEX('Area safety'!$I$5:$I$18,MATCH($W30,'Area safety'!$A$5:$A$18,0)),"n/a") -> 262 | AG30: =IFERROR(INDEX('Area safety'!$K$23:$K$41,MATCH($B30,'Area safety'!$A$23:$A$41,0)),"n/a") -> 0.083535109 | AH30: =IFERROR(INDEX('Area safety'!$J$23:$J$41,MATCH($B30,'Area safety'!$A$23:$A$41,0)),"n/a") -> 1
A31: Port Edward | B31: Banners Rest | C31: Available | D31: 630000 | E31: Apartment / Flat | F31: NOT STATED | G31: 2 | H31: 1 parking | I31: 84 | J31: 2197 | K31: 634 | L31: No | M31: Yes | N31: This Complex is idyllic setting. | No Pets Allowed, Pool | O31: Stephanie Harries | P31: Wakefields Estate Agents Shelly Beach | Q31: NOT CAPTURED (reCAPTCHA) | R31: NOT AVAILABLE (needs phone) | S31: Agent profile | T31: Open listing | U31: 20 September 2019 | V31: 2026-10-08 | W31: =IFERROR(INDEX('Area safety'!$C$23:$C$41,MATCH($B31,'Area safety'!$A$23:$A$41,0)),"n/a") -> Port Edward | X31: =IFERROR(INDEX('Area safety'!$D$23:$D$41,MATCH($B31,'Area safety'!$A$23:$A$41,0)),"n/a") -> UNCONFIRMED - provisional (assumed Port Edward precinct) | Y31: =IFERROR(INDEX('Area safety'!$F$23:$F$41,MATCH($B31,'Area safety'!$A$23:$A$41,0)),"n/a") -> 571.8582 | Z31: =IFERROR(INDEX('Area safety'!$G$23:$G$41,MATCH($B31,'Area safety'!$A$23:$A$41,0)),"n/a") -> 596.91971 | AA31: =IFERROR(INDEX('Area safety'!$H$23:$H$41,MATCH($B31,'Area safety'!$A$23:$A$41,0)),"n/a") -> 27.339834 | AB31: =IFERROR(INDEX('Area safety'!$I$23:$I$41,MATCH($B31,'Area safety'!$A$23:$A$41,0)),"n/a") -> 2039.096 | AC31: =IFERROR(INDEX('Area safety'!$F$5:$F$18,MATCH($W31,'Area safety'!$A$5:$A$18,0)),"n/a") -> 895 | AD31: =IFERROR(INDEX('Area safety'!$G$5:$G$18,MATCH($W31,'Area safety'!$A$5:$A$18,0)),"n/a") -> 12 | AE31: =IFERROR(INDEX('Area safety'!$H$5:$H$18,MATCH($W31,'Area safety'!$A$5:$A$18,0)),"n/a") -> 251 | AF31: =IFERROR(INDEX('Area safety'!$I$5:$I$18,MATCH($W31,'Area safety'!$A$5:$A$18,0)),"n/a") -> 262 | AG31: =IFERROR(INDEX('Area safety'!$K$23:$K$41,MATCH($B31,'Area safety'!$A$23:$A$41,0)),"n/a") -> 0.083535109 | AH31: =IFERROR(INDEX('Area safety'!$J$23:$J$41,MATCH($B31,'Area safety'!$A$23:$A$41,0)),"n/a") -> 1
A32: Port Edward | B32: Banners Rest | C32: Available | D32: 650000 | E32: Apartment / Flat | F32: NOT STATED | G32: 2 | H32: 1 parking | I32: 84 | J32: 2500 | K32: 650 | L32: No | M32: NOT STATED | N32: Discover the perfect blend of comfort, nature and secure estate living in this beautiful two-bedroom apartment in the sought-after Eden Wilds The spac | No Pets Allowed, Pool, Garden | O32: Judy Rademeyer | P32: Real Estate Services | Q32: NOT CAPTURED (reCAPTCHA) | R32: NOT AVAILABLE (needs phone) | S32: Agent profile | T32: Open listing | U32: 16 August 2026 | V32: 2026-10-08 | W32: =IFERROR(INDEX('Area safety'!$C$23:$C$41,MATCH($B32,'Area safety'!$A$23:$A$41,0)),"n/a") -> Port Edward | X32: =IFERROR(INDEX('Area safety'!$D$23:$D$41,MATCH($B32,'Area safety'!$A$23:$A$41,0)),"n/a") -> UNCONFIRMED - provisional (assumed Port Edward precinct) | Y32: =IFERROR(INDEX('Area safety'!$F$23:$F$41,MATCH($B32,'Area safety'!$A$23:$A$41,0)),"n/a") -> 571.8582 | Z32: =IFERROR(INDEX('Area safety'!$G$23:$G$41,MATCH($B32,'Area safety'!$A$23:$A$41,0)),"n/a") -> 596.91971 | AA32: =IFERROR(INDEX('Area safety'!$H$23:$H$41,MATCH($B32,'Area safety'!$A$23:$A$41,0)),"n/a") -> 27.339834 | AB32: =IFERROR(INDEX('Area safety'!$I$23:$I$41,MATCH($B32,'Area safety'!$A$23:$A$41,0)),"n/a") -> 2039.096 | AC32: =IFERROR(INDEX('Area safety'!$F$5:$F$18,MATCH($W32,'Area safety'!$A$5:$A$18,0)),"n/a") -> 895 | AD32: =IFERROR(INDEX('Area safety'!$G$5:$G$18,MATCH($W32,'Area safety'!$A$5:$A$18,0)),"n/a") -> 12 | AE32: =IFERROR(INDEX('Area safety'!$H$5:$H$18,MATCH($W32,'Area safety'!$A$5:$A$18,0)),"n/a") -> 251 | AF32: =IFERROR(INDEX('Area safety'!$I$5:$I$18,MATCH($W32,'Area safety'!$A$5:$A$18,0)),"n/a") -> 262 | AG32: =IFERROR(INDEX('Area safety'!$K$23:$K$41,MATCH($B32,'Area safety'!$A$23:$A$41,0)),"n/a") -> 0.083535109 | AH32: =IFERROR(INDEX('Area safety'!$J$23:$J$41,MATCH($B32,'Area safety'!$A$23:$A$41,0)),"n/a") -> 1
A33: Port Edward | B33: Banners Rest | C33: Available | D33: 650000 | E33: Apartment / Flat | F33: NOT STATED | G33: 2 | H33: 1 parking | I33: 84 | J33: 3500 | K33: 678 | L33: No | M33: NOT STATED | N33: Imagine stepping out of your open-plan lounge onto a verandah that looks out onto lush greenery, where the only sounds you hear are the gentle rustle | No Pets Allowed, Pool | O33: Tina Sykes | P33: Real Estate Services | Q33: NOT CAPTURED (reCAPTCHA) | R33: NOT AVAILABLE (needs phone) | S33: Agent profile | T33: Open listing | U33: 19 June 2026 | V33: 2026-10-08 | W33: =IFERROR(INDEX('Area safety'!$C$23:$C$41,MATCH($B33,'Area safety'!$A$23:$A$41,0)),"n/a") -> Port Edward | X33: =IFERROR(INDEX('Area safety'!$D$23:$D$41,MATCH($B33,'Area safety'!$A$23:$A$41,0)),"n/a") -> UNCONFIRMED - provisional (assumed Port Edward precinct) | Y33: =IFERROR(INDEX('Area safety'!$F$23:$F$41,MATCH($B33,'Area safety'!$A$23:$A$41,0)),"n/a") -> 571.8582 | Z33: =IFERROR(INDEX('Area safety'!$G$23:$G$41,MATCH($B33,'Area safety'!$A$23:$A$41,0)),"n/a") -> 596.91971 | AA33: =IFERROR(INDEX('Area safety'!$H$23:$H$41,MATCH($B33,'Area safety'!$A$23:$A$41,0)),"n/a") -> 27.339834 | AB33: =IFERROR(INDEX('Area safety'!$I$23:$I$41,MATCH($B33,'Area safety'!$A$23:$A$41,0)),"n/a") -> 2039.096 | AC33: =IFERROR(INDEX('Area safety'!$F$5:$F$18,MATCH($W33,'Area safety'!$A$5:$A$18,0)),"n/a") -> 895 | AD33: =IFERROR(INDEX('Area safety'!$G$5:$G$18,MATCH($W33,'Area safety'!$A$5:$A$18,0)),"n/a") -> 12 | AE33: =IFERROR(INDEX('Area safety'!$H$5:$H$18,MATCH($W33,'Area safety'!$A$5:$A$18,0)),"n/a") -> 251 | AF33: =IFERROR(INDEX('Area safety'!$I$5:$I$18,MATCH($W33,'Area safety'!$A$5:$A$18,0)),"n/a") -> 262 | AG33: =IFERROR(INDEX('Area safety'!$K$23:$K$41,MATCH($B33,'Area safety'!$A$23:$A$41,0)),"n/a") -> 0.083535109 | AH33: =IFERROR(INDEX('Area safety'!$J$23:$J$41,MATCH($B33,'Area safety'!$A$23:$A$41,0)),"n/a") -> 1
A34: Port Edward | B34: Banners Rest | C34: Available | D34: 650000 | E34: Apartment / Flat | F34: NOT STATED | G34: 2 | H34: NOT STATED | I34: 84 | J34: 2197 | K34: 634 | L34: No | M34: Yes | N34: Set in the Umthamvuna gorge and river in the Banners Rest area and on the Umthamvuna river. | No Pets Allowed, Pool | O34: Stephanie Harries | P34: Wakefields Estate Agents Shelly Beach | Q34: NOT CAPTURED (reCAPTCHA) | R34: NOT AVAILABLE (needs phone) | S34: Agent profile | T34: Open listing | U34: 10 September 2020 | V34: 2026-10-08 | W34: =IFERROR(INDEX('Area safety'!$C$23:$C$41,MATCH($B34,'Area safety'!$A$23:$A$41,0)),"n/a") -> Port Edward | X34: =IFERROR(INDEX('Area safety'!$D$23:$D$41,MATCH($B34,'Area safety'!$A$23:$A$41,0)),"n/a") -> UNCONFIRMED - provisional (assumed Port Edward precinct) | Y34: =IFERROR(INDEX('Area safety'!$F$23:$F$41,MATCH($B34,'Area safety'!$A$23:$A$41,0)),"n/a") -> 571.8582 | Z34: =IFERROR(INDEX('Area safety'!$G$23:$G$41,MATCH($B34,'Area safety'!$A$23:$A$41,0)),"n/a") -> 596.91971 | AA34: =IFERROR(INDEX('Area safety'!$H$23:$H$41,MATCH($B34,'Area safety'!$A$23:$A$41,0)),"n/a") -> 27.339834 | AB34: =IFERROR(INDEX('Area safety'!$I$23:$I$41,MATCH($B34,'Area safety'!$A$23:$A$41,0)),"n/a") -> 2039.096 | AC34: =IFERROR(INDEX('Area safety'!$F$5:$F$18,MATCH($W34,'Area safety'!$A$5:$A$18,0)),"n/a") -> 895 | AD34: =IFERROR(INDEX('Area safety'!$G$5:$G$18,MATCH($W34,'Area safety'!$A$5:$A$18,0)),"n/a") -> 12 | AE34: =IFERROR(INDEX('Area safety'!$H$5:$H$18,MATCH($W34,'Area safety'!$A$5:$A$18,0)),"n/a") -> 251 | AF34: =IFERROR(INDEX('Area safety'!$I$5:$I$18,MATCH($W34,'Area safety'!$A$5:$A$18,0)),"n/a") -> 262 | AG34: =IFERROR(INDEX('Area safety'!$K$23:$K$41,MATCH($B34,'Area safety'!$A$23:$A$41,0)),"n/a") -> 0.083535109 | AH34: =IFERROR(INDEX('Area safety'!$J$23:$J$41,MATCH($B34,'Area safety'!$A$23:$A$41,0)),"n/a") -> 1
A35: Port Edward | B35: Banners Rest | C35: Available | D35: 655000 | E35: Apartment / Flat | F35: NOT STATED | G35: 2 | H35: 1 garage | I35: NOT STATED | J35: 1680 | K35: 686 | L35: NOT STATED | M35: NOT STATED | N35: This sought after Complex offers Peace and Tranquility unsurpassed, overlooking the Umtamvuna river gorge. | Pool | O35: NOT STATED | P35: Realty1 Munster | Q35: NOT CAPTURED (reCAPTCHA) | R35: NOT AVAILABLE (needs phone) | S35: NOT STATED | T35: Open listing | U35: 24 February 2024 | V35: 2026-10-08 | W35: =IFERROR(INDEX('Area safety'!$C$23:$C$41,MATCH($B35,'Area safety'!$A$23:$A$41,0)),"n/a") -> Port Edward | X35: =IFERROR(INDEX('Area safety'!$D$23:$D$41,MATCH($B35,'Area safety'!$A$23:$A$41,0)),"n/a") -> UNCONFIRMED - provisional (assumed Port Edward precinct) | Y35: =IFERROR(INDEX('Area safety'!$F$23:$F$41,MATCH($B35,'Area safety'!$A$23:$A$41,0)),"n/a") -> 571.8582 | Z35: =IFERROR(INDEX('Area safety'!$G$23:$G$41,MATCH($B35,'Area safety'!$A$23:$A$41,0)),"n/a") -> 596.91971 | AA35: =IFERROR(INDEX('Area safety'!$H$23:$H$41,MATCH($B35,'Area safety'!$A$23:$A$41,0)),"n/a") -> 27.339834 | AB35: =IFERROR(INDEX('Area safety'!$I$23:$I$41,MATCH($B35,'Area safety'!$A$23:$A$41,0)),"n/a") -> 2039.096 | AC35: =IFERROR(INDEX('Area safety'!$F$5:$F$18,MATCH($W35,'Area safety'!$A$5:$A$18,0)),"n/a") -> 895 | AD35: =IFERROR(INDEX('Area safety'!$G$5:$G$18,MATCH($W35,'Area safety'!$A$5:$A$18,0)),"n/a") -> 12 | AE35: =IFERROR(INDEX('Area safety'!$H$5:$H$18,MATCH($W35,'Area safety'!$A$5:$A$18,0)),"n/a") -> 251 | AF35: =IFERROR(INDEX('Area safety'!$I$5:$I$18,MATCH($W35,'Area safety'!$A$5:$A$18,0)),"n/a") -> 262 | AG35: =IFERROR(INDEX('Area safety'!$K$23:$K$41,MATCH($B35,'Area safety'!$A$23:$A$41,0)),"n/a") -> 0.083535109 | AH35: =IFERROR(INDEX('Area safety'!$J$23:$J$41,MATCH($B35,'Area safety'!$A$23:$A$41,0)),"n/a") -> 1
A36: Port Edward | B36: Banners Rest | C36: Available | D36: 668475 | E36: Apartment / Flat | F36: NOT STATED | G36: 2 | H36: 1 parking | I36: 91 | J36: 1977 | K36: 580 | L36: No | M36: Yes | N36: This Resort is situated in Banners Rest stone's throw away from the idyllic peaceful village of Port Edward offering the beautiful Silver Beach and Splash Rock. | No Pets Allowed, Pool | O36: Stephanie Harries | P36: Wakefields Estate Agents Shelly Beach | Q36: NOT CAPTURED (reCAPTCHA) | R36: NOT AVAILABLE (needs phone) | S36: Agent profile | T36: Open listing | U36: 26 September 2019 | V36: 2026-10-08 | W36: =IFERROR(INDEX('Area safety'!$C$23:$C$41,MATCH($B36,'Area safety'!$A$23:$A$41,0)),"n/a") -> Port Edward | X36: =IFERROR(INDEX('Area safety'!$D$23:$D$41,MATCH($B36,'Area safety'!$A$23:$A$41,0)),"n/a") -> UNCONFIRMED - provisional (assumed Port Edward precinct) | Y36: =IFERROR(INDEX('Area safety'!$F$23:$F$41,MATCH($B36,'Area safety'!$A$23:$A$41,0)),"n/a") -> 571.8582 | Z36: =IFERROR(INDEX('Area safety'!$G$23:$G$41,MATCH($B36,'Area safety'!$A$23:$A$41,0)),"n/a") -> 596.91971 | AA36: =IFERROR(INDEX('Area safety'!$H$23:$H$41,MATCH($B36,'Area safety'!$A$23:$A$41,0)),"n/a") -> 27.339834 | AB36: =IFERROR(INDEX('Area safety'!$I$23:$I$41,MATCH($B36,'Area safety'!$A$23:$A$41,0)),"n/a") -> 2039.096 | AC36: =IFERROR(INDEX('Area safety'!$F$5:$F$18,MATCH($W36,'Area safety'!$A$5:$A$18,0)),"n/a") -> 895 | AD36: =IFERROR(INDEX('Area safety'!$G$5:$G$18,MATCH($W36,'Area safety'!$A$5:$A$18,0)),"n/a") -> 12 | AE36: =IFERROR(INDEX('Area safety'!$H$5:$H$18,MATCH($W36,'Area safety'!$A$5:$A$18,0)),"n/a") -> 251 | AF36: =IFERROR(INDEX('Area safety'!$I$5:$I$18,MATCH($W36,'Area safety'!$A$5:$A$18,0)),"n/a") -> 262 | AG36: =IFERROR(INDEX('Area safety'!$K$23:$K$41,MATCH($B36,'Area safety'!$A$23:$A$41,0)),"n/a") -> 0.083535109 | AH36: =IFERROR(INDEX('Area safety'!$J$23:$J$41,MATCH($B36,'Area safety'!$A$23:$A$41,0)),"n/a") -> 1
A37: Port Edward | B37: Banners Rest | C37: Available | D37: 668475 | E37: Apartment / Flat | F37: NOT STATED | G37: 2 | H37: 1 parking | I37: 84 | J37: 1977 | K37: 580 | L37: No | M37: Yes | N37: This unit is different The main bedroom leads of the passage not out of the lounge. | No Pets Allowed, Pool | O37: Stephanie Harries | P37: Wakefields Estate Agents Shelly Beach | Q37: NOT CAPTURED (reCAPTCHA) | R37: NOT AVAILABLE (needs phone) | S37: Agent profile | T37: Open listing | U37: 20 September 2019 | V37: 2026-10-08 | W37: =IFERROR(INDEX('Area safety'!$C$23:$C$41,MATCH($B37,'Area safety'!$A$23:$A$41,0)),"n/a") -> Port Edward | X37: =IFERROR(INDEX('Area safety'!$D$23:$D$41,MATCH($B37,'Area safety'!$A$23:$A$41,0)),"n/a") -> UNCONFIRMED - provisional (assumed Port Edward precinct) | Y37: =IFERROR(INDEX('Area safety'!$F$23:$F$41,MATCH($B37,'Area safety'!$A$23:$A$41,0)),"n/a") -> 571.8582 | Z37: =IFERROR(INDEX('Area safety'!$G$23:$G$41,MATCH($B37,'Area safety'!$A$23:$A$41,0)),"n/a") -> 596.91971 | AA37: =IFERROR(INDEX('Area safety'!$H$23:$H$41,MATCH($B37,'Area safety'!$A$23:$A$41,0)),"n/a") -> 27.339834 | AB37: =IFERROR(INDEX('Area safety'!$I$23:$I$41,MATCH($B37,'Area safety'!$A$23:$A$41,0)),"n/a") -> 2039.096 | AC37: =IFERROR(INDEX('Area safety'!$F$5:$F$18,MATCH($W37,'Area safety'!$A$5:$A$18,0)),"n/a") -> 895 | AD37: =IFERROR(INDEX('Area safety'!$G$5:$G$18,MATCH($W37,'Area safety'!$A$5:$A$18,0)),"n/a") -> 12 | AE37: =IFERROR(INDEX('Area safety'!$H$5:$H$18,MATCH($W37,'Area safety'!$A$5:$A$18,0)),"n/a") -> 251 | AF37: =IFERROR(INDEX('Area safety'!$I$5:$I$18,MATCH($W37,'Area safety'!$A$5:$A$18,0)),"n/a") -> 262 | AG37: =IFERROR(INDEX('Area safety'!$K$23:$K$41,MATCH($B37,'Area safety'!$A$23:$A$41,0)),"n/a") -> 0.083535109 | AH37: =IFERROR(INDEX('Area safety'!$J$23:$J$41,MATCH($B37,'Area safety'!$A$23:$A$41,0)),"n/a") -> 1
A38: Port Edward | B38: Banners Rest | C38: Available | D38: 670000 | E38: Apartment / Flat | F38: NOT STATED | G38: 2 | H38: NOT STATED | I38: 91 | J38: NOT STATED | K38: NOT STATED | L38: NOT STATED | M38: NOT STATED | N38: This apartment is a rare find—perfect as a tranquil permanent residence or an ideal holiday investment opportunity. | Pool | O38: Dennis Hammerschlag | P38: Pam Golding Properties - Port Edward | Q38: NOT CAPTURED (reCAPTCHA) | R38: NOT AVAILABLE (needs phone) | S38: Agent profile | T38: Open listing | U38: 31 May 2025 | V38: 2026-10-08 | W38: =IFERROR(INDEX('Area safety'!$C$23:$C$41,MATCH($B38,'Area safety'!$A$23:$A$41,0)),"n/a") -> Port Edward | X38: =IFERROR(INDEX('Area safety'!$D$23:$D$41,MATCH($B38,'Area safety'!$A$23:$A$41,0)),"n/a") -> UNCONFIRMED - provisional (assumed Port Edward precinct) | Y38: =IFERROR(INDEX('Area safety'!$F$23:$F$41,MATCH($B38,'Area safety'!$A$23:$A$41,0)),"n/a") -> 571.8582 | Z38: =IFERROR(INDEX('Area safety'!$G$23:$G$41,MATCH($B38,'Area safety'!$A$23:$A$41,0)),"n/a") -> 596.91971 | AA38: =IFERROR(INDEX('Area safety'!$H$23:$H$41,MATCH($B38,'Area safety'!$A$23:$A$41,0)),"n/a") -> 27.339834 | AB38: =IFERROR(INDEX('Area safety'!$I$23:$I$41,MATCH($B38,'Area safety'!$A$23:$A$41,0)),"n/a") -> 2039.096 | AC38: =IFERROR(INDEX('Area safety'!$F$5:$F$18,MATCH($W38,'Area safety'!$A$5:$A$18,0)),"n/a") -> 895 | AD38: =IFERROR(INDEX('Area safety'!$G$5:$G$18,MATCH($W38,'Area safety'!$A$5:$A$18,0)),"n/a") -> 12 | AE38: =IFERROR(INDEX('Area safety'!$H$5:$H$18,MATCH($W38,'Area safety'!$A$5:$A$18,0)),"n/a") -> 251 | AF38: =IFERROR(INDEX('Area safety'!$I$5:$I$18,MATCH($W38,'Area safety'!$A$5:$A$18,0)),"n/a") -> 262 | AG38: =IFERROR(INDEX('Area safety'!$K$23:$K$41,MATCH($B38,'Area safety'!$A$23:$A$41,0)),"n/a") -> 0.083535109 | AH38: =IFERROR(INDEX('Area safety'!$J$23:$J$41,MATCH($B38,'Area safety'!$A$23:$A$41,0)),"n/a") -> 1
A39: Port Edward | B39: Banners Rest | C39: Available | D39: 680000 | E39: Apartment / Flat | F39: First Floor | G39: 2 | H39: NOT STATED | I39: 84 | J39: 2410 | K39: 660 | L39: No | M39: Yes | N39: Riverside Retreat in Eden Wilds - Aquatic Lifestyle Living in Banners Rest, Port Edward Nestled within the sought-after Eden Wilds Nature Estate in Ba | No Pets Allowed, Pool | O39: Angelique Marran | P39: RE/MAX Coast and Country Southbroom | Q39: NOT CAPTURED (reCAPTCHA) | R39: NOT AVAILABLE (needs phone) | S39: Agent profile | T39: Open listing | U39: 17 June 2026 | V39: 2026-10-08 | W39: =IFERROR(INDEX('Area safety'!$C$23:$C$41,MATCH($B39,'Area safety'!$A$23:$A$41,0)),"n/a") -> Port Edward | X39: =IFERROR(INDEX('Area safety'!$D$23:$D$41,MATCH($B39,'Area safety'!$A$23:$A$41,0)),"n/a") -> UNCONFIRMED - provisional (assumed Port Edward precinct) | Y39: =IFERROR(INDEX('Area safety'!$F$23:$F$41,MATCH($B39,'Area safety'!$A$23:$A$41,0)),"n/a") -> 571.8582 | Z39: =IFERROR(INDEX('Area safety'!$G$23:$G$41,MATCH($B39,'Area safety'!$A$23:$A$41,0)),"n/a") -> 596.91971 | AA39: =IFERROR(INDEX('Area safety'!$H$23:$H$41,MATCH($B39,'Area safety'!$A$23:$A$41,0)),"n/a") -> 27.339834 | AB39: =IFERROR(INDEX('Area safety'!$I$23:$I$41,MATCH($B39,'Area safety'!$A$23:$A$41,0)),"n/a") -> 2039.096 | AC39: =IFERROR(INDEX('Area safety'!$F$5:$F$18,MATCH($W39,'Area safety'!$A$5:$A$18,0)),"n/a") -> 895 | AD39: =IFERROR(INDEX('Area safety'!$G$5:$G$18,MATCH($W39,'Area safety'!$A$5:$A$18,0)),"n/a") -> 12 | AE39: =IFERROR(INDEX('Area safety'!$H$5:$H$18,MATCH($W39,'Area safety'!$A$5:$A$18,0)),"n/a") -> 251 | AF39: =IFERROR(INDEX('Area safety'!$I$5:$I$18,MATCH($W39,'Area safety'!$A$5:$A$18,0)),"n/a") -> 262 | AG39: =IFERROR(INDEX('Area safety'!$K$23:$K$41,MATCH($B39,'Area safety'!$A$23:$A$41,0)),"n/a") -> 0.083535109 | AH39: =IFERROR(INDEX('Area safety'!$J$23:$J$41,MATCH($B39,'Area safety'!$A$23:$A$41,0)),"n/a") -> 1
A40: Port Edward | B40: Banners Rest | C40: Available | D40: 680000 | E40: Apartment / Flat | F40: NOT STATED | G40: 2 | H40: 1 garage | I40: NOT STATED | J40: 1988 | K40: 500 | L40: Yes | M40: NOT STATED | N40: Situated in a safe estate, you enter the home through the kitchen which is open plan and spacious. | Pet Friendly, Pool, Garden | O40: Michele Defilippi | P40: CPS Properties | Q40: NOT CAPTURED (reCAPTCHA) | R40: NOT AVAILABLE (needs phone) | S40: Agent profile | T40: Open listing | U40: 18 September 2025 | V40: 2026-10-08 | W40: =IFERROR(INDEX('Area safety'!$C$23:$C$41,MATCH($B40,'Area safety'!$A$23:$A$41,0)),"n/a") -> Port Edward | X40: =IFERROR(INDEX('Area safety'!$D$23:$D$41,MATCH($B40,'Area safety'!$A$23:$A$41,0)),"n/a") -> UNCONFIRMED - provisional (assumed Port Edward precinct) | Y40: =IFERROR(INDEX('Area safety'!$F$23:$F$41,MATCH($B40,'Area safety'!$A$23:$A$41,0)),"n/a") -> 571.8582 | Z40: =IFERROR(INDEX('Area safety'!$G$23:$G$41,MATCH($B40,'Area safety'!$A$23:$A$41,0)),"n/a") -> 596.91971 | AA40: =IFERROR(INDEX('Area safety'!$H$23:$H$41,MATCH($B40,'Area safety'!$A$23:$A$41,0)),"n/a") -> 27.339834 | AB40: =IFERROR(INDEX('Area safety'!$I$23:$I$41,MATCH($B40,'Area safety'!$A$23:$A$41,0)),"n/a") -> 2039.096 | AC40: =IFERROR(INDEX('Area safety'!$F$5:$F$18,MATCH($W40,'Area safety'!$A$5:$A$18,0)),"n/a") -> 895 | AD40: =IFERROR(INDEX('Area safety'!$G$5:$G$18,MATCH($W40,'Area safety'!$A$5:$A$18,0)),"n/a") -> 12 | AE40: =IFERROR(INDEX('Area safety'!$H$5:$H$18,MATCH($W40,'Area safety'!$A$5:$A$18,0)),"n/a") -> 251 | AF40: =IFERROR(INDEX('Area safety'!$I$5:$I$18,MATCH($W40,'Area safety'!$A$5:$A$18,0)),"n/a") -> 262 | AG40: =IFERROR(INDEX('Area safety'!$K$23:$K$41,MATCH($B40,'Area safety'!$A$23:$A$41,0)),"n/a") -> 0.083535109 | AH40: =IFERROR(INDEX('Area safety'!$J$23:$J$41,MATCH($B40,'Area safety'!$A$23:$A$41,0)),"n/a") -> 1
A41: Port Edward | B41: Banners Rest | C41: Available | D41: 690000 | E41: Apartment / Flat | F41: NOT STATED | G41: 2 | H41: 1 garage | I41: 91 | J41: 2500 | K41: 890 | L41: No | M41: NOT STATED | N41: Propertycoza Communities is proud to advertise this outstanding two bedroom two bathroom holiday/semi retirement apartment for Sale in Port Edward. | No Pets Allowed, Pool | O41: Rene Houghton | P41: Property.CoZa - Communities | Q41: NOT CAPTURED (reCAPTCHA) | R41: NOT AVAILABLE (needs phone) | S41: Agent profile | T41: Open listing | U41: 07 September 2024 | V41: 2026-10-08 | W41: =IFERROR(INDEX('Area safety'!$C$23:$C$41,MATCH($B41,'Area safety'!$A$23:$A$41,0)),"n/a") -> Port Edward | X41: =IFERROR(INDEX('Area safety'!$D$23:$D$41,MATCH($B41,'Area safety'!$A$23:$A$41,0)),"n/a") -> UNCONFIRMED - provisional (assumed Port Edward precinct) | Y41: =IFERROR(INDEX('Area safety'!$F$23:$F$41,MATCH($B41,'Area safety'!$A$23:$A$41,0)),"n/a") -> 571.8582 | Z41: =IFERROR(INDEX('Area safety'!$G$23:$G$41,MATCH($B41,'Area safety'!$A$23:$A$41,0)),"n/a") -> 596.91971 | AA41: =IFERROR(INDEX('Area safety'!$H$23:$H$41,MATCH($B41,'Area safety'!$A$23:$A$41,0)),"n/a") -> 27.339834 | AB41: =IFERROR(INDEX('Area safety'!$I$23:$I$41,MATCH($B41,'Area safety'!$A$23:$A$41,0)),"n/a") -> 2039.096 | AC41: =IFERROR(INDEX('Area safety'!$F$5:$F$18,MATCH($W41,'Area safety'!$A$5:$A$18,0)),"n/a") -> 895 | AD41: =IFERROR(INDEX('Area safety'!$G$5:$G$18,MATCH($W41,'Area safety'!$A$5:$A$18,0)),"n/a") -> 12 | AE41: =IFERROR(INDEX('Area safety'!$H$5:$H$18,MATCH($W41,'Area safety'!$A$5:$A$18,0)),"n/a") -> 251 | AF41: =IFERROR(INDEX('Area safety'!$I$5:$I$18,MATCH($W41,'Area safety'!$A$5:$A$18,0)),"n/a") -> 262 | AG41: =IFERROR(INDEX('Area safety'!$K$23:$K$41,MATCH($B41,'Area safety'!$A$23:$A$41,0)),"n/a") -> 0.083535109 | AH41: =IFERROR(INDEX('Area safety'!$J$23:$J$41,MATCH($B41,'Area safety'!$A$23:$A$41,0)),"n/a") -> 1
A42: Port Edward | B42: Banners Rest | C42: Available | D42: 698000 | E42: Apartment / Flat | F42: Duplex, First Floor | G42: 2 | H42: 1 parking | I42: 84 | J42: 2260 | K42: 540 | L42: NOT STATED | M42: NOT STATED | N42: Excelent buy . Price has just been reduced. | Pool, Fibre Internet | O42: Rene Le Roux | P42: Deo Volente Properties | Q42: NOT CAPTURED (reCAPTCHA) | R42: NOT AVAILABLE (needs phone) | S42: Agent profile | T42: Open listing | U42: 09 August 2024 | V42: 2026-10-08 | W42: =IFERROR(INDEX('Area safety'!$C$23:$C$41,MATCH($B42,'Area safety'!$A$23:$A$41,0)),"n/a") -> Port Edward | X42: =IFERROR(INDEX('Area safety'!$D$23:$D$41,MATCH($B42,'Area safety'!$A$23:$A$41,0)),"n/a") -> UNCONFIRMED - provisional (assumed Port Edward precinct) | Y42: =IFERROR(INDEX('Area safety'!$F$23:$F$41,MATCH($B42,'Area safety'!$A$23:$A$41,0)),"n/a") -> 571.8582 | Z42: =IFERROR(INDEX('Area safety'!$G$23:$G$41,MATCH($B42,'Area safety'!$A$23:$A$41,0)),"n/a") -> 596.91971 | AA42: =IFERROR(INDEX('Area safety'!$H$23:$H$41,MATCH($B42,'Area safety'!$A$23:$A$41,0)),"n/a") -> 27.339834 | AB42: =IFERROR(INDEX('Area safety'!$I$23:$I$41,MATCH($B42,'Area safety'!$A$23:$A$41,0)),"n/a") -> 2039.096 | AC42: =IFERROR(INDEX('Area safety'!$F$5:$F$18,MATCH($W42,'Area safety'!$A$5:$A$18,0)),"n/a") -> 895 | AD42: =IFERROR(INDEX('Area safety'!$G$5:$G$18,MATCH($W42,'Area safety'!$A$5:$A$18,0)),"n/a") -> 12 | AE42: =IFERROR(INDEX('Area safety'!$H$5:$H$18,MATCH($W42,'Area safety'!$A$5:$A$18,0)),"n/a") -> 251 | AF42: =IFERROR(INDEX('Area safety'!$I$5:$I$18,MATCH($W42,'Area safety'!$A$5:$A$18,0)),"n/a") -> 262 | AG42: =IFERROR(INDEX('Area safety'!$K$23:$K$41,MATCH($B42,'Area safety'!$A$23:$A$41,0)),"n/a") -> 0.083535109 | AH42: =IFERROR(INDEX('Area safety'!$J$23:$J$41,MATCH($B42,'Area safety'!$A$23:$A$41,0)),"n/a") -> 1
A43: Port Edward | B43: Banners Rest | C43: Available | D43: 700000 | E43: Apartment / Flat | F43: First Floor | G43: 2 | H43: NOT STATED | I43: 84 | J43: NOT STATED | K43: NOT STATED | L43: No | M43: Yes | N43: Get ready to kick back and relax in this lovely 2-bedroom, 1-bathroom home, perfectly situated in the scenic Banners Rest, Port Edward. | No Pets Allowed, Pool | O43: Angelique Marran | P43: RE/MAX Coast and Country Southbroom | Q43: NOT CAPTURED (reCAPTCHA) | R43: NOT AVAILABLE (needs phone) | S43: Agent profile | T43: Open listing | U43: 24 February 2026 | V43: 2026-10-08 | W43: =IFERROR(INDEX('Area safety'!$C$23:$C$41,MATCH($B43,'Area safety'!$A$23:$A$41,0)),"n/a") -> Port Edward | X43: =IFERROR(INDEX('Area safety'!$D$23:$D$41,MATCH($B43,'Area safety'!$A$23:$A$41,0)),"n/a") -> UNCONFIRMED - provisional (assumed Port Edward precinct) | Y43: =IFERROR(INDEX('Area safety'!$F$23:$F$41,MATCH($B43,'Area safety'!$A$23:$A$41,0)),"n/a") -> 571.8582 | Z43: =IFERROR(INDEX('Area safety'!$G$23:$G$41,MATCH($B43,'Area safety'!$A$23:$A$41,0)),"n/a") -> 596.91971 | AA43: =IFERROR(INDEX('Area safety'!$H$23:$H$41,MATCH($B43,'Area safety'!$A$23:$A$41,0)),"n/a") -> 27.339834 | AB43: =IFERROR(INDEX('Area safety'!$I$23:$I$41,MATCH($B43,'Area safety'!$A$23:$A$41,0)),"n/a") -> 2039.096 | AC43: =IFERROR(INDEX('Area safety'!$F$5:$F$18,MATCH($W43,'Area safety'!$A$5:$A$18,0)),"n/a") -> 895 | AD43: =IFERROR(INDEX('Area safety'!$G$5:$G$18,MATCH($W43,'Area safety'!$A$5:$A$18,0)),"n/a") -> 12 | AE43: =IFERROR(INDEX('Area safety'!$H$5:$H$18,MATCH($W43,'Area safety'!$A$5:$A$18,0)),"n/a") -> 251 | AF43: =IFERROR(INDEX('Area safety'!$I$5:$I$18,MATCH($W43,'Area safety'!$A$5:$A$18,0)),"n/a") -> 262 | AG43: =IFERROR(INDEX('Area safety'!$K$23:$K$41,MATCH($B43,'Area safety'!$A$23:$A$41,0)),"n/a") -> 0.083535109 | AH43: =IFERROR(INDEX('Area safety'!$J$23:$J$41,MATCH($B43,'Area safety'!$A$23:$A$41,0)),"n/a") -> 1
A44: Port Edward | B44: Banners Rest | C44: Available | D44: 700000 | E44: Apartment / Flat | F44: First Floor | G44: 2 | H44: 1 parking | I44: 84 | J44: 2295 | K44: 531 | L44: No | M44: Optional | N44: This delightful, renovated unit on the second floor of one of the well-positioned apartment blocks in the complex is ideal for holiday rental or livin | No Pets Allowed, Pool, Garden | O44: Natalie Abbott | P44: The Property Circle | Q44: NOT CAPTURED (reCAPTCHA) | R44: NOT AVAILABLE (needs phone) | S44: Agent profile | T44: Open listing | U44: 24 February 2026 | V44: 2026-10-08 | W44: =IFERROR(INDEX('Area safety'!$C$23:$C$41,MATCH($B44,'Area safety'!$A$23:$A$41,0)),"n/a") -> Port Edward | X44: =IFERROR(INDEX('Area safety'!$D$23:$D$41,MATCH($B44,'Area safety'!$A$23:$A$41,0)),"n/a") -> UNCONFIRMED - provisional (assumed Port Edward precinct) | Y44: =IFERROR(INDEX('Area safety'!$F$23:$F$41,MATCH($B44,'Area safety'!$A$23:$A$41,0)),"n/a") -> 571.8582 | Z44: =IFERROR(INDEX('Area safety'!$G$23:$G$41,MATCH($B44,'Area safety'!$A$23:$A$41,0)),"n/a") -> 596.91971 | AA44: =IFERROR(INDEX('Area safety'!$H$23:$H$41,MATCH($B44,'Area safety'!$A$23:$A$41,0)),"n/a") -> 27.339834 | AB44: =IFERROR(INDEX('Area safety'!$I$23:$I$41,MATCH($B44,'Area safety'!$A$23:$A$41,0)),"n/a") -> 2039.096 | AC44: =IFERROR(INDEX('Area safety'!$F$5:$F$18,MATCH($W44,'Area safety'!$A$5:$A$18,0)),"n/a") -> 895 | AD44: =IFERROR(INDEX('Area safety'!$G$5:$G$18,MATCH($W44,'Area safety'!$A$5:$A$18,0)),"n/a") -> 12 | AE44: =IFERROR(INDEX('Area safety'!$H$5:$H$18,MATCH($W44,'Area safety'!$A$5:$A$18,0)),"n/a") -> 251 | AF44: =IFERROR(INDEX('Area safety'!$I$5:$I$18,MATCH($W44,'Area safety'!$A$5:$A$18,0)),"n/a") -> 262 | AG44: =IFERROR(INDEX('Area safety'!$K$23:$K$41,MATCH($B44,'Area safety'!$A$23:$A$41,0)),"n/a") -> 0.083535109 | AH44: =IFERROR(INDEX('Area safety'!$J$23:$J$41,MATCH($B44,'Area safety'!$A$23:$A$41,0)),"n/a") -> 1
A45: Port Edward | B45: Banners Rest | C45: Available | D45: 700000 | E45: Apartment / Flat | F45: First floor (per description) | G45: 2 | H45: NOT STATED | I45: 84 | J45: 2194 | K45: 606 | L45: No | M45: Yes | N45: This exceptional unit offers modern living in a breathtaking natural setting. | - Expansive gardens with large trees, open spaces, and a peaceful dam., - Clubhouse with a swimming pool, creating the ideal social and recreational space., - 10-minute drive to Port Edward’s beaches, shops, and golf courses., No Pets Allowed, Pool, Garden | O45: Stephanie Harries | P45: Wakefields Estate Agents Shelly Beach | Q45: NOT CAPTURED (reCAPTCHA) | R45: NOT AVAILABLE (needs phone) | S45: Agent profile | T45: Open listing | U45: 23 August 2023 | V45: 2026-10-08 | W45: =IFERROR(INDEX('Area safety'!$C$23:$C$41,MATCH($B45,'Area safety'!$A$23:$A$41,0)),"n/a") -> Port Edward | X45: =IFERROR(INDEX('Area safety'!$D$23:$D$41,MATCH($B45,'Area safety'!$A$23:$A$41,0)),"n/a") -> UNCONFIRMED - provisional (assumed Port Edward precinct) | Y45: =IFERROR(INDEX('Area safety'!$F$23:$F$41,MATCH($B45,'Area safety'!$A$23:$A$41,0)),"n/a") -> 571.8582 | Z45: =IFERROR(INDEX('Area safety'!$G$23:$G$41,MATCH($B45,'Area safety'!$A$23:$A$41,0)),"n/a") -> 596.91971 | AA45: =IFERROR(INDEX('Area safety'!$H$23:$H$41,MATCH($B45,'Area safety'!$A$23:$A$41,0)),"n/a") -> 27.339834 | AB45: =IFERROR(INDEX('Area safety'!$I$23:$I$41,MATCH($B45,'Area safety'!$A$23:$A$41,0)),"n/a") -> 2039.096 | AC45: =IFERROR(INDEX('Area safety'!$F$5:$F$18,MATCH($W45,'Area safety'!$A$5:$A$18,0)),"n/a") -> 895 | AD45: =IFERROR(INDEX('Area safety'!$G$5:$G$18,MATCH($W45,'Area safety'!$A$5:$A$18,0)),"n/a") -> 12 | AE45: =IFERROR(INDEX('Area safety'!$H$5:$H$18,MATCH($W45,'Area safety'!$A$5:$A$18,0)),"n/a") -> 251 | AF45: =IFERROR(INDEX('Area safety'!$I$5:$I$18,MATCH($W45,'Area safety'!$A$5:$A$18,0)),"n/a") -> 262 | AG45: =IFERROR(INDEX('Area safety'!$K$23:$K$41,MATCH($B45,'Area safety'!$A$23:$A$41,0)),"n/a") -> 0.083535109 | AH45: =IFERROR(INDEX('Area safety'!$J$23:$J$41,MATCH($B45,'Area safety'!$A$23:$A$41,0)),"n/a") -> 1
A46: Port Edward | B46: Banners Rest | C46: Available | D46: 700000 | E46: Apartment / Flat | F46: Top Floor | G46: 2 | H46: NOT STATED | I46: 84 | J46: 2400 | K46: 468 | L46: NOT STATED | M46: NOT STATED | N46: This beautifully renovated top-floor apartment offers the perfect blend of comfort, style, and natural beauty. | Pool, Garden | O46: Tertia Sterley | P46: Property Port | Q46: NOT CAPTURED (reCAPTCHA) | R46: NOT AVAILABLE (needs phone) | S46: Agent profile | T46: Open listing | U46: 11 July 2025 | V46: 2026-10-08 | W46: =IFERROR(INDEX('Area safety'!$C$23:$C$41,MATCH($B46,'Area safety'!$A$23:$A$41,0)),"n/a") -> Port Edward | X46: =IFERROR(INDEX('Area safety'!$D$23:$D$41,MATCH($B46,'Area safety'!$A$23:$A$41,0)),"n/a") -> UNCONFIRMED - provisional (assumed Port Edward precinct) | Y46: =IFERROR(INDEX('Area safety'!$F$23:$F$41,MATCH($B46,'Area safety'!$A$23:$A$41,0)),"n/a") -> 571.8582 | Z46: =IFERROR(INDEX('Area safety'!$G$23:$G$41,MATCH($B46,'Area safety'!$A$23:$A$41,0)),"n/a") -> 596.91971 | AA46: =IFERROR(INDEX('Area safety'!$H$23:$H$41,MATCH($B46,'Area safety'!$A$23:$A$41,0)),"n/a") -> 27.339834 | AB46: =IFERROR(INDEX('Area safety'!$I$23:$I$41,MATCH($B46,'Area safety'!$A$23:$A$41,0)),"n/a") -> 2039.096 | AC46: =IFERROR(INDEX('Area safety'!$F$5:$F$18,MATCH($W46,'Area safety'!$A$5:$A$18,0)),"n/a") -> 895 | AD46: =IFERROR(INDEX('Area safety'!$G$5:$G$18,MATCH($W46,'Area safety'!$A$5:$A$18,0)),"n/a") -> 12 | AE46: =IFERROR(INDEX('Area safety'!$H$5:$H$18,MATCH($W46,'Area safety'!$A$5:$A$18,0)),"n/a") -> 251 | AF46: =IFERROR(INDEX('Area safety'!$I$5:$I$18,MATCH($W46,'Area safety'!$A$5:$A$18,0)),"n/a") -> 262 | AG46: =IFERROR(INDEX('Area safety'!$K$23:$K$41,MATCH($B46,'Area safety'!$A$23:$A$41,0)),"n/a") -> 0.083535109 | AH46: =IFERROR(INDEX('Area safety'!$J$23:$J$41,MATCH($B46,'Area safety'!$A$23:$A$41,0)),"n/a") -> 1
A47: Port Edward | B47: Banners Rest | C47: Available | D47: 720000 | E47: Apartment / Flat | F47: NOT STATED | G47: 2 | H47: 1 garage | I47: 95 | J47: 810 | K47: NOT STATED | L47: NOT STATED | M47: NOT STATED | N47: Secure Estate down the road from Port Edward and across the river from the Wild Coast Sun. | Pool | O47: Noel Molyneaux | P47: Pam Golding Properties - Port Edward | Q47: NOT CAPTURED (reCAPTCHA) | R47: NOT AVAILABLE (needs phone) | S47: Agent profile | T47: Open listing | U47: 05 October 2015 | V47: 2026-10-08 | W47: =IFERROR(INDEX('Area safety'!$C$23:$C$41,MATCH($B47,'Area safety'!$A$23:$A$41,0)),"n/a") -> Port Edward | X47: =IFERROR(INDEX('Area safety'!$D$23:$D$41,MATCH($B47,'Area safety'!$A$23:$A$41,0)),"n/a") -> UNCONFIRMED - provisional (assumed Port Edward precinct) | Y47: =IFERROR(INDEX('Area safety'!$F$23:$F$41,MATCH($B47,'Area safety'!$A$23:$A$41,0)),"n/a") -> 571.8582 | Z47: =IFERROR(INDEX('Area safety'!$G$23:$G$41,MATCH($B47,'Area safety'!$A$23:$A$41,0)),"n/a") -> 596.91971 | AA47: =IFERROR(INDEX('Area safety'!$H$23:$H$41,MATCH($B47,'Area safety'!$A$23:$A$41,0)),"n/a") -> 27.339834 | AB47: =IFERROR(INDEX('Area safety'!$I$23:$I$41,MATCH($B47,'Area safety'!$A$23:$A$41,0)),"n/a") -> 2039.096 | AC47: =IFERROR(INDEX('Area safety'!$F$5:$F$18,MATCH($W47,'Area safety'!$A$5:$A$18,0)),"n/a") -> 895 | AD47: =IFERROR(INDEX('Area safety'!$G$5:$G$18,MATCH($W47,'Area safety'!$A$5:$A$18,0)),"n/a") -> 12 | AE47: =IFERROR(INDEX('Area safety'!$H$5:$H$18,MATCH($W47,'Area safety'!$A$5:$A$18,0)),"n/a") -> 251 | AF47: =IFERROR(INDEX('Area safety'!$I$5:$I$18,MATCH($W47,'Area safety'!$A$5:$A$18,0)),"n/a") -> 262 | AG47: =IFERROR(INDEX('Area safety'!$K$23:$K$41,MATCH($B47,'Area safety'!$A$23:$A$41,0)),"n/a") -> 0.083535109 | AH47: =IFERROR(INDEX('Area safety'!$J$23:$J$41,MATCH($B47,'Area safety'!$A$23:$A$41,0)),"n/a") -> 1
A48: Port Edward | B48: Rennies Beach | C48: Available | D48: 620000 | E48: Apartment / Flat | F48: NOT STATED | G48: 2 | H48: NOT STATED | I48: 84 | J48: NOT STATED | K48: 500 | L48: NOT STATED | M48: Yes | N48: Hello, I'm Lerato, your dedicated real estate agent specializing in the picturesque South Coast. | Pool, Garden | O48: Gert Van Zyl | P48: Real & Proper T | Q48: NOT CAPTURED (reCAPTCHA) | R48: NOT AVAILABLE (needs phone) | S48: Agent profile | T48: Open listing | U48: 16 June 2025 | V48: 2026-10-08 | W48: =IFERROR(INDEX('Area safety'!$C$23:$C$41,MATCH($B48,'Area safety'!$A$23:$A$41,0)),"n/a") -> Port Edward | X48: =IFERROR(INDEX('Area safety'!$D$23:$D$41,MATCH($B48,'Area safety'!$A$23:$A$41,0)),"n/a") -> UNCONFIRMED - provisional (assumed Port Edward precinct) | Y48: =IFERROR(INDEX('Area safety'!$F$23:$F$41,MATCH($B48,'Area safety'!$A$23:$A$41,0)),"n/a") -> 571.8582 | Z48: =IFERROR(INDEX('Area safety'!$G$23:$G$41,MATCH($B48,'Area safety'!$A$23:$A$41,0)),"n/a") -> 596.91971 | AA48: =IFERROR(INDEX('Area safety'!$H$23:$H$41,MATCH($B48,'Area safety'!$A$23:$A$41,0)),"n/a") -> 27.339834 | AB48: =IFERROR(INDEX('Area safety'!$I$23:$I$41,MATCH($B48,'Area safety'!$A$23:$A$41,0)),"n/a") -> 2039.096 | AC48: =IFERROR(INDEX('Area safety'!$F$5:$F$18,MATCH($W48,'Area safety'!$A$5:$A$18,0)),"n/a") -> 895 | AD48: =IFERROR(INDEX('Area safety'!$G$5:$G$18,MATCH($W48,'Area safety'!$A$5:$A$18,0)),"n/a") -> 12 | AE48: =IFERROR(INDEX('Area safety'!$H$5:$H$18,MATCH($W48,'Area safety'!$A$5:$A$18,0)),"n/a") -> 251 | AF48: =IFERROR(INDEX('Area safety'!$I$5:$I$18,MATCH($W48,'Area safety'!$A$5:$A$18,0)),"n/a") -> 262 | AG48: =IFERROR(INDEX('Area safety'!$K$23:$K$41,MATCH($B48,'Area safety'!$A$23:$A$41,0)),"n/a") -> 0.083535109 | AH48: =IFERROR(INDEX('Area safety'!$J$23:$J$41,MATCH($B48,'Area safety'!$A$23:$A$41,0)),"n/a") -> 1
A49: Port Edward | B49: Rennies Beach | C49: Available | D49: 670000 | E49: Apartment / Flat | F49: Top floor (per description) | G49: 2 | H49: NOT STATED | I49: 84 | J49: 2600 | K49: 500 | L49: NOT STATED | M49: NOT STATED | N49: Hello, I'm Lerato, your dedicated real estate agent specializing in the picturesque South Coast. | Pool, Garden | O49: Gert Van Zyl | P49: Real & Proper T | Q49: NOT CAPTURED (reCAPTCHA) | R49: NOT AVAILABLE (needs phone) | S49: Agent profile | T49: Open listing | U49: 17 February 2025 | V49: 2026-10-08 | W49: =IFERROR(INDEX('Area safety'!$C$23:$C$41,MATCH($B49,'Area safety'!$A$23:$A$41,0)),"n/a") -> Port Edward | X49: =IFERROR(INDEX('Area safety'!$D$23:$D$41,MATCH($B49,'Area safety'!$A$23:$A$41,0)),"n/a") -> UNCONFIRMED - provisional (assumed Port Edward precinct) | Y49: =IFERROR(INDEX('Area safety'!$F$23:$F$41,MATCH($B49,'Area safety'!$A$23:$A$41,0)),"n/a") -> 571.8582 | Z49: =IFERROR(INDEX('Area safety'!$G$23:$G$41,MATCH($B49,'Area safety'!$A$23:$A$41,0)),"n/a") -> 596.91971 | AA49: =IFERROR(INDEX('Area safety'!$H$23:$H$41,MATCH($B49,'Area safety'!$A$23:$A$41,0)),"n/a") -> 27.339834 | AB49: =IFERROR(INDEX('Area safety'!$I$23:$I$41,MATCH($B49,'Area safety'!$A$23:$A$41,0)),"n/a") -> 2039.096 | AC49: =IFERROR(INDEX('Area safety'!$F$5:$F$18,MATCH($W49,'Area safety'!$A$5:$A$18,0)),"n/a") -> 895 | AD49: =IFERROR(INDEX('Area safety'!$G$5:$G$18,MATCH($W49,'Area safety'!$A$5:$A$18,0)),"n/a") -> 12 | AE49: =IFERROR(INDEX('Area safety'!$H$5:$H$18,MATCH($W49,'Area safety'!$A$5:$A$18,0)),"n/a") -> 251 | AF49: =IFERROR(INDEX('Area safety'!$I$5:$I$18,MATCH($W49,'Area safety'!$A$5:$A$18,0)),"n/a") -> 262 | AG49: =IFERROR(INDEX('Area safety'!$K$23:$K$41,MATCH($B49,'Area safety'!$A$23:$A$41,0)),"n/a") -> 0.083535109 | AH49: =IFERROR(INDEX('Area safety'!$J$23:$J$41,MATCH($B49,'Area safety'!$A$23:$A$41,0)),"n/a") -> 1
A50: Port Edward | B50: Rennies Beach | C50: Available | D50: 680000 | E50: Apartment / Flat | F50: NOT STATED | G50: 2 | H50: NOT STATED | I50: 84 | J50: NOT STATED | K50: 500 | L50: NOT STATED | M50: Yes | N50: Hello, I'm Lerato, your dedicated real estate agent specializing in the picturesque South Coast. | Pool | O50: Gert Van Zyl | P50: Real & Proper T | Q50: NOT CAPTURED (reCAPTCHA) | R50: NOT AVAILABLE (needs phone) | S50: Agent profile | T50: Open listing | U50: 04 February 2025 | V50: 2026-10-08 | W50: =IFERROR(INDEX('Area safety'!$C$23:$C$41,MATCH($B50,'Area safety'!$A$23:$A$41,0)),"n/a") -> Port Edward | X50: =IFERROR(INDEX('Area safety'!$D$23:$D$41,MATCH($B50,'Area safety'!$A$23:$A$41,0)),"n/a") -> UNCONFIRMED - provisional (assumed Port Edward precinct) | Y50: =IFERROR(INDEX('Area safety'!$F$23:$F$41,MATCH($B50,'Area safety'!$A$23:$A$41,0)),"n/a") -> 571.8582 | Z50: =IFERROR(INDEX('Area safety'!$G$23:$G$41,MATCH($B50,'Area safety'!$A$23:$A$41,0)),"n/a") -> 596.91971 | AA50: =IFERROR(INDEX('Area safety'!$H$23:$H$41,MATCH($B50,'Area safety'!$A$23:$A$41,0)),"n/a") -> 27.339834 | AB50: =IFERROR(INDEX('Area safety'!$I$23:$I$41,MATCH($B50,'Area safety'!$A$23:$A$41,0)),"n/a") -> 2039.096 | AC50: =IFERROR(INDEX('Area safety'!$F$5:$F$18,MATCH($W50,'Area safety'!$A$5:$A$18,0)),"n/a") -> 895 | AD50: =IFERROR(INDEX('Area safety'!$G$5:$G$18,MATCH($W50,'Area safety'!$A$5:$A$18,0)),"n/a") -> 12 | AE50: =IFERROR(INDEX('Area safety'!$H$5:$H$18,MATCH($W50,'Area safety'!$A$5:$A$18,0)),"n/a") -> 251 | AF50: =IFERROR(INDEX('Area safety'!$I$5:$I$18,MATCH($W50,'Area safety'!$A$5:$A$18,0)),"n/a") -> 262 | AG50: =IFERROR(INDEX('Area safety'!$K$23:$K$41,MATCH($B50,'Area safety'!$A$23:$A$41,0)),"n/a") -> 0.083535109 | AH50: =IFERROR(INDEX('Area safety'!$J$23:$J$41,MATCH($B50,'Area safety'!$A$23:$A$41,0)),"n/a") -> 1
A51: Port Edward | B51: Rennies Beach | C51: Available | D51: 690000 | E51: Apartment / Flat | F51: NOT STATED | G51: 2 | H51: NOT STATED | I51: 91 | J51: 2260 | K51: 500 | L51: NOT STATED | M51: NOT STATED | N51: Hello, I'm Lerato, your dedicated real estate agent specializing in the picturesque South Coast. | Pool | O51: Gert Van Zyl | P51: Real & Proper T | Q51: NOT CAPTURED (reCAPTCHA) | R51: NOT AVAILABLE (needs phone) | S51: Agent profile | T51: Open listing | U51: 12 March 2025 | V51: 2026-10-08 | W51: =IFERROR(INDEX('Area safety'!$C$23:$C$41,MATCH($B51,'Area safety'!$A$23:$A$41,0)),"n/a") -> Port Edward | X51: =IFERROR(INDEX('Area safety'!$D$23:$D$41,MATCH($B51,'Area safety'!$A$23:$A$41,0)),"n/a") -> UNCONFIRMED - provisional (assumed Port Edward precinct) | Y51: =IFERROR(INDEX('Area safety'!$F$23:$F$41,MATCH($B51,'Area safety'!$A$23:$A$41,0)),"n/a") -> 571.8582 | Z51: =IFERROR(INDEX('Area safety'!$G$23:$G$41,MATCH($B51,'Area safety'!$A$23:$A$41,0)),"n/a") -> 596.91971 | AA51: =IFERROR(INDEX('Area safety'!$H$23:$H$41,MATCH($B51,'Area safety'!$A$23:$A$41,0)),"n/a") -> 27.339834 | AB51: =IFERROR(INDEX('Area safety'!$I$23:$I$41,MATCH($B51,'Area safety'!$A$23:$A$41,0)),"n/a") -> 2039.096 | AC51: =IFERROR(INDEX('Area safety'!$F$5:$F$18,MATCH($W51,'Area safety'!$A$5:$A$18,0)),"n/a") -> 895 | AD51: =IFERROR(INDEX('Area safety'!$G$5:$G$18,MATCH($W51,'Area safety'!$A$5:$A$18,0)),"n/a") -> 12 | AE51: =IFERROR(INDEX('Area safety'!$H$5:$H$18,MATCH($W51,'Area safety'!$A$5:$A$18,0)),"n/a") -> 251 | AF51: =IFERROR(INDEX('Area safety'!$I$5:$I$18,MATCH($W51,'Area safety'!$A$5:$A$18,0)),"n/a") -> 262 | AG51: =IFERROR(INDEX('Area safety'!$K$23:$K$41,MATCH($B51,'Area safety'!$A$23:$A$41,0)),"n/a") -> 0.083535109 | AH51: =IFERROR(INDEX('Area safety'!$J$23:$J$41,MATCH($B51,'Area safety'!$A$23:$A$41,0)),"n/a") -> 1
A52: Margate | B52: Ramsgate | C52: Available | D52: 550000 | E52: Apartment / Flat | F52: First Floor | G52: 2 | H52: 1 garage | I52: 78 | J52: 1800 | K52: 800 | L52: Yes | M52: Optional | N52: Welcome home to this beautiful two-bedroom, two-bathroom apartment in a cozy, secure complex of only five units. | Pet Friendly, Garden, Fibre Internet | O52: Ayanda Zwalo | P52: Alpha Estates | Q52: NOT CAPTURED (reCAPTCHA) | R52: NOT AVAILABLE (needs phone) | S52: Agent profile | T52: Open listing | U52: 21 December 2023 | V52: 2026-10-08 | W52: =IFERROR(INDEX('Area safety'!$C$23:$C$41,MATCH($B52,'Area safety'!$A$23:$A$41,0)),"n/a") -> Margate | X52: =IFERROR(INDEX('Area safety'!$D$23:$D$41,MATCH($B52,'Area safety'!$A$23:$A$41,0)),"n/a") -> CONFIRMED | Y52: =IFERROR(INDEX('Area safety'!$F$23:$F$41,MATCH($B52,'Area safety'!$A$23:$A$41,0)),"n/a") -> 1154.5136 | Z52: =IFERROR(INDEX('Area safety'!$G$23:$G$41,MATCH($B52,'Area safety'!$A$23:$A$41,0)),"n/a") -> 691.04551 | AA52: =IFERROR(INDEX('Area safety'!$H$23:$H$41,MATCH($B52,'Area safety'!$A$23:$A$41,0)),"n/a") -> 23.900822 | AB52: =IFERROR(INDEX('Area safety'!$I$23:$I$41,MATCH($B52,'Area safety'!$A$23:$A$41,0)),"n/a") -> 4980.7235 | AC52: =IFERROR(INDEX('Area safety'!$F$5:$F$18,MATCH($W52,'Area safety'!$A$5:$A$18,0)),"n/a") -> 4793 | AD52: =IFERROR(INDEX('Area safety'!$G$5:$G$18,MATCH($W52,'Area safety'!$A$5:$A$18,0)),"n/a") -> 23 | AE52: =IFERROR(INDEX('Area safety'!$H$5:$H$18,MATCH($W52,'Area safety'!$A$5:$A$18,0)),"n/a") -> 1111 | AF52: =IFERROR(INDEX('Area safety'!$I$5:$I$18,MATCH($W52,'Area safety'!$A$5:$A$18,0)),"n/a") -> 665 | AG52: =IFERROR(INDEX('Area safety'!$K$23:$K$41,MATCH($B52,'Area safety'!$A$23:$A$41,0)),"n/a") -> 0.099059849 | AH52: =IFERROR(INDEX('Area safety'!$J$23:$J$41,MATCH($B52,'Area safety'!$A$23:$A$41,0)),"n/a") -> 4
A53: Margate | B53: Ramsgate | C53: Available | D53: 550000 | E53: Apartment / Flat | F53: NOT STATED | G53: 2 | H53: 1 garage | I53: 55 | J53: 2145 | K53: 966 | L53: No | M53: NOT STATED | N53: Step directly from your private gate onto the sand. | No Pets Allowed, Garden | O53: Frederik Olivier | P53: Urban Link JHB Zone 1 | Q53: NOT CAPTURED (reCAPTCHA) | R53: NOT AVAILABLE (needs phone) | S53: Agent profile | T53: Open listing | U53: 02 July 2026 | V53: 2026-10-08 | W53: =IFERROR(INDEX('Area safety'!$C$23:$C$41,MATCH($B53,'Area safety'!$A$23:$A$41,0)),"n/a") -> Margate | X53: =IFERROR(INDEX('Area safety'!$D$23:$D$41,MATCH($B53,'Area safety'!$A$23:$A$41,0)),"n/a") -> CONFIRMED | Y53: =IFERROR(INDEX('Area safety'!$F$23:$F$41,MATCH($B53,'Area safety'!$A$23:$A$41,0)),"n/a") -> 1154.5136 | Z53: =IFERROR(INDEX('Area safety'!$G$23:$G$41,MATCH($B53,'Area safety'!$A$23:$A$41,0)),"n/a") -> 691.04551 | AA53: =IFERROR(INDEX('Area safety'!$H$23:$H$41,MATCH($B53,'Area safety'!$A$23:$A$41,0)),"n/a") -> 23.900822 | AB53: =IFERROR(INDEX('Area safety'!$I$23:$I$41,MATCH($B53,'Area safety'!$A$23:$A$41,0)),"n/a") -> 4980.7235 | AC53: =IFERROR(INDEX('Area safety'!$F$5:$F$18,MATCH($W53,'Area safety'!$A$5:$A$18,0)),"n/a") -> 4793 | AD53: =IFERROR(INDEX('Area safety'!$G$5:$G$18,MATCH($W53,'Area safety'!$A$5:$A$18,0)),"n/a") -> 23 | AE53: =IFERROR(INDEX('Area safety'!$H$5:$H$18,MATCH($W53,'Area safety'!$A$5:$A$18,0)),"n/a") -> 1111 | AF53: =IFERROR(INDEX('Area safety'!$I$5:$I$18,MATCH($W53,'Area safety'!$A$5:$A$18,0)),"n/a") -> 665 | AG53: =IFERROR(INDEX('Area safety'!$K$23:$K$41,MATCH($B53,'Area safety'!$A$23:$A$41,0)),"n/a") -> 0.099059849 | AH53: =IFERROR(INDEX('Area safety'!$J$23:$J$41,MATCH($B53,'Area safety'!$A$23:$A$41,0)),"n/a") -> 4
A54: Margate | B54: Ramsgate | C54: Available | D54: 560000 | E54: Apartment / Flat | F54: First floor (per description) | G54: 2 | H54: 1 garage | I54: 90 | J54: 1080 | K54: 2700 | L54: Yes | M54: NOT STATED | N54: This charming and spacious first-floor unit is perfectly positioned in the heart of Ramsgate, just 600 metres from the renowned Blue Flag Ramsgate swi | Pet Friendly, Garden, Fibre Internet | O54: Kristina Schafer | P54: Seeff Hibiscus Coast | Q54: NOT CAPTURED (reCAPTCHA) | R54: NOT AVAILABLE (needs phone) | S54: Agent profile | T54: Open listing | U54: 14 April 2026 | V54: 2026-10-08 | W54: =IFERROR(INDEX('Area safety'!$C$23:$C$41,MATCH($B54,'Area safety'!$A$23:$A$41,0)),"n/a") -> Margate | X54: =IFERROR(INDEX('Area safety'!$D$23:$D$41,MATCH($B54,'Area safety'!$A$23:$A$41,0)),"n/a") -> CONFIRMED | Y54: =IFERROR(INDEX('Area safety'!$F$23:$F$41,MATCH($B54,'Area safety'!$A$23:$A$41,0)),"n/a") -> 1154.5136 | Z54: =IFERROR(INDEX('Area safety'!$G$23:$G$41,MATCH($B54,'Area safety'!$A$23:$A$41,0)),"n/a") -> 691.04551 | AA54: =IFERROR(INDEX('Area safety'!$H$23:$H$41,MATCH($B54,'Area safety'!$A$23:$A$41,0)),"n/a") -> 23.900822 | AB54: =IFERROR(INDEX('Area safety'!$I$23:$I$41,MATCH($B54,'Area safety'!$A$23:$A$41,0)),"n/a") -> 4980.7235 | AC54: =IFERROR(INDEX('Area safety'!$F$5:$F$18,MATCH($W54,'Area safety'!$A$5:$A$18,0)),"n/a") -> 4793 | AD54: =IFERROR(INDEX('Area safety'!$G$5:$G$18,MATCH($W54,'Area safety'!$A$5:$A$18,0)),"n/a") -> 23 | AE54: =IFERROR(INDEX('Area safety'!$H$5:$H$18,MATCH($W54,'Area safety'!$A$5:$A$18,0)),"n/a") -> 1111 | AF54: =IFERROR(INDEX('Area safety'!$I$5:$I$18,MATCH($W54,'Area safety'!$A$5:$A$18,0)),"n/a") -> 665 | AG54: =IFERROR(INDEX('Area safety'!$K$23:$K$41,MATCH($B54,'Area safety'!$A$23:$A$41,0)),"n/a") -> 0.099059849 | AH54: =IFERROR(INDEX('Area safety'!$J$23:$J$41,MATCH($B54,'Area safety'!$A$23:$A$41,0)),"n/a") -> 4
A55: Margate | B55: Ramsgate | C55: Available | D55: 570000 | E55: Apartment / Flat | F55: NOT STATED | G55: 2 | H55: 1 garage | I55: 81 | J55: 2081 | K55: 2000 | L55: Yes | M55: NOT STATED | N55: Looking for a peaceful home surrounded by beautiful greenery? | Pet Friendly | O55: Stephan Fouche | P55: Mandated | Q55: NOT CAPTURED (reCAPTCHA) | R55: NOT AVAILABLE (needs phone) | S55: Agent profile | T55: Open listing | U55: 11 September 2026 | V55: 2026-10-08 | W55: =IFERROR(INDEX('Area safety'!$C$23:$C$41,MATCH($B55,'Area safety'!$A$23:$A$41,0)),"n/a") -> Margate | X55: =IFERROR(INDEX('Area safety'!$D$23:$D$41,MATCH($B55,'Area safety'!$A$23:$A$41,0)),"n/a") -> CONFIRMED | Y55: =IFERROR(INDEX('Area safety'!$F$23:$F$41,MATCH($B55,'Area safety'!$A$23:$A$41,0)),"n/a") -> 1154.5136 | Z55: =IFERROR(INDEX('Area safety'!$G$23:$G$41,MATCH($B55,'Area safety'!$A$23:$A$41,0)),"n/a") -> 691.04551 | AA55: =IFERROR(INDEX('Area safety'!$H$23:$H$41,MATCH($B55,'Area safety'!$A$23:$A$41,0)),"n/a") -> 23.900822 | AB55: =IFERROR(INDEX('Area safety'!$I$23:$I$41,MATCH($B55,'Area safety'!$A$23:$A$41,0)),"n/a") -> 4980.7235 | AC55: =IFERROR(INDEX('Area safety'!$F$5:$F$18,MATCH($W55,'Area safety'!$A$5:$A$18,0)),"n/a") -> 4793 | AD55: =IFERROR(INDEX('Area safety'!$G$5:$G$18,MATCH($W55,'Area safety'!$A$5:$A$18,0)),"n/a") -> 23 | AE55: =IFERROR(INDEX('Area safety'!$H$5:$H$18,MATCH($W55,'Area safety'!$A$5:$A$18,0)),"n/a") -> 1111 | AF55: =IFERROR(INDEX('Area safety'!$I$5:$I$18,MATCH($W55,'Area safety'!$A$5:$A$18,0)),"n/a") -> 665 | AG55: =IFERROR(INDEX('Area safety'!$K$23:$K$41,MATCH($B55,'Area safety'!$A$23:$A$41,0)),"n/a") -> 0.099059849 | AH55: =IFERROR(INDEX('Area safety'!$J$23:$J$41,MATCH($B55,'Area safety'!$A$23:$A$41,0)),"n/a") -> 4
A56: Margate | B56: Ramsgate | C56: Available | D56: 570000 | E56: Apartment / Flat | F56: Second floor (per description) | G56: 2 | H56: 1 garage | I56: 110 | J56: 2050 | K56: 1000 | L56: Yes | M56: NOT STATED | N56: Second-floor apartment in Ramsgate, KwaZulu-Natal, offers an excellent opportunity for first-time buyers, investors, or those seeking a coastal retreat. | Pet Friendly | O56: Mary-Anne de Villiers | P56: Property.CoZa - Legends | Q56: NOT CAPTURED (reCAPTCHA) | R56: NOT AVAILABLE (needs phone) | S56: Agent profile | T56: Open listing | U56: 21 April 2026 | V56: 2026-10-08 | W56: =IFERROR(INDEX('Area safety'!$C$23:$C$41,MATCH($B56,'Area safety'!$A$23:$A$41,0)),"n/a") -> Margate | X56: =IFERROR(INDEX('Area safety'!$D$23:$D$41,MATCH($B56,'Area safety'!$A$23:$A$41,0)),"n/a") -> CONFIRMED | Y56: =IFERROR(INDEX('Area safety'!$F$23:$F$41,MATCH($B56,'Area safety'!$A$23:$A$41,0)),"n/a") -> 1154.5136 | Z56: =IFERROR(INDEX('Area safety'!$G$23:$G$41,MATCH($B56,'Area safety'!$A$23:$A$41,0)),"n/a") -> 691.04551 | AA56: =IFERROR(INDEX('Area safety'!$H$23:$H$41,MATCH($B56,'Area safety'!$A$23:$A$41,0)),"n/a") -> 23.900822 | AB56: =IFERROR(INDEX('Area safety'!$I$23:$I$41,MATCH($B56,'Area safety'!$A$23:$A$41,0)),"n/a") -> 4980.7235 | AC56: =IFERROR(INDEX('Area safety'!$F$5:$F$18,MATCH($W56,'Area safety'!$A$5:$A$18,0)),"n/a") -> 4793 | AD56: =IFERROR(INDEX('Area safety'!$G$5:$G$18,MATCH($W56,'Area safety'!$A$5:$A$18,0)),"n/a") -> 23 | AE56: =IFERROR(INDEX('Area safety'!$H$5:$H$18,MATCH($W56,'Area safety'!$A$5:$A$18,0)),"n/a") -> 1111 | AF56: =IFERROR(INDEX('Area safety'!$I$5:$I$18,MATCH($W56,'Area safety'!$A$5:$A$18,0)),"n/a") -> 665 | AG56: =IFERROR(INDEX('Area safety'!$K$23:$K$41,MATCH($B56,'Area safety'!$A$23:$A$41,0)),"n/a") -> 0.099059849 | AH56: =IFERROR(INDEX('Area safety'!$J$23:$J$41,MATCH($B56,'Area safety'!$A$23:$A$41,0)),"n/a") -> 4
A57: Margate | B57: Ramsgate | C57: Available | D57: 595000 | E57: Apartment / Flat | F57: Third Floor | G57: 2 | H57: 1 parking | I57: 48 | J57: 1400 | K57: 800 | L57: No | M57: NOT STATED | N57: Escape to a light filled Ramsgate apartment that balances easy living with security and comfort. | No Pets Allowed | O57: Shevaun Erica Gandy | P57: Property Finders Westrand | Q57: NOT CAPTURED (reCAPTCHA) | R57: NOT AVAILABLE (needs phone) | S57: Agent profile | T57: Open listing | U57: 29 May 2026 | V57: 2026-10-08 | W57: =IFERROR(INDEX('Area safety'!$C$23:$C$41,MATCH($B57,'Area safety'!$A$23:$A$41,0)),"n/a") -> Margate | X57: =IFERROR(INDEX('Area safety'!$D$23:$D$41,MATCH($B57,'Area safety'!$A$23:$A$41,0)),"n/a") -> CONFIRMED | Y57: =IFERROR(INDEX('Area safety'!$F$23:$F$41,MATCH($B57,'Area safety'!$A$23:$A$41,0)),"n/a") -> 1154.5136 | Z57: =IFERROR(INDEX('Area safety'!$G$23:$G$41,MATCH($B57,'Area safety'!$A$23:$A$41,0)),"n/a") -> 691.04551 | AA57: =IFERROR(INDEX('Area safety'!$H$23:$H$41,MATCH($B57,'Area safety'!$A$23:$A$41,0)),"n/a") -> 23.900822 | AB57: =IFERROR(INDEX('Area safety'!$I$23:$I$41,MATCH($B57,'Area safety'!$A$23:$A$41,0)),"n/a") -> 4980.7235 | AC57: =IFERROR(INDEX('Area safety'!$F$5:$F$18,MATCH($W57,'Area safety'!$A$5:$A$18,0)),"n/a") -> 4793 | AD57: =IFERROR(INDEX('Area safety'!$G$5:$G$18,MATCH($W57,'Area safety'!$A$5:$A$18,0)),"n/a") -> 23 | AE57: =IFERROR(INDEX('Area safety'!$H$5:$H$18,MATCH($W57,'Area safety'!$A$5:$A$18,0)),"n/a") -> 1111 | AF57: =IFERROR(INDEX('Area safety'!$I$5:$I$18,MATCH($W57,'Area safety'!$A$5:$A$18,0)),"n/a") -> 665 | AG57: =IFERROR(INDEX('Area safety'!$K$23:$K$41,MATCH($B57,'Area safety'!$A$23:$A$41,0)),"n/a") -> 0.099059849 | AH57: =IFERROR(INDEX('Area safety'!$J$23:$J$41,MATCH($B57,'Area safety'!$A$23:$A$41,0)),"n/a") -> 4
A58: Margate | B58: Ramsgate | C58: Available | D58: 650000 | E58: Apartment / Flat | F58: First floor (per description) | G58: 2 | H58: 2 garage | I58: 149 | J58: 2000 | K58: 1200 | L58: Yes | M58: NOT STATED | N58: Welcome to our newest Dual Mandate. | Pet Friendly, Pool | O58: Nadia Beattie | P58: Just Property Living | Q58: NOT CAPTURED (reCAPTCHA) | R58: NOT AVAILABLE (needs phone) | S58: Agent profile | T58: Open listing | U58: 05 June 2026 | V58: 2026-10-08 | W58: =IFERROR(INDEX('Area safety'!$C$23:$C$41,MATCH($B58,'Area safety'!$A$23:$A$41,0)),"n/a") -> Margate | X58: =IFERROR(INDEX('Area safety'!$D$23:$D$41,MATCH($B58,'Area safety'!$A$23:$A$41,0)),"n/a") -> CONFIRMED | Y58: =IFERROR(INDEX('Area safety'!$F$23:$F$41,MATCH($B58,'Area safety'!$A$23:$A$41,0)),"n/a") -> 1154.5136 | Z58: =IFERROR(INDEX('Area safety'!$G$23:$G$41,MATCH($B58,'Area safety'!$A$23:$A$41,0)),"n/a") -> 691.04551 | AA58: =IFERROR(INDEX('Area safety'!$H$23:$H$41,MATCH($B58,'Area safety'!$A$23:$A$41,0)),"n/a") -> 23.900822 | AB58: =IFERROR(INDEX('Area safety'!$I$23:$I$41,MATCH($B58,'Area safety'!$A$23:$A$41,0)),"n/a") -> 4980.7235 | AC58: =IFERROR(INDEX('Area safety'!$F$5:$F$18,MATCH($W58,'Area safety'!$A$5:$A$18,0)),"n/a") -> 4793 | AD58: =IFERROR(INDEX('Area safety'!$G$5:$G$18,MATCH($W58,'Area safety'!$A$5:$A$18,0)),"n/a") -> 23 | AE58: =IFERROR(INDEX('Area safety'!$H$5:$H$18,MATCH($W58,'Area safety'!$A$5:$A$18,0)),"n/a") -> 1111 | AF58: =IFERROR(INDEX('Area safety'!$I$5:$I$18,MATCH($W58,'Area safety'!$A$5:$A$18,0)),"n/a") -> 665 | AG58: =IFERROR(INDEX('Area safety'!$K$23:$K$41,MATCH($B58,'Area safety'!$A$23:$A$41,0)),"n/a") -> 0.099059849 | AH58: =IFERROR(INDEX('Area safety'!$J$23:$J$41,MATCH($B58,'Area safety'!$A$23:$A$41,0)),"n/a") -> 4
A59: Margate | B59: Ramsgate | C59: Available | D59: 665000 | E59: Apartment / Flat | F59: NOT STATED | G59: 2 | H59: 1 parking | I59: 47 | J59: NOT STATED | K59: 600 | L59: No | M59: NOT STATED | N59: This 2 Bedroom flat features you with an open plan kitchen, build in cupboards,2 bedrooms,1 bathroom, small patio in a secure complex. | No Pets Allowed | O59: Jason Noel | P59: RealNet South Coast | Q59: NOT CAPTURED (reCAPTCHA) | R59: NOT AVAILABLE (needs phone) | S59: Agent profile | T59: Open listing | U59: 03 July 2026 | V59: 2026-10-08 | W59: =IFERROR(INDEX('Area safety'!$C$23:$C$41,MATCH($B59,'Area safety'!$A$23:$A$41,0)),"n/a") -> Margate | X59: =IFERROR(INDEX('Area safety'!$D$23:$D$41,MATCH($B59,'Area safety'!$A$23:$A$41,0)),"n/a") -> CONFIRMED | Y59: =IFERROR(INDEX('Area safety'!$F$23:$F$41,MATCH($B59,'Area safety'!$A$23:$A$41,0)),"n/a") -> 1154.5136 | Z59: =IFERROR(INDEX('Area safety'!$G$23:$G$41,MATCH($B59,'Area safety'!$A$23:$A$41,0)),"n/a") -> 691.04551 | AA59: =IFERROR(INDEX('Area safety'!$H$23:$H$41,MATCH($B59,'Area safety'!$A$23:$A$41,0)),"n/a") -> 23.900822 | AB59: =IFERROR(INDEX('Area safety'!$I$23:$I$41,MATCH($B59,'Area safety'!$A$23:$A$41,0)),"n/a") -> 4980.7235 | AC59: =IFERROR(INDEX('Area safety'!$F$5:$F$18,MATCH($W59,'Area safety'!$A$5:$A$18,0)),"n/a") -> 4793 | AD59: =IFERROR(INDEX('Area safety'!$G$5:$G$18,MATCH($W59,'Area safety'!$A$5:$A$18,0)),"n/a") -> 23 | AE59: =IFERROR(INDEX('Area safety'!$H$5:$H$18,MATCH($W59,'Area safety'!$A$5:$A$18,0)),"n/a") -> 1111 | AF59: =IFERROR(INDEX('Area safety'!$I$5:$I$18,MATCH($W59,'Area safety'!$A$5:$A$18,0)),"n/a") -> 665 | AG59: =IFERROR(INDEX('Area safety'!$K$23:$K$41,MATCH($B59,'Area safety'!$A$23:$A$41,0)),"n/a") -> 0.099059849 | AH59: =IFERROR(INDEX('Area safety'!$J$23:$J$41,MATCH($B59,'Area safety'!$A$23:$A$41,0)),"n/a") -> 4
A60: Margate | B60: Ramsgate | C60: Available | D60: 750000 | E60: Apartment / Flat | F60: NOT STATED | G60: 2 | H60: 1 parking | I60: 56 | J60: 2400 | K60: 1000 | L60: Yes | M60: NOT STATED | N60: This traditional style block, of just 16 flats, is situated in Ramsgate, bordering Margate, and has direct access to the communal braai area and path | Pet Friendly | O60: Karen Harris | P60: Harcourts Scott Bay | Q60: NOT CAPTURED (reCAPTCHA) | R60: NOT AVAILABLE (needs phone) | S60: Agent profile | T60: Open listing | U60: 07 October 2026 | V60: 2026-10-08 | W60: =IFERROR(INDEX('Area safety'!$C$23:$C$41,MATCH($B60,'Area safety'!$A$23:$A$41,0)),"n/a") -> Margate | X60: =IFERROR(INDEX('Area safety'!$D$23:$D$41,MATCH($B60,'Area safety'!$A$23:$A$41,0)),"n/a") -> CONFIRMED | Y60: =IFERROR(INDEX('Area safety'!$F$23:$F$41,MATCH($B60,'Area safety'!$A$23:$A$41,0)),"n/a") -> 1154.5136 | Z60: =IFERROR(INDEX('Area safety'!$G$23:$G$41,MATCH($B60,'Area safety'!$A$23:$A$41,0)),"n/a") -> 691.04551 | AA60: =IFERROR(INDEX('Area safety'!$H$23:$H$41,MATCH($B60,'Area safety'!$A$23:$A$41,0)),"n/a") -> 23.900822 | AB60: =IFERROR(INDEX('Area safety'!$I$23:$I$41,MATCH($B60,'Area safety'!$A$23:$A$41,0)),"n/a") -> 4980.7235 | AC60: =IFERROR(INDEX('Area safety'!$F$5:$F$18,MATCH($W60,'Area safety'!$A$5:$A$18,0)),"n/a") -> 4793 | AD60: =IFERROR(INDEX('Area safety'!$G$5:$G$18,MATCH($W60,'Area safety'!$A$5:$A$18,0)),"n/a") -> 23 | AE60: =IFERROR(INDEX('Area safety'!$H$5:$H$18,MATCH($W60,'Area safety'!$A$5:$A$18,0)),"n/a") -> 1111 | AF60: =IFERROR(INDEX('Area safety'!$I$5:$I$18,MATCH($W60,'Area safety'!$A$5:$A$18,0)),"n/a") -> 665 | AG60: =IFERROR(INDEX('Area safety'!$K$23:$K$41,MATCH($B60,'Area safety'!$A$23:$A$41,0)),"n/a") -> 0.099059849 | AH60: =IFERROR(INDEX('Area safety'!$J$23:$J$41,MATCH($B60,'Area safety'!$A$23:$A$41,0)),"n/a") -> 4
A61: Margate | B61: Ramsgate | C61: Available | D61: 750000 | E61: Apartment / Flat | F61: Top Floor | G61: 2 | H61: 1 garage | I61: 85 | J61: 1545 | K61: 960 | L61: Yes | M61: Yes | N61: Charming Coastal Living in Ramsgate Discover this delightful two-bedroom top floor residence, perfectly situated in the desirable coastal suburb of Ra | Communal Swimming Pool and Garden, Balcony and Paved Driveway, Pets Allowed, Pet Friendly, Pool, Garden | O61: Pierre Collinette | P61: RE/MAX Coast and Country Southbroom | Q61: NOT CAPTURED (reCAPTCHA) | R61: NOT AVAILABLE (needs phone) | S61: Agent profile | T61: Open listing | U61: 11 May 2026 | V61: 2026-10-08 | W61: =IFERROR(INDEX('Area safety'!$C$23:$C$41,MATCH($B61,'Area safety'!$A$23:$A$41,0)),"n/a") -> Margate | X61: =IFERROR(INDEX('Area safety'!$D$23:$D$41,MATCH($B61,'Area safety'!$A$23:$A$41,0)),"n/a") -> CONFIRMED | Y61: =IFERROR(INDEX('Area safety'!$F$23:$F$41,MATCH($B61,'Area safety'!$A$23:$A$41,0)),"n/a") -> 1154.5136 | Z61: =IFERROR(INDEX('Area safety'!$G$23:$G$41,MATCH($B61,'Area safety'!$A$23:$A$41,0)),"n/a") -> 691.04551 | AA61: =IFERROR(INDEX('Area safety'!$H$23:$H$41,MATCH($B61,'Area safety'!$A$23:$A$41,0)),"n/a") -> 23.900822 | AB61: =IFERROR(INDEX('Area safety'!$I$23:$I$41,MATCH($B61,'Area safety'!$A$23:$A$41,0)),"n/a") -> 4980.7235 | AC61: =IFERROR(INDEX('Area safety'!$F$5:$F$18,MATCH($W61,'Area safety'!$A$5:$A$18,0)),"n/a") -> 4793 | AD61: =IFERROR(INDEX('Area safety'!$G$5:$G$18,MATCH($W61,'Area safety'!$A$5:$A$18,0)),"n/a") -> 23 | AE61: =IFERROR(INDEX('Area safety'!$H$5:$H$18,MATCH($W61,'Area safety'!$A$5:$A$18,0)),"n/a") -> 1111 | AF61: =IFERROR(INDEX('Area safety'!$I$5:$I$18,MATCH($W61,'Area safety'!$A$5:$A$18,0)),"n/a") -> 665 | AG61: =IFERROR(INDEX('Area safety'!$K$23:$K$41,MATCH($B61,'Area safety'!$A$23:$A$41,0)),"n/a") -> 0.099059849 | AH61: =IFERROR(INDEX('Area safety'!$J$23:$J$41,MATCH($B61,'Area safety'!$A$23:$A$41,0)),"n/a") -> 4
A62: Margate | B62: Ramsgate | C62: Available | D62: 750000 | E62: Apartment / Flat | F62: First floor (per description) | G62: 2 | H62: 1 parking | I62: 56 | J62: 2088 | K62: 947 | L62: Yes | M62: NOT STATED | N62: Immaculate Coastal Living: Your Ramsgate Retreat! | Pet Friendly, Garden, Fibre Internet | O62: Ansie Van Der Merwe | P62: RE/MAX Coast and Country Shelly Beach | Q62: NOT CAPTURED (reCAPTCHA) | R62: NOT AVAILABLE (needs phone) | S62: Agent profile | T62: Open listing | U62: 07 September 2025 | V62: 2026-10-08 | W62: =IFERROR(INDEX('Area safety'!$C$23:$C$41,MATCH($B62,'Area safety'!$A$23:$A$41,0)),"n/a") -> Margate | X62: =IFERROR(INDEX('Area safety'!$D$23:$D$41,MATCH($B62,'Area safety'!$A$23:$A$41,0)),"n/a") -> CONFIRMED | Y62: =IFERROR(INDEX('Area safety'!$F$23:$F$41,MATCH($B62,'Area safety'!$A$23:$A$41,0)),"n/a") -> 1154.5136 | Z62: =IFERROR(INDEX('Area safety'!$G$23:$G$41,MATCH($B62,'Area safety'!$A$23:$A$41,0)),"n/a") -> 691.04551 | AA62: =IFERROR(INDEX('Area safety'!$H$23:$H$41,MATCH($B62,'Area safety'!$A$23:$A$41,0)),"n/a") -> 23.900822 | AB62: =IFERROR(INDEX('Area safety'!$I$23:$I$41,MATCH($B62,'Area safety'!$A$23:$A$41,0)),"n/a") -> 4980.7235 | AC62: =IFERROR(INDEX('Area safety'!$F$5:$F$18,MATCH($W62,'Area safety'!$A$5:$A$18,0)),"n/a") -> 4793 | AD62: =IFERROR(INDEX('Area safety'!$G$5:$G$18,MATCH($W62,'Area safety'!$A$5:$A$18,0)),"n/a") -> 23 | AE62: =IFERROR(INDEX('Area safety'!$H$5:$H$18,MATCH($W62,'Area safety'!$A$5:$A$18,0)),"n/a") -> 1111 | AF62: =IFERROR(INDEX('Area safety'!$I$5:$I$18,MATCH($W62,'Area safety'!$A$5:$A$18,0)),"n/a") -> 665 | AG62: =IFERROR(INDEX('Area safety'!$K$23:$K$41,MATCH($B62,'Area safety'!$A$23:$A$41,0)),"n/a") -> 0.099059849 | AH62: =IFERROR(INDEX('Area safety'!$J$23:$J$41,MATCH($B62,'Area safety'!$A$23:$A$41,0)),"n/a") -> 4
A63: Margate | B63: Margate | C63: Available | D63: 530000 | E63: Apartment / Flat | F63: NOT STATED | G63: 2 | H63: 1 parking | I63: 54 | J63: 588 | K63: 600 | L63: NOT STATED | M63: NOT STATED | N63: This 2-bedroom, 1-bathroom apartment is ideally positioned in the heart of Margate town, above popular restaurants and within easy walking distance to the beach. | O63: Fathima Raja | P63: Pam Golding Properties - Port Shepstone / Margate | Q63: NOT CAPTURED (reCAPTCHA) | R63: NOT AVAILABLE (needs phone) | S63: Agent profile | T63: Open listing | U63: 03 March 2026 | V63: 2026-10-08 | W63: =IFERROR(INDEX('Area safety'!$C$23:$C$41,MATCH($B63,'Area safety'!$A$23:$A$41,0)),"n/a") -> Margate | X63: =IFERROR(INDEX('Area safety'!$D$23:$D$41,MATCH($B63,'Area safety'!$A$23:$A$41,0)),"n/a") -> CONFIRMED | Y63: =IFERROR(INDEX('Area safety'!$F$23:$F$41,MATCH($B63,'Area safety'!$A$23:$A$41,0)),"n/a") -> 1154.5136 | Z63: =IFERROR(INDEX('Area safety'!$G$23:$G$41,MATCH($B63,'Area safety'!$A$23:$A$41,0)),"n/a") -> 691.04551 | AA63: =IFERROR(INDEX('Area safety'!$H$23:$H$41,MATCH($B63,'Area safety'!$A$23:$A$41,0)),"n/a") -> 23.900822 | AB63: =IFERROR(INDEX('Area safety'!$I$23:$I$41,MATCH($B63,'Area safety'!$A$23:$A$41,0)),"n/a") -> 4980.7235 | AC63: =IFERROR(INDEX('Area safety'!$F$5:$F$18,MATCH($W63,'Area safety'!$A$5:$A$18,0)),"n/a") -> 4793 | AD63: =IFERROR(INDEX('Area safety'!$G$5:$G$18,MATCH($W63,'Area safety'!$A$5:$A$18,0)),"n/a") -> 23 | AE63: =IFERROR(INDEX('Area safety'!$H$5:$H$18,MATCH($W63,'Area safety'!$A$5:$A$18,0)),"n/a") -> 1111 | AF63: =IFERROR(INDEX('Area safety'!$I$5:$I$18,MATCH($W63,'Area safety'!$A$5:$A$18,0)),"n/a") -> 665 | AG63: =IFERROR(INDEX('Area safety'!$K$23:$K$41,MATCH($B63,'Area safety'!$A$23:$A$41,0)),"n/a") -> 0.099059849 | AH63: =IFERROR(INDEX('Area safety'!$J$23:$J$41,MATCH($B63,'Area safety'!$A$23:$A$41,0)),"n/a") -> 4
A64: Margate | B64: Margate | C64: Available | D64: 535000 | E64: Apartment / Flat | F64: First Floor | G64: 2 | H64: NOT STATED | I64: 58 | J64: NOT STATED | K64: 620 | L64: No | M64: Yes | N64: Situated in a well sought-after area of Margate, this neat and fully furnished flat offers comfortable coastal living with a peaceful garden setting. | No Pets Allowed, Garden | O64: Carolina Choles | P64: Mandated | Q64: NOT CAPTURED (reCAPTCHA) | R64: NOT AVAILABLE (needs phone) | S64: Agent profile | T64: Open listing | U64: 18 May 2026 | V64: 2026-10-08 | W64: =IFERROR(INDEX('Area safety'!$C$23:$C$41,MATCH($B64,'Area safety'!$A$23:$A$41,0)),"n/a") -> Margate | X64: =IFERROR(INDEX('Area safety'!$D$23:$D$41,MATCH($B64,'Area safety'!$A$23:$A$41,0)),"n/a") -> CONFIRMED | Y64: =IFERROR(INDEX('Area safety'!$F$23:$F$41,MATCH($B64,'Area safety'!$A$23:$A$41,0)),"n/a") -> 1154.5136 | Z64: =IFERROR(INDEX('Area safety'!$G$23:$G$41,MATCH($B64,'Area safety'!$A$23:$A$41,0)),"n/a") -> 691.04551 | AA64: =IFERROR(INDEX('Area safety'!$H$23:$H$41,MATCH($B64,'Area safety'!$A$23:$A$41,0)),"n/a") -> 23.900822 | AB64: =IFERROR(INDEX('Area safety'!$I$23:$I$41,MATCH($B64,'Area safety'!$A$23:$A$41,0)),"n/a") -> 4980.7235 | AC64: =IFERROR(INDEX('Area safety'!$F$5:$F$18,MATCH($W64,'Area safety'!$A$5:$A$18,0)),"n/a") -> 4793 | AD64: =IFERROR(INDEX('Area safety'!$G$5:$G$18,MATCH($W64,'Area safety'!$A$5:$A$18,0)),"n/a") -> 23 | AE64: =IFERROR(INDEX('Area safety'!$H$5:$H$18,MATCH($W64,'Area safety'!$A$5:$A$18,0)),"n/a") -> 1111 | AF64: =IFERROR(INDEX('Area safety'!$I$5:$I$18,MATCH($W64,'Area safety'!$A$5:$A$18,0)),"n/a") -> 665 | AG64: =IFERROR(INDEX('Area safety'!$K$23:$K$41,MATCH($B64,'Area safety'!$A$23:$A$41,0)),"n/a") -> 0.099059849 | AH64: =IFERROR(INDEX('Area safety'!$J$23:$J$41,MATCH($B64,'Area safety'!$A$23:$A$41,0)),"n/a") -> 4
A65: Margate | B65: Margate | C65: Available | D65: 570000 | E65: Apartment / Flat | F65: Second floor and above | G65: 2 | H65: 1 garage | I65: 61 | J65: 1200 | K65: 600 | L65: NOT STATED | M65: NOT STATED | N65: Location, convenience and affordability – this is Margate living made simple. | Garden | O65: Nolene Fuhri | P65: Property Port | Q65: NOT CAPTURED (reCAPTCHA) | R65: NOT AVAILABLE (needs phone) | S65: Agent profile | T65: Open listing | U65: 07 October 2026 | V65: 2026-10-08 | W65: =IFERROR(INDEX('Area safety'!$C$23:$C$41,MATCH($B65,'Area safety'!$A$23:$A$41,0)),"n/a") -> Margate | X65: =IFERROR(INDEX('Area safety'!$D$23:$D$41,MATCH($B65,'Area safety'!$A$23:$A$41,0)),"n/a") -> CONFIRMED | Y65: =IFERROR(INDEX('Area safety'!$F$23:$F$41,MATCH($B65,'Area safety'!$A$23:$A$41,0)),"n/a") -> 1154.5136 | Z65: =IFERROR(INDEX('Area safety'!$G$23:$G$41,MATCH($B65,'Area safety'!$A$23:$A$41,0)),"n/a") -> 691.04551 | AA65: =IFERROR(INDEX('Area safety'!$H$23:$H$41,MATCH($B65,'Area safety'!$A$23:$A$41,0)),"n/a") -> 23.900822 | AB65: =IFERROR(INDEX('Area safety'!$I$23:$I$41,MATCH($B65,'Area safety'!$A$23:$A$41,0)),"n/a") -> 4980.7235 | AC65: =IFERROR(INDEX('Area safety'!$F$5:$F$18,MATCH($W65,'Area safety'!$A$5:$A$18,0)),"n/a") -> 4793 | AD65: =IFERROR(INDEX('Area safety'!$G$5:$G$18,MATCH($W65,'Area safety'!$A$5:$A$18,0)),"n/a") -> 23 | AE65: =IFERROR(INDEX('Area safety'!$H$5:$H$18,MATCH($W65,'Area safety'!$A$5:$A$18,0)),"n/a") -> 1111 | AF65: =IFERROR(INDEX('Area safety'!$I$5:$I$18,MATCH($W65,'Area safety'!$A$5:$A$18,0)),"n/a") -> 665 | AG65: =IFERROR(INDEX('Area safety'!$K$23:$K$41,MATCH($B65,'Area safety'!$A$23:$A$41,0)),"n/a") -> 0.099059849 | AH65: =IFERROR(INDEX('Area safety'!$J$23:$J$41,MATCH($B65,'Area safety'!$A$23:$A$41,0)),"n/a") -> 4
A66: Margate | B66: Margate | C66: Available | D66: 570000 | E66: Apartment / Flat | F66: NOT STATED | G66: 2 | H66: 1 garage | I66: 61 | J66: 1200 | K66: 600 | L66: NOT STATED | M66: NOT STATED | N66: Welcome to your urban retreat, this charming, compact apartment is the ideal space for anyone seeking the convenience of city living without compromis | Garden | O66: Nomini Mbasane | P66: Pam Golding Properties - Port Shepstone / Margate | Q66: NOT CAPTURED (reCAPTCHA) | R66: NOT AVAILABLE (needs phone) | S66: Agent profile | T66: Open listing | U66: 27 March 2025 | V66: 2026-10-08 | W66: =IFERROR(INDEX('Area safety'!$C$23:$C$41,MATCH($B66,'Area safety'!$A$23:$A$41,0)),"n/a") -> Margate | X66: =IFERROR(INDEX('Area safety'!$D$23:$D$41,MATCH($B66,'Area safety'!$A$23:$A$41,0)),"n/a") -> CONFIRMED | Y66: =IFERROR(INDEX('Area safety'!$F$23:$F$41,MATCH($B66,'Area safety'!$A$23:$A$41,0)),"n/a") -> 1154.5136 | Z66: =IFERROR(INDEX('Area safety'!$G$23:$G$41,MATCH($B66,'Area safety'!$A$23:$A$41,0)),"n/a") -> 691.04551 | AA66: =IFERROR(INDEX('Area safety'!$H$23:$H$41,MATCH($B66,'Area safety'!$A$23:$A$41,0)),"n/a") -> 23.900822 | AB66: =IFERROR(INDEX('Area safety'!$I$23:$I$41,MATCH($B66,'Area safety'!$A$23:$A$41,0)),"n/a") -> 4980.7235 | AC66: =IFERROR(INDEX('Area safety'!$F$5:$F$18,MATCH($W66,'Area safety'!$A$5:$A$18,0)),"n/a") -> 4793 | AD66: =IFERROR(INDEX('Area safety'!$G$5:$G$18,MATCH($W66,'Area safety'!$A$5:$A$18,0)),"n/a") -> 23 | AE66: =IFERROR(INDEX('Area safety'!$H$5:$H$18,MATCH($W66,'Area safety'!$A$5:$A$18,0)),"n/a") -> 1111 | AF66: =IFERROR(INDEX('Area safety'!$I$5:$I$18,MATCH($W66,'Area safety'!$A$5:$A$18,0)),"n/a") -> 665 | AG66: =IFERROR(INDEX('Area safety'!$K$23:$K$41,MATCH($B66,'Area safety'!$A$23:$A$41,0)),"n/a") -> 0.099059849 | AH66: =IFERROR(INDEX('Area safety'!$J$23:$J$41,MATCH($B66,'Area safety'!$A$23:$A$41,0)),"n/a") -> 4
A67: Margate | B67: Margate | C67: Available | D67: 590000 | E67: Apartment / Flat | F67: NOT STATED | G67: 2 | H67: 1 garage | I67: 57 | J67: 1021 | K67: 908 | L67: NOT STATED | M67: NOT STATED | N67: Authority to sell. Bargain buy!! | O67: Retha Kelly | P67: Home Finders Coastal | Q67: NOT CAPTURED (reCAPTCHA) | R67: NOT AVAILABLE (needs phone) | S67: Agent profile | T67: Open listing | U67: 07 September 2026 | V67: 2026-10-08 | W67: =IFERROR(INDEX('Area safety'!$C$23:$C$41,MATCH($B67,'Area safety'!$A$23:$A$41,0)),"n/a") -> Margate | X67: =IFERROR(INDEX('Area safety'!$D$23:$D$41,MATCH($B67,'Area safety'!$A$23:$A$41,0)),"n/a") -> CONFIRMED | Y67: =IFERROR(INDEX('Area safety'!$F$23:$F$41,MATCH($B67,'Area safety'!$A$23:$A$41,0)),"n/a") -> 1154.5136 | Z67: =IFERROR(INDEX('Area safety'!$G$23:$G$41,MATCH($B67,'Area safety'!$A$23:$A$41,0)),"n/a") -> 691.04551 | AA67: =IFERROR(INDEX('Area safety'!$H$23:$H$41,MATCH($B67,'Area safety'!$A$23:$A$41,0)),"n/a") -> 23.900822 | AB67: =IFERROR(INDEX('Area safety'!$I$23:$I$41,MATCH($B67,'Area safety'!$A$23:$A$41,0)),"n/a") -> 4980.7235 | AC67: =IFERROR(INDEX('Area safety'!$F$5:$F$18,MATCH($W67,'Area safety'!$A$5:$A$18,0)),"n/a") -> 4793 | AD67: =IFERROR(INDEX('Area safety'!$G$5:$G$18,MATCH($W67,'Area safety'!$A$5:$A$18,0)),"n/a") -> 23 | AE67: =IFERROR(INDEX('Area safety'!$H$5:$H$18,MATCH($W67,'Area safety'!$A$5:$A$18,0)),"n/a") -> 1111 | AF67: =IFERROR(INDEX('Area safety'!$I$5:$I$18,MATCH($W67,'Area safety'!$A$5:$A$18,0)),"n/a") -> 665 | AG67: =IFERROR(INDEX('Area safety'!$K$23:$K$41,MATCH($B67,'Area safety'!$A$23:$A$41,0)),"n/a") -> 0.099059849 | AH67: =IFERROR(INDEX('Area safety'!$J$23:$J$41,MATCH($B67,'Area safety'!$A$23:$A$41,0)),"n/a") -> 4
A68: Margate | B68: Margate | C68: Available | D68: 595000 | E68: Apartment / Flat | F68: NOT STATED | G68: 2 | H68: 1 garage | I68: 91 | J68: 2900 | K68: 730 | L68: No | M68: Yes | N68: This great 2-bedroom duplex unit is for sale in Margate. | No Pets Allowed | O68: Lorraine Ferreira | P68: Mandated | Q68: NOT CAPTURED (reCAPTCHA) | R68: NOT AVAILABLE (needs phone) | S68: Agent profile | T68: Open listing | U68: 20 May 2025 | V68: 2026-10-08 | W68: =IFERROR(INDEX('Area safety'!$C$23:$C$41,MATCH($B68,'Area safety'!$A$23:$A$41,0)),"n/a") -> Margate | X68: =IFERROR(INDEX('Area safety'!$D$23:$D$41,MATCH($B68,'Area safety'!$A$23:$A$41,0)),"n/a") -> CONFIRMED | Y68: =IFERROR(INDEX('Area safety'!$F$23:$F$41,MATCH($B68,'Area safety'!$A$23:$A$41,0)),"n/a") -> 1154.5136 | Z68: =IFERROR(INDEX('Area safety'!$G$23:$G$41,MATCH($B68,'Area safety'!$A$23:$A$41,0)),"n/a") -> 691.04551 | AA68: =IFERROR(INDEX('Area safety'!$H$23:$H$41,MATCH($B68,'Area safety'!$A$23:$A$41,0)),"n/a") -> 23.900822 | AB68: =IFERROR(INDEX('Area safety'!$I$23:$I$41,MATCH($B68,'Area safety'!$A$23:$A$41,0)),"n/a") -> 4980.7235 | AC68: =IFERROR(INDEX('Area safety'!$F$5:$F$18,MATCH($W68,'Area safety'!$A$5:$A$18,0)),"n/a") -> 4793 | AD68: =IFERROR(INDEX('Area safety'!$G$5:$G$18,MATCH($W68,'Area safety'!$A$5:$A$18,0)),"n/a") -> 23 | AE68: =IFERROR(INDEX('Area safety'!$H$5:$H$18,MATCH($W68,'Area safety'!$A$5:$A$18,0)),"n/a") -> 1111 | AF68: =IFERROR(INDEX('Area safety'!$I$5:$I$18,MATCH($W68,'Area safety'!$A$5:$A$18,0)),"n/a") -> 665 | AG68: =IFERROR(INDEX('Area safety'!$K$23:$K$41,MATCH($B68,'Area safety'!$A$23:$A$41,0)),"n/a") -> 0.099059849 | AH68: =IFERROR(INDEX('Area safety'!$J$23:$J$41,MATCH($B68,'Area safety'!$A$23:$A$41,0)),"n/a") -> 4
A69: Margate | B69: Margate | C69: Available | D69: 600000 | E69: Apartment / Flat | F69: NOT STATED | G69: 2 | H69: 1 parking | I69: 98 | J69: NOT STATED | K69: NOT STATED | L69: NOT STATED | M69: NOT STATED | N69: 2 Bedrooms | 2 Bathrooms | Secure Parking | Lift Access Ideally situated in the heart of Margate Central, this neat and well-maintained apartment offe | O69: Nomini Mbasane | P69: Pam Golding Properties - Port Shepstone / Margate | Q69: NOT CAPTURED (reCAPTCHA) | R69: NOT AVAILABLE (needs phone) | S69: Agent profile | T69: Open listing | U69: 16 July 2026 | V69: 2026-10-08 | W69: =IFERROR(INDEX('Area safety'!$C$23:$C$41,MATCH($B69,'Area safety'!$A$23:$A$41,0)),"n/a") -> Margate | X69: =IFERROR(INDEX('Area safety'!$D$23:$D$41,MATCH($B69,'Area safety'!$A$23:$A$41,0)),"n/a") -> CONFIRMED | Y69: =IFERROR(INDEX('Area safety'!$F$23:$F$41,MATCH($B69,'Area safety'!$A$23:$A$41,0)),"n/a") -> 1154.5136 | Z69: =IFERROR(INDEX('Area safety'!$G$23:$G$41,MATCH($B69,'Area safety'!$A$23:$A$41,0)),"n/a") -> 691.04551 | AA69: =IFERROR(INDEX('Area safety'!$H$23:$H$41,MATCH($B69,'Area safety'!$A$23:$A$41,0)),"n/a") -> 23.900822 | AB69: =IFERROR(INDEX('Area safety'!$I$23:$I$41,MATCH($B69,'Area safety'!$A$23:$A$41,0)),"n/a") -> 4980.7235 | AC69: =IFERROR(INDEX('Area safety'!$F$5:$F$18,MATCH($W69,'Area safety'!$A$5:$A$18,0)),"n/a") -> 4793 | AD69: =IFERROR(INDEX('Area safety'!$G$5:$G$18,MATCH($W69,'Area safety'!$A$5:$A$18,0)),"n/a") -> 23 | AE69: =IFERROR(INDEX('Area safety'!$H$5:$H$18,MATCH($W69,'Area safety'!$A$5:$A$18,0)),"n/a") -> 1111 | AF69: =IFERROR(INDEX('Area safety'!$I$5:$I$18,MATCH($W69,'Area safety'!$A$5:$A$18,0)),"n/a") -> 665 | AG69: =IFERROR(INDEX('Area safety'!$K$23:$K$41,MATCH($B69,'Area safety'!$A$23:$A$41,0)),"n/a") -> 0.099059849 | AH69: =IFERROR(INDEX('Area safety'!$J$23:$J$41,MATCH($B69,'Area safety'!$A$23:$A$41,0)),"n/a") -> 4
A70: Margate | B70: Margate | C70: Available | D70: 600000 | E70: Apartment / Flat | F70: Single Storey, Second floor and above | G70: 2 | H70: 1 garage | I70: 98 | J70: NOT STATED | K70: 1258 | L70: No | M70: NOT STATED | N70: Two bedroom two bathroom unit walking distance from margate main beach for sale Two bedroom two bathroom unit walking distance from margate main beach | No Pets Allowed | O70: Lizette Venter | P70: EXP South Africa | Q70: NOT CAPTURED (reCAPTCHA) | R70: NOT AVAILABLE (needs phone) | S70: Agent profile | T70: Open listing | U70: 17 August 2026 | V70: 2026-10-08 | W70: =IFERROR(INDEX('Area safety'!$C$23:$C$41,MATCH($B70,'Area safety'!$A$23:$A$41,0)),"n/a") -> Margate | X70: =IFERROR(INDEX('Area safety'!$D$23:$D$41,MATCH($B70,'Area safety'!$A$23:$A$41,0)),"n/a") -> CONFIRMED | Y70: =IFERROR(INDEX('Area safety'!$F$23:$F$41,MATCH($B70,'Area safety'!$A$23:$A$41,0)),"n/a") -> 1154.5136 | Z70: =IFERROR(INDEX('Area safety'!$G$23:$G$41,MATCH($B70,'Area safety'!$A$23:$A$41,0)),"n/a") -> 691.04551 | AA70: =IFERROR(INDEX('Area safety'!$H$23:$H$41,MATCH($B70,'Area safety'!$A$23:$A$41,0)),"n/a") -> 23.900822 | AB70: =IFERROR(INDEX('Area safety'!$I$23:$I$41,MATCH($B70,'Area safety'!$A$23:$A$41,0)),"n/a") -> 4980.7235 | AC70: =IFERROR(INDEX('Area safety'!$F$5:$F$18,MATCH($W70,'Area safety'!$A$5:$A$18,0)),"n/a") -> 4793 | AD70: =IFERROR(INDEX('Area safety'!$G$5:$G$18,MATCH($W70,'Area safety'!$A$5:$A$18,0)),"n/a") -> 23 | AE70: =IFERROR(INDEX('Area safety'!$H$5:$H$18,MATCH($W70,'Area safety'!$A$5:$A$18,0)),"n/a") -> 1111 | AF70: =IFERROR(INDEX('Area safety'!$I$5:$I$18,MATCH($W70,'Area safety'!$A$5:$A$18,0)),"n/a") -> 665 | AG70: =IFERROR(INDEX('Area safety'!$K$23:$K$41,MATCH($B70,'Area safety'!$A$23:$A$41,0)),"n/a") -> 0.099059849 | AH70: =IFERROR(INDEX('Area safety'!$J$23:$J$41,MATCH($B70,'Area safety'!$A$23:$A$41,0)),"n/a") -> 4
A71: Margate | B71: Margate | C71: Available | D71: 600000 | E71: Apartment / Flat | F71: Second floor and above | G71: 2 | H71: 1 garage | I71: 98 | J71: 1200 | K71: 220 | L71: No | M71: NOT STATED | N71: Experience the quintessential coastal lifestyle with this apartment situated in the heart of Margate. | No Pets Allowed | O71: Lorraine Ferreira | P71: Mandated | Q71: NOT CAPTURED (reCAPTCHA) | R71: NOT AVAILABLE (needs phone) | S71: Agent profile | T71: Open listing | U71: 22 July 2026 | V71: 2026-10-08 | W71: =IFERROR(INDEX('Area safety'!$C$23:$C$41,MATCH($B71,'Area safety'!$A$23:$A$41,0)),"n/a") -> Margate | X71: =IFERROR(INDEX('Area safety'!$D$23:$D$41,MATCH($B71,'Area safety'!$A$23:$A$41,0)),"n/a") -> CONFIRMED | Y71: =IFERROR(INDEX('Area safety'!$F$23:$F$41,MATCH($B71,'Area safety'!$A$23:$A$41,0)),"n/a") -> 1154.5136 | Z71: =IFERROR(INDEX('Area safety'!$G$23:$G$41,MATCH($B71,'Area safety'!$A$23:$A$41,0)),"n/a") -> 691.04551 | AA71: =IFERROR(INDEX('Area safety'!$H$23:$H$41,MATCH($B71,'Area safety'!$A$23:$A$41,0)),"n/a") -> 23.900822 | AB71: =IFERROR(INDEX('Area safety'!$I$23:$I$41,MATCH($B71,'Area safety'!$A$23:$A$41,0)),"n/a") -> 4980.7235 | AC71: =IFERROR(INDEX('Area safety'!$F$5:$F$18,MATCH($W71,'Area safety'!$A$5:$A$18,0)),"n/a") -> 4793 | AD71: =IFERROR(INDEX('Area safety'!$G$5:$G$18,MATCH($W71,'Area safety'!$A$5:$A$18,0)),"n/a") -> 23 | AE71: =IFERROR(INDEX('Area safety'!$H$5:$H$18,MATCH($W71,'Area safety'!$A$5:$A$18,0)),"n/a") -> 1111 | AF71: =IFERROR(INDEX('Area safety'!$I$5:$I$18,MATCH($W71,'Area safety'!$A$5:$A$18,0)),"n/a") -> 665 | AG71: =IFERROR(INDEX('Area safety'!$K$23:$K$41,MATCH($B71,'Area safety'!$A$23:$A$41,0)),"n/a") -> 0.099059849 | AH71: =IFERROR(INDEX('Area safety'!$J$23:$J$41,MATCH($B71,'Area safety'!$A$23:$A$41,0)),"n/a") -> 4
A72: Margate | B72: Margate | C72: Available | D72: 650000 | E72: Apartment / Flat | F72: Second floor (per description) | G72: 2 | H72: 1 garage | I72: 17 | J72: 2000 | K72: 650 | L72: NOT STATED | M72: NOT STATED | N72: ositioned in one of Margate’s most sought-after coastal locations, this well-maintained two-bedroom apartment offers an exceptional opportunity for pe | O72: Yolandi Du Plooy | P72: Pam Golding Properties - Port Shepstone / Margate | Q72: NOT CAPTURED (reCAPTCHA) | R72: NOT AVAILABLE (needs phone) | S72: Agent profile | T72: Open listing | U72: 28 September 2026 | V72: 2026-10-08 | W72: =IFERROR(INDEX('Area safety'!$C$23:$C$41,MATCH($B72,'Area safety'!$A$23:$A$41,0)),"n/a") -> Margate | X72: =IFERROR(INDEX('Area safety'!$D$23:$D$41,MATCH($B72,'Area safety'!$A$23:$A$41,0)),"n/a") -> CONFIRMED | Y72: =IFERROR(INDEX('Area safety'!$F$23:$F$41,MATCH($B72,'Area safety'!$A$23:$A$41,0)),"n/a") -> 1154.5136 | Z72: =IFERROR(INDEX('Area safety'!$G$23:$G$41,MATCH($B72,'Area safety'!$A$23:$A$41,0)),"n/a") -> 691.04551 | AA72: =IFERROR(INDEX('Area safety'!$H$23:$H$41,MATCH($B72,'Area safety'!$A$23:$A$41,0)),"n/a") -> 23.900822 | AB72: =IFERROR(INDEX('Area safety'!$I$23:$I$41,MATCH($B72,'Area safety'!$A$23:$A$41,0)),"n/a") -> 4980.7235 | AC72: =IFERROR(INDEX('Area safety'!$F$5:$F$18,MATCH($W72,'Area safety'!$A$5:$A$18,0)),"n/a") -> 4793 | AD72: =IFERROR(INDEX('Area safety'!$G$5:$G$18,MATCH($W72,'Area safety'!$A$5:$A$18,0)),"n/a") -> 23 | AE72: =IFERROR(INDEX('Area safety'!$H$5:$H$18,MATCH($W72,'Area safety'!$A$5:$A$18,0)),"n/a") -> 1111 | AF72: =IFERROR(INDEX('Area safety'!$I$5:$I$18,MATCH($W72,'Area safety'!$A$5:$A$18,0)),"n/a") -> 665 | AG72: =IFERROR(INDEX('Area safety'!$K$23:$K$41,MATCH($B72,'Area safety'!$A$23:$A$41,0)),"n/a") -> 0.099059849 | AH72: =IFERROR(INDEX('Area safety'!$J$23:$J$41,MATCH($B72,'Area safety'!$A$23:$A$41,0)),"n/a") -> 4
A73: Margate | B73: Margate | C73: Available | D73: 650000 | E73: Apartment / Flat | F73: Floor 3 | G73: 2 | H73: 1 garage | I73: 96 | J73: 1200 | K73: 550 | L73: NOT STATED | M73: NOT STATED | N73: PERFECT INVESTMENT * MARGATE CBD LOCATION * RENTAL INCOME OPPORTUNITY * RETIREMENT * FIRST INVESTMENT * MOVE IN READY Margate is a well-known holiday | O73: Johann Nieuwoudt | P73: EXP South Africa | Q73: NOT CAPTURED (reCAPTCHA) | R73: NOT AVAILABLE (needs phone) | S73: Agent profile | T73: Open listing | U73: 11 September 2026 | V73: 2026-10-08 | W73: =IFERROR(INDEX('Area safety'!$C$23:$C$41,MATCH($B73,'Area safety'!$A$23:$A$41,0)),"n/a") -> Margate | X73: =IFERROR(INDEX('Area safety'!$D$23:$D$41,MATCH($B73,'Area safety'!$A$23:$A$41,0)),"n/a") -> CONFIRMED | Y73: =IFERROR(INDEX('Area safety'!$F$23:$F$41,MATCH($B73,'Area safety'!$A$23:$A$41,0)),"n/a") -> 1154.5136 | Z73: =IFERROR(INDEX('Area safety'!$G$23:$G$41,MATCH($B73,'Area safety'!$A$23:$A$41,0)),"n/a") -> 691.04551 | AA73: =IFERROR(INDEX('Area safety'!$H$23:$H$41,MATCH($B73,'Area safety'!$A$23:$A$41,0)),"n/a") -> 23.900822 | AB73: =IFERROR(INDEX('Area safety'!$I$23:$I$41,MATCH($B73,'Area safety'!$A$23:$A$41,0)),"n/a") -> 4980.7235 | AC73: =IFERROR(INDEX('Area safety'!$F$5:$F$18,MATCH($W73,'Area safety'!$A$5:$A$18,0)),"n/a") -> 4793 | AD73: =IFERROR(INDEX('Area safety'!$G$5:$G$18,MATCH($W73,'Area safety'!$A$5:$A$18,0)),"n/a") -> 23 | AE73: =IFERROR(INDEX('Area safety'!$H$5:$H$18,MATCH($W73,'Area safety'!$A$5:$A$18,0)),"n/a") -> 1111 | AF73: =IFERROR(INDEX('Area safety'!$I$5:$I$18,MATCH($W73,'Area safety'!$A$5:$A$18,0)),"n/a") -> 665 | AG73: =IFERROR(INDEX('Area safety'!$K$23:$K$41,MATCH($B73,'Area safety'!$A$23:$A$41,0)),"n/a") -> 0.099059849 | AH73: =IFERROR(INDEX('Area safety'!$J$23:$J$41,MATCH($B73,'Area safety'!$A$23:$A$41,0)),"n/a") -> 4
A74: Margate | B74: Margate | C74: Available | D74: 650000 | E74: Apartment / Flat | F74: NOT STATED | G74: 2 | H74: NOT STATED | I74: 71 | J74: 1800 | K74: 600 | L74: No | M74: NOT STATED | N74: It's that easy!! This well maintained complex is located in Manaba, a small holiday town nestled in between the well-known towns of Uvongo and Margate | No Pets Allowed | O74: Precious Lupindo | P74: RealNet South Coast | Q74: NOT CAPTURED (reCAPTCHA) | R74: NOT AVAILABLE (needs phone) | S74: Agent profile | T74: Open listing | U74: 27 July 2026 | V74: 2026-10-08 | W74: =IFERROR(INDEX('Area safety'!$C$23:$C$41,MATCH($B74,'Area safety'!$A$23:$A$41,0)),"n/a") -> Margate | X74: =IFERROR(INDEX('Area safety'!$D$23:$D$41,MATCH($B74,'Area safety'!$A$23:$A$41,0)),"n/a") -> CONFIRMED | Y74: =IFERROR(INDEX('Area safety'!$F$23:$F$41,MATCH($B74,'Area safety'!$A$23:$A$41,0)),"n/a") -> 1154.5136 | Z74: =IFERROR(INDEX('Area safety'!$G$23:$G$41,MATCH($B74,'Area safety'!$A$23:$A$41,0)),"n/a") -> 691.04551 | AA74: =IFERROR(INDEX('Area safety'!$H$23:$H$41,MATCH($B74,'Area safety'!$A$23:$A$41,0)),"n/a") -> 23.900822 | AB74: =IFERROR(INDEX('Area safety'!$I$23:$I$41,MATCH($B74,'Area safety'!$A$23:$A$41,0)),"n/a") -> 4980.7235 | AC74: =IFERROR(INDEX('Area safety'!$F$5:$F$18,MATCH($W74,'Area safety'!$A$5:$A$18,0)),"n/a") -> 4793 | AD74: =IFERROR(INDEX('Area safety'!$G$5:$G$18,MATCH($W74,'Area safety'!$A$5:$A$18,0)),"n/a") -> 23 | AE74: =IFERROR(INDEX('Area safety'!$H$5:$H$18,MATCH($W74,'Area safety'!$A$5:$A$18,0)),"n/a") -> 1111 | AF74: =IFERROR(INDEX('Area safety'!$I$5:$I$18,MATCH($W74,'Area safety'!$A$5:$A$18,0)),"n/a") -> 665 | AG74: =IFERROR(INDEX('Area safety'!$K$23:$K$41,MATCH($B74,'Area safety'!$A$23:$A$41,0)),"n/a") -> 0.099059849 | AH74: =IFERROR(INDEX('Area safety'!$J$23:$J$41,MATCH($B74,'Area safety'!$A$23:$A$41,0)),"n/a") -> 4
A75: Margate | B75: Margate | C75: Available | D75: 650000 | E75: Apartment / Flat | F75: 2nd floor (per description) | G75: 2 | H75: 1 garage | I75: 93 | J75: 200 | K75: 650 | L75: Yes | M75: NOT STATED | N75: This well maintained 2 bedroom unit located in the bustling heart of the town of Margate has recently entered the market ,its location makes it one of | Pet Friendly | O75: Riette Vorster | P75: Wakefields Estate Agents Shelly Beach | Q75: NOT CAPTURED (reCAPTCHA) | R75: NOT AVAILABLE (needs phone) | S75: Agent profile | T75: Open listing | U75: 16 January 2025 | V75: 2026-10-08 | W75: =IFERROR(INDEX('Area safety'!$C$23:$C$41,MATCH($B75,'Area safety'!$A$23:$A$41,0)),"n/a") -> Margate | X75: =IFERROR(INDEX('Area safety'!$D$23:$D$41,MATCH($B75,'Area safety'!$A$23:$A$41,0)),"n/a") -> CONFIRMED | Y75: =IFERROR(INDEX('Area safety'!$F$23:$F$41,MATCH($B75,'Area safety'!$A$23:$A$41,0)),"n/a") -> 1154.5136 | Z75: =IFERROR(INDEX('Area safety'!$G$23:$G$41,MATCH($B75,'Area safety'!$A$23:$A$41,0)),"n/a") -> 691.04551 | AA75: =IFERROR(INDEX('Area safety'!$H$23:$H$41,MATCH($B75,'Area safety'!$A$23:$A$41,0)),"n/a") -> 23.900822 | AB75: =IFERROR(INDEX('Area safety'!$I$23:$I$41,MATCH($B75,'Area safety'!$A$23:$A$41,0)),"n/a") -> 4980.7235 | AC75: =IFERROR(INDEX('Area safety'!$F$5:$F$18,MATCH($W75,'Area safety'!$A$5:$A$18,0)),"n/a") -> 4793 | AD75: =IFERROR(INDEX('Area safety'!$G$5:$G$18,MATCH($W75,'Area safety'!$A$5:$A$18,0)),"n/a") -> 23 | AE75: =IFERROR(INDEX('Area safety'!$H$5:$H$18,MATCH($W75,'Area safety'!$A$5:$A$18,0)),"n/a") -> 1111 | AF75: =IFERROR(INDEX('Area safety'!$I$5:$I$18,MATCH($W75,'Area safety'!$A$5:$A$18,0)),"n/a") -> 665 | AG75: =IFERROR(INDEX('Area safety'!$K$23:$K$41,MATCH($B75,'Area safety'!$A$23:$A$41,0)),"n/a") -> 0.099059849 | AH75: =IFERROR(INDEX('Area safety'!$J$23:$J$41,MATCH($B75,'Area safety'!$A$23:$A$41,0)),"n/a") -> 4
A76: Margate | B76: Margate | C76: Available | D76: 650000 | E76: Apartment / Flat | F76: NOT STATED | G76: 2 | H76: NOT STATED | I76: 86 | J76: 1200 | K76: 600 | L76: NOT STATED | M76: NOT STATED | N76: This beautiful apartment which is a stone throw away from the beach consists of 2 spacious bedroom of which one has an end suite, fully fitted kitchen | O76: Prince Ngxolashe | P76: Chas Everitt KZN South Coast | Q76: NOT CAPTURED (reCAPTCHA) | R76: NOT AVAILABLE (needs phone) | S76: Agent profile | T76: Open listing | U76: 12 July 2026 | V76: 2026-10-08 | W76: =IFERROR(INDEX('Area safety'!$C$23:$C$41,MATCH($B76,'Area safety'!$A$23:$A$41,0)),"n/a") -> Margate | X76: =IFERROR(INDEX('Area safety'!$D$23:$D$41,MATCH($B76,'Area safety'!$A$23:$A$41,0)),"n/a") -> CONFIRMED | Y76: =IFERROR(INDEX('Area safety'!$F$23:$F$41,MATCH($B76,'Area safety'!$A$23:$A$41,0)),"n/a") -> 1154.5136 | Z76: =IFERROR(INDEX('Area safety'!$G$23:$G$41,MATCH($B76,'Area safety'!$A$23:$A$41,0)),"n/a") -> 691.04551 | AA76: =IFERROR(INDEX('Area safety'!$H$23:$H$41,MATCH($B76,'Area safety'!$A$23:$A$41,0)),"n/a") -> 23.900822 | AB76: =IFERROR(INDEX('Area safety'!$I$23:$I$41,MATCH($B76,'Area safety'!$A$23:$A$41,0)),"n/a") -> 4980.7235 | AC76: =IFERROR(INDEX('Area safety'!$F$5:$F$18,MATCH($W76,'Area safety'!$A$5:$A$18,0)),"n/a") -> 4793 | AD76: =IFERROR(INDEX('Area safety'!$G$5:$G$18,MATCH($W76,'Area safety'!$A$5:$A$18,0)),"n/a") -> 23 | AE76: =IFERROR(INDEX('Area safety'!$H$5:$H$18,MATCH($W76,'Area safety'!$A$5:$A$18,0)),"n/a") -> 1111 | AF76: =IFERROR(INDEX('Area safety'!$I$5:$I$18,MATCH($W76,'Area safety'!$A$5:$A$18,0)),"n/a") -> 665 | AG76: =IFERROR(INDEX('Area safety'!$K$23:$K$41,MATCH($B76,'Area safety'!$A$23:$A$41,0)),"n/a") -> 0.099059849 | AH76: =IFERROR(INDEX('Area safety'!$J$23:$J$41,MATCH($B76,'Area safety'!$A$23:$A$41,0)),"n/a") -> 4
A77: Margate | B77: Margate | C77: Available | D77: 650000 | E77: Apartment / Flat | F77: First Floor | G77: 2 | H77: 1 garage | I77: 118 | J77: 1500 | K77: 850 | L77: Yes | M77: NOT STATED | N77: Discover an exceptional investment opportunity perfectly positioned just a 50-meter stroll from the lively Margate Beach. | Pet Friendly | O77: Roelien Lundin | P77: RE/MAX Coast and Country Shelly Beach | Q77: NOT CAPTURED (reCAPTCHA) | R77: NOT AVAILABLE (needs phone) | S77: Agent profile | T77: Open listing | U77: 18 May 2026 | V77: 2026-10-08 | W77: =IFERROR(INDEX('Area safety'!$C$23:$C$41,MATCH($B77,'Area safety'!$A$23:$A$41,0)),"n/a") -> Margate | X77: =IFERROR(INDEX('Area safety'!$D$23:$D$41,MATCH($B77,'Area safety'!$A$23:$A$41,0)),"n/a") -> CONFIRMED | Y77: =IFERROR(INDEX('Area safety'!$F$23:$F$41,MATCH($B77,'Area safety'!$A$23:$A$41,0)),"n/a") -> 1154.5136 | Z77: =IFERROR(INDEX('Area safety'!$G$23:$G$41,MATCH($B77,'Area safety'!$A$23:$A$41,0)),"n/a") -> 691.04551 | AA77: =IFERROR(INDEX('Area safety'!$H$23:$H$41,MATCH($B77,'Area safety'!$A$23:$A$41,0)),"n/a") -> 23.900822 | AB77: =IFERROR(INDEX('Area safety'!$I$23:$I$41,MATCH($B77,'Area safety'!$A$23:$A$41,0)),"n/a") -> 4980.7235 | AC77: =IFERROR(INDEX('Area safety'!$F$5:$F$18,MATCH($W77,'Area safety'!$A$5:$A$18,0)),"n/a") -> 4793 | AD77: =IFERROR(INDEX('Area safety'!$G$5:$G$18,MATCH($W77,'Area safety'!$A$5:$A$18,0)),"n/a") -> 23 | AE77: =IFERROR(INDEX('Area safety'!$H$5:$H$18,MATCH($W77,'Area safety'!$A$5:$A$18,0)),"n/a") -> 1111 | AF77: =IFERROR(INDEX('Area safety'!$I$5:$I$18,MATCH($W77,'Area safety'!$A$5:$A$18,0)),"n/a") -> 665 | AG77: =IFERROR(INDEX('Area safety'!$K$23:$K$41,MATCH($B77,'Area safety'!$A$23:$A$41,0)),"n/a") -> 0.099059849 | AH77: =IFERROR(INDEX('Area safety'!$J$23:$J$41,MATCH($B77,'Area safety'!$A$23:$A$41,0)),"n/a") -> 4
A78: Margate | B78: Margate | C78: Available | D78: 650000 | E78: Apartment / Flat | F78: NOT STATED | G78: 2 | H78: 1 parking | I78: 66 | J78: 2500 | K78: 1000 | L78: NOT STATED | M78: NOT STATED | N78: Positioned in one of Margate’s most desirable beachfront locations, this apartment offers the perfect blend of seaside living, everyday convenience, a | O78: Precious Nxasana | P78: Pam Golding Properties - Port Shepstone / Margate | Q78: NOT CAPTURED (reCAPTCHA) | R78: NOT AVAILABLE (needs phone) | S78: Agent profile | T78: Open listing | U78: 14 April 2026 | V78: 2026-10-08 | W78: =IFERROR(INDEX('Area safety'!$C$23:$C$41,MATCH($B78,'Area safety'!$A$23:$A$41,0)),"n/a") -> Margate | X78: =IFERROR(INDEX('Area safety'!$D$23:$D$41,MATCH($B78,'Area safety'!$A$23:$A$41,0)),"n/a") -> CONFIRMED | Y78: =IFERROR(INDEX('Area safety'!$F$23:$F$41,MATCH($B78,'Area safety'!$A$23:$A$41,0)),"n/a") -> 1154.5136 | Z78: =IFERROR(INDEX('Area safety'!$G$23:$G$41,MATCH($B78,'Area safety'!$A$23:$A$41,0)),"n/a") -> 691.04551 | AA78: =IFERROR(INDEX('Area safety'!$H$23:$H$41,MATCH($B78,'Area safety'!$A$23:$A$41,0)),"n/a") -> 23.900822 | AB78: =IFERROR(INDEX('Area safety'!$I$23:$I$41,MATCH($B78,'Area safety'!$A$23:$A$41,0)),"n/a") -> 4980.7235 | AC78: =IFERROR(INDEX('Area safety'!$F$5:$F$18,MATCH($W78,'Area safety'!$A$5:$A$18,0)),"n/a") -> 4793 | AD78: =IFERROR(INDEX('Area safety'!$G$5:$G$18,MATCH($W78,'Area safety'!$A$5:$A$18,0)),"n/a") -> 23 | AE78: =IFERROR(INDEX('Area safety'!$H$5:$H$18,MATCH($W78,'Area safety'!$A$5:$A$18,0)),"n/a") -> 1111 | AF78: =IFERROR(INDEX('Area safety'!$I$5:$I$18,MATCH($W78,'Area safety'!$A$5:$A$18,0)),"n/a") -> 665 | AG78: =IFERROR(INDEX('Area safety'!$K$23:$K$41,MATCH($B78,'Area safety'!$A$23:$A$41,0)),"n/a") -> 0.099059849 | AH78: =IFERROR(INDEX('Area safety'!$J$23:$J$41,MATCH($B78,'Area safety'!$A$23:$A$41,0)),"n/a") -> 4
A79: Margate | B79: Margate | C79: Available | D79: 655000 | E79: Apartment / Flat | F79: NOT STATED | G79: 2 | H79: 1 parking | I79: 71 | J79: 1897 | K79: 450 | L79: NOT STATED | M79: NOT STATED | N79: This unit is located in a quiet street in Margate. | O79: Ntombenhle Sidaki | P79: Pam Golding Properties - Port Shepstone / Margate | Q79: NOT CAPTURED (reCAPTCHA) | R79: NOT AVAILABLE (needs phone) | S79: Agent profile | T79: Open listing | U79: 28 July 2026 | V79: 2026-10-08 | W79: =IFERROR(INDEX('Area safety'!$C$23:$C$41,MATCH($B79,'Area safety'!$A$23:$A$41,0)),"n/a") -> Margate | X79: =IFERROR(INDEX('Area safety'!$D$23:$D$41,MATCH($B79,'Area safety'!$A$23:$A$41,0)),"n/a") -> CONFIRMED | Y79: =IFERROR(INDEX('Area safety'!$F$23:$F$41,MATCH($B79,'Area safety'!$A$23:$A$41,0)),"n/a") -> 1154.5136 | Z79: =IFERROR(INDEX('Area safety'!$G$23:$G$41,MATCH($B79,'Area safety'!$A$23:$A$41,0)),"n/a") -> 691.04551 | AA79: =IFERROR(INDEX('Area safety'!$H$23:$H$41,MATCH($B79,'Area safety'!$A$23:$A$41,0)),"n/a") -> 23.900822 | AB79: =IFERROR(INDEX('Area safety'!$I$23:$I$41,MATCH($B79,'Area safety'!$A$23:$A$41,0)),"n/a") -> 4980.7235 | AC79: =IFERROR(INDEX('Area safety'!$F$5:$F$18,MATCH($W79,'Area safety'!$A$5:$A$18,0)),"n/a") -> 4793 | AD79: =IFERROR(INDEX('Area safety'!$G$5:$G$18,MATCH($W79,'Area safety'!$A$5:$A$18,0)),"n/a") -> 23 | AE79: =IFERROR(INDEX('Area safety'!$H$5:$H$18,MATCH($W79,'Area safety'!$A$5:$A$18,0)),"n/a") -> 1111 | AF79: =IFERROR(INDEX('Area safety'!$I$5:$I$18,MATCH($W79,'Area safety'!$A$5:$A$18,0)),"n/a") -> 665 | AG79: =IFERROR(INDEX('Area safety'!$K$23:$K$41,MATCH($B79,'Area safety'!$A$23:$A$41,0)),"n/a") -> 0.099059849 | AH79: =IFERROR(INDEX('Area safety'!$J$23:$J$41,MATCH($B79,'Area safety'!$A$23:$A$41,0)),"n/a") -> 4
A80: Margate | B80: Margate | C80: Available | D80: 655000 | E80: Apartment / Flat | F80: 1st floor (per description) | G80: 2 | H80: 1 garage | I80: 100 | J80: 3020 | K80: 800 | L80: NOT STATED | M80: NOT STATED | N80: Located close to the beach this 1st floor spacious unit is in a small and secure complex. | O80: Farren Govender | P80: Pam Golding Properties - Port Shepstone / Margate | Q80: NOT CAPTURED (reCAPTCHA) | R80: NOT AVAILABLE (needs phone) | S80: Agent profile | T80: Open listing | U80: 01 June 2026 | V80: 2026-10-08 | W80: =IFERROR(INDEX('Area safety'!$C$23:$C$41,MATCH($B80,'Area safety'!$A$23:$A$41,0)),"n/a") -> Margate | X80: =IFERROR(INDEX('Area safety'!$D$23:$D$41,MATCH($B80,'Area safety'!$A$23:$A$41,0)),"n/a") -> CONFIRMED | Y80: =IFERROR(INDEX('Area safety'!$F$23:$F$41,MATCH($B80,'Area safety'!$A$23:$A$41,0)),"n/a") -> 1154.5136 | Z80: =IFERROR(INDEX('Area safety'!$G$23:$G$41,MATCH($B80,'Area safety'!$A$23:$A$41,0)),"n/a") -> 691.04551 | AA80: =IFERROR(INDEX('Area safety'!$H$23:$H$41,MATCH($B80,'Area safety'!$A$23:$A$41,0)),"n/a") -> 23.900822 | AB80: =IFERROR(INDEX('Area safety'!$I$23:$I$41,MATCH($B80,'Area safety'!$A$23:$A$41,0)),"n/a") -> 4980.7235 | AC80: =IFERROR(INDEX('Area safety'!$F$5:$F$18,MATCH($W80,'Area safety'!$A$5:$A$18,0)),"n/a") -> 4793 | AD80: =IFERROR(INDEX('Area safety'!$G$5:$G$18,MATCH($W80,'Area safety'!$A$5:$A$18,0)),"n/a") -> 23 | AE80: =IFERROR(INDEX('Area safety'!$H$5:$H$18,MATCH($W80,'Area safety'!$A$5:$A$18,0)),"n/a") -> 1111 | AF80: =IFERROR(INDEX('Area safety'!$I$5:$I$18,MATCH($W80,'Area safety'!$A$5:$A$18,0)),"n/a") -> 665 | AG80: =IFERROR(INDEX('Area safety'!$K$23:$K$41,MATCH($B80,'Area safety'!$A$23:$A$41,0)),"n/a") -> 0.099059849 | AH80: =IFERROR(INDEX('Area safety'!$J$23:$J$41,MATCH($B80,'Area safety'!$A$23:$A$41,0)),"n/a") -> 4
A81: Margate | B81: Margate | C81: Available | D81: 657000 | E81: Apartment / Flat | F81: Second floor and above | G81: 2 | H81: 1 parking | I81: 47 | J81: 1008 | K81: 861 | L81: Yes | M81: NOT STATED | N81: Modern Coastal Living Just Minutes from the Beach. | Pet Friendly | O81: Angelique Venter | P81: Home Finders Coastal | Q81: NOT CAPTURED (reCAPTCHA) | R81: NOT AVAILABLE (needs phone) | S81: Agent profile | T81: Open listing | U81: 14 July 2026 | V81: 2026-10-08 | W81: =IFERROR(INDEX('Area safety'!$C$23:$C$41,MATCH($B81,'Area safety'!$A$23:$A$41,0)),"n/a") -> Margate | X81: =IFERROR(INDEX('Area safety'!$D$23:$D$41,MATCH($B81,'Area safety'!$A$23:$A$41,0)),"n/a") -> CONFIRMED | Y81: =IFERROR(INDEX('Area safety'!$F$23:$F$41,MATCH($B81,'Area safety'!$A$23:$A$41,0)),"n/a") -> 1154.5136 | Z81: =IFERROR(INDEX('Area safety'!$G$23:$G$41,MATCH($B81,'Area safety'!$A$23:$A$41,0)),"n/a") -> 691.04551 | AA81: =IFERROR(INDEX('Area safety'!$H$23:$H$41,MATCH($B81,'Area safety'!$A$23:$A$41,0)),"n/a") -> 23.900822 | AB81: =IFERROR(INDEX('Area safety'!$I$23:$I$41,MATCH($B81,'Area safety'!$A$23:$A$41,0)),"n/a") -> 4980.7235 | AC81: =IFERROR(INDEX('Area safety'!$F$5:$F$18,MATCH($W81,'Area safety'!$A$5:$A$18,0)),"n/a") -> 4793 | AD81: =IFERROR(INDEX('Area safety'!$G$5:$G$18,MATCH($W81,'Area safety'!$A$5:$A$18,0)),"n/a") -> 23 | AE81: =IFERROR(INDEX('Area safety'!$H$5:$H$18,MATCH($W81,'Area safety'!$A$5:$A$18,0)),"n/a") -> 1111 | AF81: =IFERROR(INDEX('Area safety'!$I$5:$I$18,MATCH($W81,'Area safety'!$A$5:$A$18,0)),"n/a") -> 665 | AG81: =IFERROR(INDEX('Area safety'!$K$23:$K$41,MATCH($B81,'Area safety'!$A$23:$A$41,0)),"n/a") -> 0.099059849 | AH81: =IFERROR(INDEX('Area safety'!$J$23:$J$41,MATCH($B81,'Area safety'!$A$23:$A$41,0)),"n/a") -> 4
A82: Margate | B82: Margate | C82: Available | D82: 660000 | E82: Apartment / Flat | F82: NOT STATED | G82: 2 | H82: 1 garage | I82: 96 | J82: 1100 | K82: 800 | L82: NOT STATED | M82: NOT STATED | N82: This well-maintained two-bedroom apartment offers a convenient coastal lifestyle in the heart of Margate. | Garden | O82: Precious Nxasana | P82: Pam Golding Properties - Port Shepstone / Margate | Q82: NOT CAPTURED (reCAPTCHA) | R82: NOT AVAILABLE (needs phone) | S82: Agent profile | T82: Open listing | U82: 30 September 2026 | V82: 2026-10-08 | W82: =IFERROR(INDEX('Area safety'!$C$23:$C$41,MATCH($B82,'Area safety'!$A$23:$A$41,0)),"n/a") -> Margate | X82: =IFERROR(INDEX('Area safety'!$D$23:$D$41,MATCH($B82,'Area safety'!$A$23:$A$41,0)),"n/a") -> CONFIRMED | Y82: =IFERROR(INDEX('Area safety'!$F$23:$F$41,MATCH($B82,'Area safety'!$A$23:$A$41,0)),"n/a") -> 1154.5136 | Z82: =IFERROR(INDEX('Area safety'!$G$23:$G$41,MATCH($B82,'Area safety'!$A$23:$A$41,0)),"n/a") -> 691.04551 | AA82: =IFERROR(INDEX('Area safety'!$H$23:$H$41,MATCH($B82,'Area safety'!$A$23:$A$41,0)),"n/a") -> 23.900822 | AB82: =IFERROR(INDEX('Area safety'!$I$23:$I$41,MATCH($B82,'Area safety'!$A$23:$A$41,0)),"n/a") -> 4980.7235 | AC82: =IFERROR(INDEX('Area safety'!$F$5:$F$18,MATCH($W82,'Area safety'!$A$5:$A$18,0)),"n/a") -> 4793 | AD82: =IFERROR(INDEX('Area safety'!$G$5:$G$18,MATCH($W82,'Area safety'!$A$5:$A$18,0)),"n/a") -> 23 | AE82: =IFERROR(INDEX('Area safety'!$H$5:$H$18,MATCH($W82,'Area safety'!$A$5:$A$18,0)),"n/a") -> 1111 | AF82: =IFERROR(INDEX('Area safety'!$I$5:$I$18,MATCH($W82,'Area safety'!$A$5:$A$18,0)),"n/a") -> 665 | AG82: =IFERROR(INDEX('Area safety'!$K$23:$K$41,MATCH($B82,'Area safety'!$A$23:$A$41,0)),"n/a") -> 0.099059849 | AH82: =IFERROR(INDEX('Area safety'!$J$23:$J$41,MATCH($B82,'Area safety'!$A$23:$A$41,0)),"n/a") -> 4
... A100: Margate | B100: Margate | C100: Available | D100: 750000 | E100: Apartment / Flat | F100: Second floor and above | G100: 2 | H100: 2 parking | I100: 67 | J100: 3700 | K100: 950 | L100: No | M100: Yes | N100: Coastal Living Redefined: Top-Floor Apartment with Panoramic Sea Views in Margate Wake up to the sound of the ocean and enjoy relaxed coastal living f | No Pets Allowed | O100: Paul Dowdle | P100: RE/MAX Coast and Country Southbroom | Q100: NOT CAPTURED (reCAPTCHA) | R100: NOT AVAILABLE (needs phone) | S100: Agent profile | T100: Open listing | U100: 14 May 2026 | V100: 2026-10-08 | W100: =IFERROR(INDEX('Area safety'!$C$23:$C$41,MATCH($B100,'Area safety'!$A$23:$A$41,0)),"n/a") -> Margate | X100: =IFERROR(INDEX('Area safety'!$D$23:$D$41,MATCH($B100,'Area safety'!$A$23:$A$41,0)),"n/a") -> CONFIRMED | Y100: =IFERROR(INDEX('Area safety'!$F$23:$F$41,MATCH($B100,'Area safety'!$A$23:$A$41,0)),"n/a") -> 1154.5136 | Z100: =IFERROR(INDEX('Area safety'!$G$23:$G$41,MATCH($B100,'Area safety'!$A$23:$A$41,0)),"n/a") -> 691.04551 | AA100: =IFERROR(INDEX('Area safety'!$H$23:$H$41,MATCH($B100,'Area safety'!$A$23:$A$41,0)),"n/a") -> 23.900822 | AB100: =IFERROR(INDEX('Area safety'!$I$23:$I$41,MATCH($B100,'Area safety'!$A$23:$A$41,0)),"n/a") -> 4980.7235 | AC100: =IFERROR(INDEX('Area safety'!$F$5:$F$18,MATCH($W100,'Area safety'!$A$5:$A$18,0)),"n/a") -> 4793 | AD100: =IFERROR(INDEX('Area safety'!$G$5:$G$18,MATCH($W100,'Area safety'!$A$5:$A$18,0)),"n/a") -> 23 | AE100: =IFERROR(INDEX('Area safety'!$H$5:$H$18,MATCH($W100,'Area safety'!$A$5:$A$18,0)),"n/a") -> 1111 | AF100: =IFERROR(INDEX('Area safety'!$I$5:$I$18,MATCH($W100,'Area safety'!$A$5:$A$18,0)),"n/a") -> 665 | AG100: =IFERROR(INDEX('Area safety'!$K$23:$K$41,MATCH($B100,'Area safety'!$A$23:$A$41,0)),"n/a") -> 0.099059849 | AH100: =IFERROR(INDEX('Area safety'!$J$23:$J$41,MATCH($B100,'Area safety'!$A$23:$A$41,0)),"n/a") -> 4
A101: Margate | B101: Manaba Beach | C101: Available | D101: 535000 | E101: Apartment / Flat | F101: NOT STATED | G101: 2 | H101: 3 parking | I101: NOT STATED | J101: NOT STATED | K101: NOT STATED | L101: NOT STATED | M101: NOT STATED | N101: This affordable 2-bedroom, 2-bathroom apartment is an excellent opportunity for first-time buyers or investors looking to expand their property portfolio. | O101: John Chambeau | P101: Real & Proper T | Q101: NOT CAPTURED (reCAPTCHA) | R101: NOT AVAILABLE (needs phone) | S101: Agent profile | T101: Open listing | U101: 16 July 2026 | V101: 2026-10-08 | W101: =IFERROR(INDEX('Area safety'!$C$23:$C$41,MATCH($B101,'Area safety'!$A$23:$A$41,0)),"n/a") -> Margate | X101: =IFERROR(INDEX('Area safety'!$D$23:$D$41,MATCH($B101,'Area safety'!$A$23:$A$41,0)),"n/a") -> CONFIRMED | Y101: =IFERROR(INDEX('Area safety'!$F$23:$F$41,MATCH($B101,'Area safety'!$A$23:$A$41,0)),"n/a") -> 1154.5136 | Z101: =IFERROR(INDEX('Area safety'!$G$23:$G$41,MATCH($B101,'Area safety'!$A$23:$A$41,0)),"n/a") -> 691.04551 | AA101: =IFERROR(INDEX('Area safety'!$H$23:$H$41,MATCH($B101,'Area safety'!$A$23:$A$41,0)),"n/a") -> 23.900822 | AB101: =IFERROR(INDEX('Area safety'!$I$23:$I$41,MATCH($B101,'Area safety'!$A$23:$A$41,0)),"n/a") -> 4980.7235 | AC101: =IFERROR(INDEX('Area safety'!$F$5:$F$18,MATCH($W101,'Area safety'!$A$5:$A$18,0)),"n/a") -> 4793 | AD101: =IFERROR(INDEX('Area safety'!$G$5:$G$18,MATCH($W101,'Area safety'!$A$5:$A$18,0)),"n/a") -> 23 | AE101: =IFERROR(INDEX('Area safety'!$H$5:$H$18,MATCH($W101,'Area safety'!$A$5:$A$18,0)),"n/a") -> 1111 | AF101: =IFERROR(INDEX('Area safety'!$I$5:$I$18,MATCH($W101,'Area safety'!$A$5:$A$18,0)),"n/a") -> 665 | AG101: =IFERROR(INDEX('Area safety'!$K$23:$K$41,MATCH($B101,'Area safety'!$A$23:$A$41,0)),"n/a") -> 0.099059849 | AH101: =IFERROR(INDEX('Area safety'!$J$23:$J$41,MATCH($B101,'Area safety'!$A$23:$A$41,0)),"n/a") -> 4
A102: Margate | B102: Manaba Beach | C102: Available | D102: 550000 | E102: Apartment / Flat | F102: NOT STATED | G102: 2 | H102: 2 parking | I102: 96 | J102: 1600 | K102: 800 | L102: Yes | M102: NOT STATED | N102: Sole Mandate - Welcome to your ideal investment property, without breaking the bank. | Pet Friendly, Garden | O102: Nadia Beattie | P102: Just Property Living | Q102: NOT CAPTURED (reCAPTCHA) | R102: NOT AVAILABLE (needs phone) | S102: Agent profile | T102: Open listing | U102: 06 October 2026 | V102: 2026-10-08 | W102: =IFERROR(INDEX('Area safety'!$C$23:$C$41,MATCH($B102,'Area safety'!$A$23:$A$41,0)),"n/a") -> Margate | X102: =IFERROR(INDEX('Area safety'!$D$23:$D$41,MATCH($B102,'Area safety'!$A$23:$A$41,0)),"n/a") -> CONFIRMED | Y102: =IFERROR(INDEX('Area safety'!$F$23:$F$41,MATCH($B102,'Area safety'!$A$23:$A$41,0)),"n/a") -> 1154.5136 | Z102: =IFERROR(INDEX('Area safety'!$G$23:$G$41,MATCH($B102,'Area safety'!$A$23:$A$41,0)),"n/a") -> 691.04551 | AA102: =IFERROR(INDEX('Area safety'!$H$23:$H$41,MATCH($B102,'Area safety'!$A$23:$A$41,0)),"n/a") -> 23.900822 | AB102: =IFERROR(INDEX('Area safety'!$I$23:$I$41,MATCH($B102,'Area safety'!$A$23:$A$41,0)),"n/a") -> 4980.7235 | AC102: =IFERROR(INDEX('Area safety'!$F$5:$F$18,MATCH($W102,'Area safety'!$A$5:$A$18,0)),"n/a") -> 4793 | AD102: =IFERROR(INDEX('Area safety'!$G$5:$G$18,MATCH($W102,'Area safety'!$A$5:$A$18,0)),"n/a") -> 23 | AE102: =IFERROR(INDEX('Area safety'!$H$5:$H$18,MATCH($W102,'Area safety'!$A$5:$A$18,0)),"n/a") -> 1111 | AF102: =IFERROR(INDEX('Area safety'!$I$5:$I$18,MATCH($W102,'Area safety'!$A$5:$A$18,0)),"n/a") -> 665 | AG102: =IFERROR(INDEX('Area safety'!$K$23:$K$41,MATCH($B102,'Area safety'!$A$23:$A$41,0)),"n/a") -> 0.099059849 | AH102: =IFERROR(INDEX('Area safety'!$J$23:$J$41,MATCH($B102,'Area safety'!$A$23:$A$41,0)),"n/a") -> 4
A103: Margate | B103: Manaba Beach | C103: Available | D103: 550000 | E103: Apartment / Flat | F103: NOT STATED | G103: 2 | H103: 2 parking | I103: 72 | J103: 1200 | K103: 800 | L103: No | M103: NOT STATED | N103: You walk in and the ocean sets the tone. | No Pets Allowed | O103: Melanie Brierley | P103: RE/MAX Coast and Country Shelly Beach | Q103: NOT CAPTURED (reCAPTCHA) | R103: NOT AVAILABLE (needs phone) | S103: Agent profile | T103: Open listing | U103: 16 May 2026 | V103: 2026-10-08 | W103: =IFERROR(INDEX('Area safety'!$C$23:$C$41,MATCH($B103,'Area safety'!$A$23:$A$41,0)),"n/a") -> Margate | X103: =IFERROR(INDEX('Area safety'!$D$23:$D$41,MATCH($B103,'Area safety'!$A$23:$A$41,0)),"n/a") -> CONFIRMED | Y103: =IFERROR(INDEX('Area safety'!$F$23:$F$41,MATCH($B103,'Area safety'!$A$23:$A$41,0)),"n/a") -> 1154.5136 | Z103: =IFERROR(INDEX('Area safety'!$G$23:$G$41,MATCH($B103,'Area safety'!$A$23:$A$41,0)),"n/a") -> 691.04551 | AA103: =IFERROR(INDEX('Area safety'!$H$23:$H$41,MATCH($B103,'Area safety'!$A$23:$A$41,0)),"n/a") -> 23.900822 | AB103: =IFERROR(INDEX('Area safety'!$I$23:$I$41,MATCH($B103,'Area safety'!$A$23:$A$41,0)),"n/a") -> 4980.7235 | AC103: =IFERROR(INDEX('Area safety'!$F$5:$F$18,MATCH($W103,'Area safety'!$A$5:$A$18,0)),"n/a") -> 4793 | AD103: =IFERROR(INDEX('Area safety'!$G$5:$G$18,MATCH($W103,'Area safety'!$A$5:$A$18,0)),"n/a") -> 23 | AE103: =IFERROR(INDEX('Area safety'!$H$5:$H$18,MATCH($W103,'Area safety'!$A$5:$A$18,0)),"n/a") -> 1111 | AF103: =IFERROR(INDEX('Area safety'!$I$5:$I$18,MATCH($W103,'Area safety'!$A$5:$A$18,0)),"n/a") -> 665 | AG103: =IFERROR(INDEX('Area safety'!$K$23:$K$41,MATCH($B103,'Area safety'!$A$23:$A$41,0)),"n/a") -> 0.099059849 | AH103: =IFERROR(INDEX('Area safety'!$J$23:$J$41,MATCH($B103,'Area safety'!$A$23:$A$41,0)),"n/a") -> 4
A104: Margate | B104: Manaba Beach | C104: Available | D104: 595000 | E104: Apartment / Flat | F104: Second floor (per description) | G104: 2 | H104: 1 parking | I104: 71 | J104: 1920 | K104: NOT STATED | L104: No | M104: NOT STATED | N104: Location is everything, and this spacious 2-bedroom apartment has it all! | No Pets Allowed, Garden | O104: Sipho Bentswana | P104: Just Property Living | Q104: NOT CAPTURED (reCAPTCHA) | R104: NOT AVAILABLE (needs phone) | S104: Agent profile | T104: Open listing | U104: 21 July 2026 | V104: 2026-10-08 | W104: =IFERROR(INDEX('Area safety'!$C$23:$C$41,MATCH($B104,'Area safety'!$A$23:$A$41,0)),"n/a") -> Margate | X104: =IFERROR(INDEX('Area safety'!$D$23:$D$41,MATCH($B104,'Area safety'!$A$23:$A$41,0)),"n/a") -> CONFIRMED | Y104: =IFERROR(INDEX('Area safety'!$F$23:$F$41,MATCH($B104,'Area safety'!$A$23:$A$41,0)),"n/a") -> 1154.5136 | Z104: =IFERROR(INDEX('Area safety'!$G$23:$G$41,MATCH($B104,'Area safety'!$A$23:$A$41,0)),"n/a") -> 691.04551 | AA104: =IFERROR(INDEX('Area safety'!$H$23:$H$41,MATCH($B104,'Area safety'!$A$23:$A$41,0)),"n/a") -> 23.900822 | AB104: =IFERROR(INDEX('Area safety'!$I$23:$I$41,MATCH($B104,'Area safety'!$A$23:$A$41,0)),"n/a") -> 4980.7235 | AC104: =IFERROR(INDEX('Area safety'!$F$5:$F$18,MATCH($W104,'Area safety'!$A$5:$A$18,0)),"n/a") -> 4793 | AD104: =IFERROR(INDEX('Area safety'!$G$5:$G$18,MATCH($W104,'Area safety'!$A$5:$A$18,0)),"n/a") -> 23 | AE104: =IFERROR(INDEX('Area safety'!$H$5:$H$18,MATCH($W104,'Area safety'!$A$5:$A$18,0)),"n/a") -> 1111 | AF104: =IFERROR(INDEX('Area safety'!$I$5:$I$18,MATCH($W104,'Area safety'!$A$5:$A$18,0)),"n/a") -> 665 | AG104: =IFERROR(INDEX('Area safety'!$K$23:$K$41,MATCH($B104,'Area safety'!$A$23:$A$41,0)),"n/a") -> 0.099059849 | AH104: =IFERROR(INDEX('Area safety'!$J$23:$J$41,MATCH($B104,'Area safety'!$A$23:$A$41,0)),"n/a") -> 4
A105: Margate | B105: Manaba Beach | C105: Available | D105: 650000 | E105: Apartment / Flat | F105: NOT STATED | G105: 2 | H105: 1 parking | I105: 72 | J105: 1232 | K105: 700 | L105: NOT STATED | M105: NOT STATED | N105: This two-bedroom apartment has a renovated and modern kitchen, a full-size bathroom with a shower and tub, redone and polished parquet floors througho | Garden | O105: Shobanie Singh | P105: Pam Golding Properties - Port Shepstone / Margate | Q105: NOT CAPTURED (reCAPTCHA) | R105: NOT AVAILABLE (needs phone) | S105: Agent profile | T105: Open listing | U105: 02 October 2026 | V105: 2026-10-08 | W105: =IFERROR(INDEX('Area safety'!$C$23:$C$41,MATCH($B105,'Area safety'!$A$23:$A$41,0)),"n/a") -> Margate | X105: =IFERROR(INDEX('Area safety'!$D$23:$D$41,MATCH($B105,'Area safety'!$A$23:$A$41,0)),"n/a") -> CONFIRMED | Y105: =IFERROR(INDEX('Area safety'!$F$23:$F$41,MATCH($B105,'Area safety'!$A$23:$A$41,0)),"n/a") -> 1154.5136 | Z105: =IFERROR(INDEX('Area safety'!$G$23:$G$41,MATCH($B105,'Area safety'!$A$23:$A$41,0)),"n/a") -> 691.04551 | AA105: =IFERROR(INDEX('Area safety'!$H$23:$H$41,MATCH($B105,'Area safety'!$A$23:$A$41,0)),"n/a") -> 23.900822 | AB105: =IFERROR(INDEX('Area safety'!$I$23:$I$41,MATCH($B105,'Area safety'!$A$23:$A$41,0)),"n/a") -> 4980.7235 | AC105: =IFERROR(INDEX('Area safety'!$F$5:$F$18,MATCH($W105,'Area safety'!$A$5:$A$18,0)),"n/a") -> 4793 | AD105: =IFERROR(INDEX('Area safety'!$G$5:$G$18,MATCH($W105,'Area safety'!$A$5:$A$18,0)),"n/a") -> 23 | AE105: =IFERROR(INDEX('Area safety'!$H$5:$H$18,MATCH($W105,'Area safety'!$A$5:$A$18,0)),"n/a") -> 1111 | AF105: =IFERROR(INDEX('Area safety'!$I$5:$I$18,MATCH($W105,'Area safety'!$A$5:$A$18,0)),"n/a") -> 665 | AG105: =IFERROR(INDEX('Area safety'!$K$23:$K$41,MATCH($B105,'Area safety'!$A$23:$A$41,0)),"n/a") -> 0.099059849 | AH105: =IFERROR(INDEX('Area safety'!$J$23:$J$41,MATCH($B105,'Area safety'!$A$23:$A$41,0)),"n/a") -> 4
A106: Margate | B106: Manaba Beach | C106: Available | D106: 650000 | E106: Apartment / Flat | F106: First floor (per description) | G106: 2 | H106: 1 parking | I106: 71 | J106: 1925 | K106: 569 | L106: No | M106: NOT STATED | N106: First floor, charming, ideal starter home. | No Pets Allowed | O106: Kotie Koekemoer | P106: Property.CoZa - Legends | Q106: NOT CAPTURED (reCAPTCHA) | R106: NOT AVAILABLE (needs phone) | S106: Agent profile | T106: Open listing | U106: 02 September 2026 | V106: 2026-10-08 | W106: =IFERROR(INDEX('Area safety'!$C$23:$C$41,MATCH($B106,'Area safety'!$A$23:$A$41,0)),"n/a") -> Margate | X106: =IFERROR(INDEX('Area safety'!$D$23:$D$41,MATCH($B106,'Area safety'!$A$23:$A$41,0)),"n/a") -> CONFIRMED | Y106: =IFERROR(INDEX('Area safety'!$F$23:$F$41,MATCH($B106,'Area safety'!$A$23:$A$41,0)),"n/a") -> 1154.5136 | Z106: =IFERROR(INDEX('Area safety'!$G$23:$G$41,MATCH($B106,'Area safety'!$A$23:$A$41,0)),"n/a") -> 691.04551 | AA106: =IFERROR(INDEX('Area safety'!$H$23:$H$41,MATCH($B106,'Area safety'!$A$23:$A$41,0)),"n/a") -> 23.900822 | AB106: =IFERROR(INDEX('Area safety'!$I$23:$I$41,MATCH($B106,'Area safety'!$A$23:$A$41,0)),"n/a") -> 4980.7235 | AC106: =IFERROR(INDEX('Area safety'!$F$5:$F$18,MATCH($W106,'Area safety'!$A$5:$A$18,0)),"n/a") -> 4793 | AD106: =IFERROR(INDEX('Area safety'!$G$5:$G$18,MATCH($W106,'Area safety'!$A$5:$A$18,0)),"n/a") -> 23 | AE106: =IFERROR(INDEX('Area safety'!$H$5:$H$18,MATCH($W106,'Area safety'!$A$5:$A$18,0)),"n/a") -> 1111 | AF106: =IFERROR(INDEX('Area safety'!$I$5:$I$18,MATCH($W106,'Area safety'!$A$5:$A$18,0)),"n/a") -> 665 | AG106: =IFERROR(INDEX('Area safety'!$K$23:$K$41,MATCH($B106,'Area safety'!$A$23:$A$41,0)),"n/a") -> 0.099059849 | AH106: =IFERROR(INDEX('Area safety'!$J$23:$J$41,MATCH($B106,'Area safety'!$A$23:$A$41,0)),"n/a") -> 4
A107: Margate | B107: Manaba Beach | C107: Available | D107: 690000 | E107: Apartment / Flat | F107: NOT STATED | G107: 2 | H107: 1 garage | I107: 88 | J107: NOT STATED | K107: NOT STATED | L107: NOT STATED | M107: Yes | N107: Embrace coastal living with this lovely 2-bedroom, 2-bathroom apartment, just a short stroll from Margate’s beach, where fresh ocean air greets you every day. | O107: Yolandi Grobler | P107: Real & Proper T | Q107: NOT CAPTURED (reCAPTCHA) | R107: NOT AVAILABLE (needs phone) | S107: Agent profile | T107: Open listing | U107: 08 September 2026 | V107: 2026-10-08 | W107: =IFERROR(INDEX('Area safety'!$C$23:$C$41,MATCH($B107,'Area safety'!$A$23:$A$41,0)),"n/a") -> Margate | X107: =IFERROR(INDEX('Area safety'!$D$23:$D$41,MATCH($B107,'Area safety'!$A$23:$A$41,0)),"n/a") -> CONFIRMED | Y107: =IFERROR(INDEX('Area safety'!$F$23:$F$41,MATCH($B107,'Area safety'!$A$23:$A$41,0)),"n/a") -> 1154.5136 | Z107: =IFERROR(INDEX('Area safety'!$G$23:$G$41,MATCH($B107,'Area safety'!$A$23:$A$41,0)),"n/a") -> 691.04551 | AA107: =IFERROR(INDEX('Area safety'!$H$23:$H$41,MATCH($B107,'Area safety'!$A$23:$A$41,0)),"n/a") -> 23.900822 | AB107: =IFERROR(INDEX('Area safety'!$I$23:$I$41,MATCH($B107,'Area safety'!$A$23:$A$41,0)),"n/a") -> 4980.7235 | AC107: =IFERROR(INDEX('Area safety'!$F$5:$F$18,MATCH($W107,'Area safety'!$A$5:$A$18,0)),"n/a") -> 4793 | AD107: =IFERROR(INDEX('Area safety'!$G$5:$G$18,MATCH($W107,'Area safety'!$A$5:$A$18,0)),"n/a") -> 23 | AE107: =IFERROR(INDEX('Area safety'!$H$5:$H$18,MATCH($W107,'Area safety'!$A$5:$A$18,0)),"n/a") -> 1111 | AF107: =IFERROR(INDEX('Area safety'!$I$5:$I$18,MATCH($W107,'Area safety'!$A$5:$A$18,0)),"n/a") -> 665 | AG107: =IFERROR(INDEX('Area safety'!$K$23:$K$41,MATCH($B107,'Area safety'!$A$23:$A$41,0)),"n/a") -> 0.099059849 | AH107: =IFERROR(INDEX('Area safety'!$J$23:$J$41,MATCH($B107,'Area safety'!$A$23:$A$41,0)),"n/a") -> 4
A108: Margate | B108: Manaba Beach | C108: Available | D108: 695000 | E108: Apartment / Flat | F108: Floor 2 | G108: 2 | H108: 2 parking | I108: 72 | J108: 1200 | K108: 800 | L108: NOT STATED | M108: NOT STATED | N108: Bright, Breezy, & Beachbound: The Perfect Coastal Lock-Up-and-Go! | O108: Shaun & Jackie Van Niekerk | P108: EXP South Africa | Q108: NOT CAPTURED (reCAPTCHA) | R108: NOT AVAILABLE (needs phone) | S108: Agent profile | T108: Open listing | U108: 26 February 2026 | V108: 2026-10-08 | W108: =IFERROR(INDEX('Area safety'!$C$23:$C$41,MATCH($B108,'Area safety'!$A$23:$A$41,0)),"n/a") -> Margate | X108: =IFERROR(INDEX('Area safety'!$D$23:$D$41,MATCH($B108,'Area safety'!$A$23:$A$41,0)),"n/a") -> CONFIRMED | Y108: =IFERROR(INDEX('Area safety'!$F$23:$F$41,MATCH($B108,'Area safety'!$A$23:$A$41,0)),"n/a") -> 1154.5136 | Z108: =IFERROR(INDEX('Area safety'!$G$23:$G$41,MATCH($B108,'Area safety'!$A$23:$A$41,0)),"n/a") -> 691.04551 | AA108: =IFERROR(INDEX('Area safety'!$H$23:$H$41,MATCH($B108,'Area safety'!$A$23:$A$41,0)),"n/a") -> 23.900822 | AB108: =IFERROR(INDEX('Area safety'!$I$23:$I$41,MATCH($B108,'Area safety'!$A$23:$A$41,0)),"n/a") -> 4980.7235 | AC108: =IFERROR(INDEX('Area safety'!$F$5:$F$18,MATCH($W108,'Area safety'!$A$5:$A$18,0)),"n/a") -> 4793 | AD108: =IFERROR(INDEX('Area safety'!$G$5:$G$18,MATCH($W108,'Area safety'!$A$5:$A$18,0)),"n/a") -> 23 | AE108: =IFERROR(INDEX('Area safety'!$H$5:$H$18,MATCH($W108,'Area safety'!$A$5:$A$18,0)),"n/a") -> 1111 | AF108: =IFERROR(INDEX('Area safety'!$I$5:$I$18,MATCH($W108,'Area safety'!$A$5:$A$18,0)),"n/a") -> 665 | AG108: =IFERROR(INDEX('Area safety'!$K$23:$K$41,MATCH($B108,'Area safety'!$A$23:$A$41,0)),"n/a") -> 0.099059849 | AH108: =IFERROR(INDEX('Area safety'!$J$23:$J$41,MATCH($B108,'Area safety'!$A$23:$A$41,0)),"n/a") -> 4
A109: Margate | B109: Manaba Beach | C109: Available | D109: 700000 | E109: Apartment / Flat | F109: First Floor | G109: 2 | H109: 1 garage | I109: 90 | J109: 2568 | K109: 696 | L109: No | M109: NOT STATED | N109: Stunning Sea Views, Small, safe, and secure, well-maintained complex. | No Pets Allowed | O109: Anne De Klerk | P109: RE/MAX Coast and Country Shelly Beach | Q109: NOT CAPTURED (reCAPTCHA) | R109: NOT AVAILABLE (needs phone) | S109: Agent profile | T109: Open listing | U109: 30 October 2023 | V109: 2026-10-08 | W109: =IFERROR(INDEX('Area safety'!$C$23:$C$41,MATCH($B109,'Area safety'!$A$23:$A$41,0)),"n/a") -> Margate | X109: =IFERROR(INDEX('Area safety'!$D$23:$D$41,MATCH($B109,'Area safety'!$A$23:$A$41,0)),"n/a") -> CONFIRMED | Y109: =IFERROR(INDEX('Area safety'!$F$23:$F$41,MATCH($B109,'Area safety'!$A$23:$A$41,0)),"n/a") -> 1154.5136 | Z109: =IFERROR(INDEX('Area safety'!$G$23:$G$41,MATCH($B109,'Area safety'!$A$23:$A$41,0)),"n/a") -> 691.04551 | AA109: =IFERROR(INDEX('Area safety'!$H$23:$H$41,MATCH($B109,'Area safety'!$A$23:$A$41,0)),"n/a") -> 23.900822 | AB109: =IFERROR(INDEX('Area safety'!$I$23:$I$41,MATCH($B109,'Area safety'!$A$23:$A$41,0)),"n/a") -> 4980.7235 | AC109: =IFERROR(INDEX('Area safety'!$F$5:$F$18,MATCH($W109,'Area safety'!$A$5:$A$18,0)),"n/a") -> 4793 | AD109: =IFERROR(INDEX('Area safety'!$G$5:$G$18,MATCH($W109,'Area safety'!$A$5:$A$18,0)),"n/a") -> 23 | AE109: =IFERROR(INDEX('Area safety'!$H$5:$H$18,MATCH($W109,'Area safety'!$A$5:$A$18,0)),"n/a") -> 1111 | AF109: =IFERROR(INDEX('Area safety'!$I$5:$I$18,MATCH($W109,'Area safety'!$A$5:$A$18,0)),"n/a") -> 665 | AG109: =IFERROR(INDEX('Area safety'!$K$23:$K$41,MATCH($B109,'Area safety'!$A$23:$A$41,0)),"n/a") -> 0.099059849 | AH109: =IFERROR(INDEX('Area safety'!$J$23:$J$41,MATCH($B109,'Area safety'!$A$23:$A$41,0)),"n/a") -> 4
A110: Margate | B110: Manaba Beach | C110: Available | D110: 750000 | E110: Apartment / Flat | F110: Top Floor | G110: 2 | H110: 1 parking | I110: 90 | J110: 3860 | K110: 974 | L110: No | M110: NOT STATED | N110: Coastal Living in Manaba Beach This 2-bedroom, 2-bathroom property offers a comfortable retreat in the sought-after Manaba Beach complex. | Sea views from balcony, Coastal beach location in established..., Coastal Living in Manaba Beach, This 2-bedroom, 2-bathroom property offers a comfortable retreat in the sought-after Manaba Beach complex. Positioned on a generous 4,855 sqm erf, the apartment provides a peaceful coastal lifestyle with direct access to beach amenities and the natural beauty of the South Coast, The compact 90 sqm floor plan is efficiently designed with a lounge and single kitchen, creating a functional living space ideal for couples, small families, or holiday accommodation. The property features a balcony that captures sea views, allowing you to enjoy the coastal atmosphere from your own private space. Security is maintained through perimeter fencing and an access gate, ensuring peace of mind in this established complex environment., Sea views from balcony | O110: Michelle Angelique Adcock | P110: RE/MAX Coast and Country Shelly Beach | Q110: NOT CAPTURED (reCAPTCHA) | R110: NOT AVAILABLE (needs phone) | S110: Agent profile | T110: Open listing | U110: 28 September 2026 | V110: 2026-10-08 | W110: =IFERROR(INDEX('Area safety'!$C$23:$C$41,MATCH($B110,'Area safety'!$A$23:$A$41,0)),"n/a") -> Margate | X110: =IFERROR(INDEX('Area safety'!$D$23:$D$41,MATCH($B110,'Area safety'!$A$23:$A$41,0)),"n/a") -> CONFIRMED | Y110: =IFERROR(INDEX('Area safety'!$F$23:$F$41,MATCH($B110,'Area safety'!$A$23:$A$41,0)),"n/a") -> 1154.5136 | Z110: =IFERROR(INDEX('Area safety'!$G$23:$G$41,MATCH($B110,'Area safety'!$A$23:$A$41,0)),"n/a") -> 691.04551 | AA110: =IFERROR(INDEX('Area safety'!$H$23:$H$41,MATCH($B110,'Area safety'!$A$23:$A$41,0)),"n/a") -> 23.900822 | AB110: =IFERROR(INDEX('Area safety'!$I$23:$I$41,MATCH($B110,'Area safety'!$A$23:$A$41,0)),"n/a") -> 4980.7235 | AC110: =IFERROR(INDEX('Area safety'!$F$5:$F$18,MATCH($W110,'Area safety'!$A$5:$A$18,0)),"n/a") -> 4793 | AD110: =IFERROR(INDEX('Area safety'!$G$5:$G$18,MATCH($W110,'Area safety'!$A$5:$A$18,0)),"n/a") -> 23 | AE110: =IFERROR(INDEX('Area safety'!$H$5:$H$18,MATCH($W110,'Area safety'!$A$5:$A$18,0)),"n/a") -> 1111 | AF110: =IFERROR(INDEX('Area safety'!$I$5:$I$18,MATCH($W110,'Area safety'!$A$5:$A$18,0)),"n/a") -> 665 | AG110: =IFERROR(INDEX('Area safety'!$K$23:$K$41,MATCH($B110,'Area safety'!$A$23:$A$41,0)),"n/a") -> 0.099059849 | AH110: =IFERROR(INDEX('Area safety'!$J$23:$J$41,MATCH($B110,'Area safety'!$A$23:$A$41,0)),"n/a") -> 4
A111: Margate | B111: Manaba Beach | C111: Available | D111: 750000 | E111: Apartment / Flat | F111: NOT STATED | G111: 2 | H111: 1 garage | I111: 55 | J111: NOT STATED | K111: NOT STATED | L111: NOT STATED | M111: NOT STATED | N111: Step into this charming 2-bedroom, 1-bathroom unit with an open-plan kitchen — a safe haven where the fresh Margate ocean breeze welcomes you and new | O111: Yolandi Grobler | P111: Real & Proper T | Q111: NOT CAPTURED (reCAPTCHA) | R111: NOT AVAILABLE (needs phone) | S111: Agent profile | T111: Open listing | U111: 16 September 2026 | V111: 2026-10-08 | W111: =IFERROR(INDEX('Area safety'!$C$23:$C$41,MATCH($B111,'Area safety'!$A$23:$A$41,0)),"n/a") -> Margate | X111: =IFERROR(INDEX('Area safety'!$D$23:$D$41,MATCH($B111,'Area safety'!$A$23:$A$41,0)),"n/a") -> CONFIRMED | Y111: =IFERROR(INDEX('Area safety'!$F$23:$F$41,MATCH($B111,'Area safety'!$A$23:$A$41,0)),"n/a") -> 1154.5136 | Z111: =IFERROR(INDEX('Area safety'!$G$23:$G$41,MATCH($B111,'Area safety'!$A$23:$A$41,0)),"n/a") -> 691.04551 | AA111: =IFERROR(INDEX('Area safety'!$H$23:$H$41,MATCH($B111,'Area safety'!$A$23:$A$41,0)),"n/a") -> 23.900822 | AB111: =IFERROR(INDEX('Area safety'!$I$23:$I$41,MATCH($B111,'Area safety'!$A$23:$A$41,0)),"n/a") -> 4980.7235 | AC111: =IFERROR(INDEX('Area safety'!$F$5:$F$18,MATCH($W111,'Area safety'!$A$5:$A$18,0)),"n/a") -> 4793 | AD111: =IFERROR(INDEX('Area safety'!$G$5:$G$18,MATCH($W111,'Area safety'!$A$5:$A$18,0)),"n/a") -> 23 | AE111: =IFERROR(INDEX('Area safety'!$H$5:$H$18,MATCH($W111,'Area safety'!$A$5:$A$18,0)),"n/a") -> 1111 | AF111: =IFERROR(INDEX('Area safety'!$I$5:$I$18,MATCH($W111,'Area safety'!$A$5:$A$18,0)),"n/a") -> 665 | AG111: =IFERROR(INDEX('Area safety'!$K$23:$K$41,MATCH($B111,'Area safety'!$A$23:$A$41,0)),"n/a") -> 0.099059849 | AH111: =IFERROR(INDEX('Area safety'!$J$23:$J$41,MATCH($B111,'Area safety'!$A$23:$A$41,0)),"n/a") -> 4
A112: Margate | B112: Manaba Beach | C112: Available | D112: 750000 | E112: Apartment / Flat | F112: NOT STATED | G112: 2 | H112: 1 parking | I112: 77 | J112: 2200 | K112: 980 | L112: NOT STATED | M112: Yes | N112: Authority to sell* This perfectly positioned apartment in Manaba Beach is a rare opportunity to secure a prime apartment situated right on Lilliecrona | Garden | O112: Rochelle Combrink | P112: Home Finders Coastal | Q112: NOT CAPTURED (reCAPTCHA) | R112: NOT AVAILABLE (needs phone) | S112: Agent profile | T112: Open listing | U112: 22 April 2026 | V112: 2026-10-08 | W112: =IFERROR(INDEX('Area safety'!$C$23:$C$41,MATCH($B112,'Area safety'!$A$23:$A$41,0)),"n/a") -> Margate | X112: =IFERROR(INDEX('Area safety'!$D$23:$D$41,MATCH($B112,'Area safety'!$A$23:$A$41,0)),"n/a") -> CONFIRMED | Y112: =IFERROR(INDEX('Area safety'!$F$23:$F$41,MATCH($B112,'Area safety'!$A$23:$A$41,0)),"n/a") -> 1154.5136 | Z112: =IFERROR(INDEX('Area safety'!$G$23:$G$41,MATCH($B112,'Area safety'!$A$23:$A$41,0)),"n/a") -> 691.04551 | AA112: =IFERROR(INDEX('Area safety'!$H$23:$H$41,MATCH($B112,'Area safety'!$A$23:$A$41,0)),"n/a") -> 23.900822 | AB112: =IFERROR(INDEX('Area safety'!$I$23:$I$41,MATCH($B112,'Area safety'!$A$23:$A$41,0)),"n/a") -> 4980.7235 | AC112: =IFERROR(INDEX('Area safety'!$F$5:$F$18,MATCH($W112,'Area safety'!$A$5:$A$18,0)),"n/a") -> 4793 | AD112: =IFERROR(INDEX('Area safety'!$G$5:$G$18,MATCH($W112,'Area safety'!$A$5:$A$18,0)),"n/a") -> 23 | AE112: =IFERROR(INDEX('Area safety'!$H$5:$H$18,MATCH($W112,'Area safety'!$A$5:$A$18,0)),"n/a") -> 1111 | AF112: =IFERROR(INDEX('Area safety'!$I$5:$I$18,MATCH($W112,'Area safety'!$A$5:$A$18,0)),"n/a") -> 665 | AG112: =IFERROR(INDEX('Area safety'!$K$23:$K$41,MATCH($B112,'Area safety'!$A$23:$A$41,0)),"n/a") -> 0.099059849 | AH112: =IFERROR(INDEX('Area safety'!$J$23:$J$41,MATCH($B112,'Area safety'!$A$23:$A$41,0)),"n/a") -> 4
A113: Margate | B113: Margate Beach | C113: Available | D113: 595000 | E113: Apartment / Flat | F113: NOT STATED | G113: 2 | H113: 1 garage | I113: 76 | J113: 1984 | K113: 675 | L113: No | M113: Yes | N113: If you are looking for the perfect unit to start or an income generator, this is the one for you. | No Pets Allowed | O113: Ayanda Zwalo | P113: Alpha Estates | Q113: NOT CAPTURED (reCAPTCHA) | R113: NOT AVAILABLE (needs phone) | S113: Agent profile | T113: Open listing | U113: 11 October 2025 | V113: 2026-10-08 | W113: =IFERROR(INDEX('Area safety'!$C$23:$C$41,MATCH($B113,'Area safety'!$A$23:$A$41,0)),"n/a") -> Margate | X113: =IFERROR(INDEX('Area safety'!$D$23:$D$41,MATCH($B113,'Area safety'!$A$23:$A$41,0)),"n/a") -> CONFIRMED | Y113: =IFERROR(INDEX('Area safety'!$F$23:$F$41,MATCH($B113,'Area safety'!$A$23:$A$41,0)),"n/a") -> 1154.5136 | Z113: =IFERROR(INDEX('Area safety'!$G$23:$G$41,MATCH($B113,'Area safety'!$A$23:$A$41,0)),"n/a") -> 691.04551 | AA113: =IFERROR(INDEX('Area safety'!$H$23:$H$41,MATCH($B113,'Area safety'!$A$23:$A$41,0)),"n/a") -> 23.900822 | AB113: =IFERROR(INDEX('Area safety'!$I$23:$I$41,MATCH($B113,'Area safety'!$A$23:$A$41,0)),"n/a") -> 4980.7235 | AC113: =IFERROR(INDEX('Area safety'!$F$5:$F$18,MATCH($W113,'Area safety'!$A$5:$A$18,0)),"n/a") -> 4793 | AD113: =IFERROR(INDEX('Area safety'!$G$5:$G$18,MATCH($W113,'Area safety'!$A$5:$A$18,0)),"n/a") -> 23 | AE113: =IFERROR(INDEX('Area safety'!$H$5:$H$18,MATCH($W113,'Area safety'!$A$5:$A$18,0)),"n/a") -> 1111 | AF113: =IFERROR(INDEX('Area safety'!$I$5:$I$18,MATCH($W113,'Area safety'!$A$5:$A$18,0)),"n/a") -> 665 | AG113: =IFERROR(INDEX('Area safety'!$K$23:$K$41,MATCH($B113,'Area safety'!$A$23:$A$41,0)),"n/a") -> 0.099059849 | AH113: =IFERROR(INDEX('Area safety'!$J$23:$J$41,MATCH($B113,'Area safety'!$A$23:$A$41,0)),"n/a") -> 4
A114: Margate | B114: Margate Beach | C114: Available | D114: 600000 | E114: Apartment / Flat | F114: NOT STATED | G114: 2 | H114: 1 parking | I114: 66 | J114: 2500 | K114: 500 | L114: NOT STATED | M114: NOT STATED | N114: This neat and tidy two bedroomed apartment is perfectly positioned to take advantage of all that Margate has to offer. | O114: Jim Spencer | P114: Rawson Properties Margate | Q114: NOT CAPTURED (reCAPTCHA) | R114: NOT AVAILABLE (needs phone) | S114: Agent profile | T114: Open listing | U114: 06 September 2026 | V114: 2026-10-08 | W114: =IFERROR(INDEX('Area safety'!$C$23:$C$41,MATCH($B114,'Area safety'!$A$23:$A$41,0)),"n/a") -> Margate | X114: =IFERROR(INDEX('Area safety'!$D$23:$D$41,MATCH($B114,'Area safety'!$A$23:$A$41,0)),"n/a") -> CONFIRMED | Y114: =IFERROR(INDEX('Area safety'!$F$23:$F$41,MATCH($B114,'Area safety'!$A$23:$A$41,0)),"n/a") -> 1154.5136 | Z114: =IFERROR(INDEX('Area safety'!$G$23:$G$41,MATCH($B114,'Area safety'!$A$23:$A$41,0)),"n/a") -> 691.04551 | AA114: =IFERROR(INDEX('Area safety'!$H$23:$H$41,MATCH($B114,'Area safety'!$A$23:$A$41,0)),"n/a") -> 23.900822 | AB114: =IFERROR(INDEX('Area safety'!$I$23:$I$41,MATCH($B114,'Area safety'!$A$23:$A$41,0)),"n/a") -> 4980.7235 | AC114: =IFERROR(INDEX('Area safety'!$F$5:$F$18,MATCH($W114,'Area safety'!$A$5:$A$18,0)),"n/a") -> 4793 | AD114: =IFERROR(INDEX('Area safety'!$G$5:$G$18,MATCH($W114,'Area safety'!$A$5:$A$18,0)),"n/a") -> 23 | AE114: =IFERROR(INDEX('Area safety'!$H$5:$H$18,MATCH($W114,'Area safety'!$A$5:$A$18,0)),"n/a") -> 1111 | AF114: =IFERROR(INDEX('Area safety'!$I$5:$I$18,MATCH($W114,'Area safety'!$A$5:$A$18,0)),"n/a") -> 665 | AG114: =IFERROR(INDEX('Area safety'!$K$23:$K$41,MATCH($B114,'Area safety'!$A$23:$A$41,0)),"n/a") -> 0.099059849 | AH114: =IFERROR(INDEX('Area safety'!$J$23:$J$41,MATCH($B114,'Area safety'!$A$23:$A$41,0)),"n/a") -> 4
A115: Margate | B115: Margate Beach | C115: Available | D115: 600000 | E115: Apartment / Flat | F115: NOT STATED | G115: 2 | H115: NOT STATED | I115: 77 | J115: 1760 | K115: 600 | L115: No | M115: NOT STATED | N115: This well-sized 2-bedroom flat offers comfortable living in a highly sought-after location. | No Pets Allowed | O115: Natasha Heathfield | P115: Property.CoZa - Legends | Q115: NOT CAPTURED (reCAPTCHA) | R115: NOT AVAILABLE (needs phone) | S115: Agent profile | T115: Open listing | U115: 19 June 2025 | V115: 2026-10-08 | W115: =IFERROR(INDEX('Area safety'!$C$23:$C$41,MATCH($B115,'Area safety'!$A$23:$A$41,0)),"n/a") -> Margate | X115: =IFERROR(INDEX('Area safety'!$D$23:$D$41,MATCH($B115,'Area safety'!$A$23:$A$41,0)),"n/a") -> CONFIRMED | Y115: =IFERROR(INDEX('Area safety'!$F$23:$F$41,MATCH($B115,'Area safety'!$A$23:$A$41,0)),"n/a") -> 1154.5136 | Z115: =IFERROR(INDEX('Area safety'!$G$23:$G$41,MATCH($B115,'Area safety'!$A$23:$A$41,0)),"n/a") -> 691.04551 | AA115: =IFERROR(INDEX('Area safety'!$H$23:$H$41,MATCH($B115,'Area safety'!$A$23:$A$41,0)),"n/a") -> 23.900822 | AB115: =IFERROR(INDEX('Area safety'!$I$23:$I$41,MATCH($B115,'Area safety'!$A$23:$A$41,0)),"n/a") -> 4980.7235 | AC115: =IFERROR(INDEX('Area safety'!$F$5:$F$18,MATCH($W115,'Area safety'!$A$5:$A$18,0)),"n/a") -> 4793 | AD115: =IFERROR(INDEX('Area safety'!$G$5:$G$18,MATCH($W115,'Area safety'!$A$5:$A$18,0)),"n/a") -> 23 | AE115: =IFERROR(INDEX('Area safety'!$H$5:$H$18,MATCH($W115,'Area safety'!$A$5:$A$18,0)),"n/a") -> 1111 | AF115: =IFERROR(INDEX('Area safety'!$I$5:$I$18,MATCH($W115,'Area safety'!$A$5:$A$18,0)),"n/a") -> 665 | AG115: =IFERROR(INDEX('Area safety'!$K$23:$K$41,MATCH($B115,'Area safety'!$A$23:$A$41,0)),"n/a") -> 0.099059849 | AH115: =IFERROR(INDEX('Area safety'!$J$23:$J$41,MATCH($B115,'Area safety'!$A$23:$A$41,0)),"n/a") -> 4
A116: Margate | B116: Margate Beach | C116: Available | D116: 640000 | E116: Apartment / Flat | F116: First Floor | G116: 2 | H116: 2 parking | I116: 112 | J116: 1200 | K116: 1300 | L116: No | M116: NOT STATED | N116: This beautifully appointed two-bedroom apartment in the heart of Margate Beach offers an exceptional combination of comfort, style, and location. | No Pets Allowed, Fibre Internet | O116: Siyanda Cele | P116: Alpha Estates | Q116: NOT CAPTURED (reCAPTCHA) | R116: NOT AVAILABLE (needs phone) | S116: Agent profile | T116: Open listing | U116: 18 January 2025 | V116: 2026-10-08 | W116: =IFERROR(INDEX('Area safety'!$C$23:$C$41,MATCH($B116,'Area safety'!$A$23:$A$41,0)),"n/a") -> Margate | X116: =IFERROR(INDEX('Area safety'!$D$23:$D$41,MATCH($B116,'Area safety'!$A$23:$A$41,0)),"n/a") -> CONFIRMED | Y116: =IFERROR(INDEX('Area safety'!$F$23:$F$41,MATCH($B116,'Area safety'!$A$23:$A$41,0)),"n/a") -> 1154.5136 | Z116: =IFERROR(INDEX('Area safety'!$G$23:$G$41,MATCH($B116,'Area safety'!$A$23:$A$41,0)),"n/a") -> 691.04551 | AA116: =IFERROR(INDEX('Area safety'!$H$23:$H$41,MATCH($B116,'Area safety'!$A$23:$A$41,0)),"n/a") -> 23.900822 | AB116: =IFERROR(INDEX('Area safety'!$I$23:$I$41,MATCH($B116,'Area safety'!$A$23:$A$41,0)),"n/a") -> 4980.7235 | AC116: =IFERROR(INDEX('Area safety'!$F$5:$F$18,MATCH($W116,'Area safety'!$A$5:$A$18,0)),"n/a") -> 4793 | AD116: =IFERROR(INDEX('Area safety'!$G$5:$G$18,MATCH($W116,'Area safety'!$A$5:$A$18,0)),"n/a") -> 23 | AE116: =IFERROR(INDEX('Area safety'!$H$5:$H$18,MATCH($W116,'Area safety'!$A$5:$A$18,0)),"n/a") -> 1111 | AF116: =IFERROR(INDEX('Area safety'!$I$5:$I$18,MATCH($W116,'Area safety'!$A$5:$A$18,0)),"n/a") -> 665 | AG116: =IFERROR(INDEX('Area safety'!$K$23:$K$41,MATCH($B116,'Area safety'!$A$23:$A$41,0)),"n/a") -> 0.099059849 | AH116: =IFERROR(INDEX('Area safety'!$J$23:$J$41,MATCH($B116,'Area safety'!$A$23:$A$41,0)),"n/a") -> 4
A117: Margate | B117: Margate Beach | C117: Available | D117: 650000 | E117: Apartment / Flat | F117: Second floor and above | G117: 2 | H117: 1 parking | I117: 87 | J117: 3388 | K117: 1000 | L117: No | M117: NOT STATED | N117: Holiday Investment – Seabrook Flats, Margate This stunning corner unit offers an excellent holiday investment opportunity in one of Margate’s most sou | No Pets Allowed, Garden, Fibre Internet | O117: Ada van Wyk | P117: iProperty Investment | Q117: NOT CAPTURED (reCAPTCHA) | R117: NOT AVAILABLE (needs phone) | S117: Agent profile | T117: Open listing | U117: 24 May 2026 | V117: 2026-10-08 | W117: =IFERROR(INDEX('Area safety'!$C$23:$C$41,MATCH($B117,'Area safety'!$A$23:$A$41,0)),"n/a") -> Margate | X117: =IFERROR(INDEX('Area safety'!$D$23:$D$41,MATCH($B117,'Area safety'!$A$23:$A$41,0)),"n/a") -> CONFIRMED | Y117: =IFERROR(INDEX('Area safety'!$F$23:$F$41,MATCH($B117,'Area safety'!$A$23:$A$41,0)),"n/a") -> 1154.5136 | Z117: =IFERROR(INDEX('Area safety'!$G$23:$G$41,MATCH($B117,'Area safety'!$A$23:$A$41,0)),"n/a") -> 691.04551 | AA117: =IFERROR(INDEX('Area safety'!$H$23:$H$41,MATCH($B117,'Area safety'!$A$23:$A$41,0)),"n/a") -> 23.900822 | AB117: =IFERROR(INDEX('Area safety'!$I$23:$I$41,MATCH($B117,'Area safety'!$A$23:$A$41,0)),"n/a") -> 4980.7235 | AC117: =IFERROR(INDEX('Area safety'!$F$5:$F$18,MATCH($W117,'Area safety'!$A$5:$A$18,0)),"n/a") -> 4793 | AD117: =IFERROR(INDEX('Area safety'!$G$5:$G$18,MATCH($W117,'Area safety'!$A$5:$A$18,0)),"n/a") -> 23 | AE117: =IFERROR(INDEX('Area safety'!$H$5:$H$18,MATCH($W117,'Area safety'!$A$5:$A$18,0)),"n/a") -> 1111 | AF117: =IFERROR(INDEX('Area safety'!$I$5:$I$18,MATCH($W117,'Area safety'!$A$5:$A$18,0)),"n/a") -> 665 | AG117: =IFERROR(INDEX('Area safety'!$K$23:$K$41,MATCH($B117,'Area safety'!$A$23:$A$41,0)),"n/a") -> 0.099059849 | AH117: =IFERROR(INDEX('Area safety'!$J$23:$J$41,MATCH($B117,'Area safety'!$A$23:$A$41,0)),"n/a") -> 4
...

Sheet Area safety
A1: Area safety - SAPS precinct crime, Apr 2025 - Mar 2026, per 100,000 residents
A2: Scope: Port Edward north to Pennington plus inland (<=30 km). Only corridor precincts ranked 1-5 on violent-crime rate are kept. Counts: SAPS quarterly statistics via SafeSuburb (violent = SAPS contact crime; property = property-related). Population: ISS Crimehub precinct population implied from its "incidents per 100,000" charts (2024 data year, applied to 2025/26 counts, so rates are indicative). Rural inland precincts with no apartment market (Sawoti, Msinsini, Mehlomnyama, Dududu, Ezinqoleni, Harding, St Faiths) are not ranked. Scraped 2026-10-08. Rank 1 = lowest violent rate.
A4: Precinct | B4: District | C4: Group | D4: Population (Crimehub, 2024) | E4: Population source | F4: Total crimes 25/26 | G4: Murders 25/26 | H4: Violent (contact) 25/26 | I4: Property 25/26 | J4: Total crimes 24/25 | K4: Violent 24/25 | L4: Total per 100k | M4: Murder per 100k | N4: Violent per 100k | O4: Property per 100k | P4: Change in total vs 24/25 | Q4: Change in violent vs 24/25 | R4: Most common crime | S4: Count of most common | T4: Rank (violent rate, 1 = best) | U4: Decision
A5: Port Edward | B5: Ugu | C5: Corridor (ranked) | D5: 43892 | E5: ISS Crimehub precinct population (implied, 2024) | F5: 895 | G5: 12 | H5: 251 | I5: 262 | J5: 826 | K5: 266 | L5: =IFERROR(F5/D5*100000,"n/a") -> 2039.096 | M5: =IFERROR(G5/D5*100000,"n/a") -> 27.339834 | N5: =IFERROR(H5/D5*100000,"n/a") -> 571.8582 | O5: =IFERROR(I5/D5*100000,"n/a") -> 596.91971 | P5: =IFERROR(F5/J5-1,"n/a") -> 0.083535109 | Q5: =IFERROR(H5/K5-1,"n/a") -> -0.056390977 | R5: Burglary at residential premises | S5: 172 | T5: =IFERROR(RANK(N5,$N$5:$N$13,1),"n/a") -> 1 | U5: =IF(T5<=5,"KEEP","AVOID") -> KEEP
A6: Southport | B6: Ugu | C6: Corridor (ranked) | D6: 28552 | E6: ISS Crimehub precinct population (implied, 2024) | F6: 647 | G6: 8 | H6: 211 | I6: 193 | J6: 658 | K6: 202 | L6: =IFERROR(F6/D6*100000,"n/a") -> 2266.0409 | M6: =IFERROR(G6/D6*100000,"n/a") -> 28.019053 | N6: =IFERROR(H6/D6*100000,"n/a") -> 739.00252 | O6: =IFERROR(I6/D6*100000,"n/a") -> 675.95965 | P6: =IFERROR(F6/J6-1,"n/a") -> -0.016717325 | Q6: =IFERROR(H6/K6-1,"n/a") -> 0.044554455 | R6: Burglary at residential premises | S6: 139 | T6: =IFERROR(RANK(N6,$N$5:$N$13,1),"n/a") -> 2 | U6: =IF(T6<=5,"KEEP","AVOID") -> KEEP
A7: Hibberdene | B7: Ugu | C7: Corridor (ranked) | D7: 64633 | E7: ISS Crimehub precinct population (implied, 2024) | F7: 1590 | G7: 40 | H7: 681 | I7: 339 | J7: 1735 | K7: 793 | L7: =IFERROR(F7/D7*100000,"n/a") -> 2460.0436 | M7: =IFERROR(G7/D7*100000,"n/a") -> 61.88789 | N7: =IFERROR(H7/D7*100000,"n/a") -> 1053.6413 | O7: =IFERROR(I7/D7*100000,"n/a") -> 524.49987 | P7: =IFERROR(F7/J7-1,"n/a") -> -0.083573487 | Q7: =IFERROR(H7/K7-1,"n/a") -> -0.14123581 | R7: Burglary at residential premises | S7: 232 | T7: =IFERROR(RANK(N7,$N$5:$N$13,1),"n/a") -> 3 | U7: =IF(T7<=5,"KEEP","AVOID") -> KEEP
A8: Margate | B8: Ugu | C8: Corridor (ranked) | D8: 96231 | E8: ISS Crimehub precinct population (implied, 2024) | F8: 4793 | G8: 23 | H8: 1111 | I8: 665 | J8: 4361 | K8: 1171 | L8: =IFERROR(F8/D8*100000,"n/a") -> 4980.7235 | M8: =IFERROR(G8/D8*100000,"n/a") -> 23.900822 | N8: =IFERROR(H8/D8*100000,"n/a") -> 1154.5136 | O8: =IFERROR(I8/D8*100000,"n/a") -> 691.04551 | P8: =IFERROR(F8/J8-1,"n/a") -> 0.099059849 | Q8: =IFERROR(H8/K8-1,"n/a") -> -0.051238258 | R8: Drug-related crime | S8: 714 | T8: =IFERROR(RANK(N8,$N$5:$N$13,1),"n/a") -> 4 | U8: =IF(T8<=5,"KEEP","AVOID") -> KEEP
A9: Scottburgh | B9: Ugu | C9: Corridor (ranked) | D9: 30664 | E9: ISS Crimehub precinct population (implied, 2024) | F9: 1495 | G9: 13 | H9: 383 | I9: 293 | J9: 1467 | K9: 386 | L9: =IFERROR(F9/D9*100000,"n/a") -> 4875.4239 | M9: =IFERROR(G9/D9*100000,"n/a") -> 42.394991 | N9: =IFERROR(H9/D9*100000,"n/a") -> 1249.0217 | O9: =IFERROR(I9/D9*100000,"n/a") -> 955.51787 | P9: =IFERROR(F9/J9-1,"n/a") -> 0.019086571 | Q9: =IFERROR(H9/K9-1,"n/a") -> -0.0077720207 | R9: Commercial crime | S9: 226 | T9: =IFERROR(RANK(N9,$N$5:$N$13,1),"n/a") -> 5 | U9: =IF(T9<=5,"KEEP","AVOID") -> KEEP
A10: Umzinto | B10: Ugu | C10: Corridor (ranked) | D10: 45761 | E10: ISS Crimehub precinct population (implied, 2024) | F10: 1432 | G10: 28 | H10: 579 | I10: 168 | J10: 1432 | K10: 537 | L10: =IFERROR(F10/D10*100000,"n/a") -> 3129.3022 | M10: =IFERROR(G10/D10*100000,"n/a") -> 61.187474 | N10: =IFERROR(H10/D10*100000,"n/a") -> 1265.2696 | O10: =IFERROR(I10/D10*100000,"n/a") -> 367.12484 | P10: =IFERROR(F10/J10-1,"n/a") -> 0 | Q10: =IFERROR(H10/K10-1,"n/a") -> 0.078212291 | R10: Drug-related crime | S10: 255 | T10: =IFERROR(RANK(N10,$N$5:$N$13,1),"n/a") -> 6 | U10: =IF(T10<=5,"KEEP","AVOID") -> AVOID
A11: Paddock | B11: Ugu | C11: Corridor (ranked) | D11: 15207 | E11: ISS Crimehub precinct population (implied, 2024) | F11: 490 | G11: 9 | H11: 222 | I11: 117 | J11: 522 | K11: 247 | L11: =IFERROR(F11/D11*100000,"n/a") -> 3222.2003 | M11: =IFERROR(G11/D11*100000,"n/a") -> 59.183271 | N11: =IFERROR(H11/D11*100000,"n/a") -> 1459.854 | O11: =IFERROR(I11/D11*100000,"n/a") -> 769.38252 | P11: =IFERROR(F11/J11-1,"n/a") -> -0.061302682 | Q11: =IFERROR(H11/K11-1,"n/a") -> -0.10121457 | R11: Burglary at residential premises | S11: 85 | T11: =IFERROR(RANK(N11,$N$5:$N$13,1),"n/a") -> 7 | U11: =IF(T11<=5,"KEEP","AVOID") -> AVOID
A12: Port Shepstone | B12: Ugu | C12: Corridor (ranked) | D12: 79084 | E12: ISS Crimehub precinct population (implied, 2024) | F12: 4202 | G12: 37 | H12: 1269 | I12: 734 | J12: 4167 | K12: 1333 | L12: =IFERROR(F12/D12*100000,"n/a") -> 5313.3377 | M12: =IFERROR(G12/D12*100000,"n/a") -> 46.785696 | N12: =IFERROR(H12/D12*100000,"n/a") -> 1604.6229 | O12: =IFERROR(I12/D12*100000,"n/a") -> 928.12705 | P12: =IFERROR(F12/J12-1,"n/a") -> 0.0083993281 | Q12: =IFERROR(H12/K12-1,"n/a") -> -0.048012003 | R12: Common assault | S12: 520 | T12: =IFERROR(RANK(N12,$N$5:$N$13,1),"n/a") -> 8 | U12: =IF(T12<=5,"KEEP","AVOID") -> AVOID
A13: Gamalakhe | B13: Ugu | C13: Corridor (ranked) | D13: 34259 | E13: ISS Crimehub precinct population (implied, 2024) | F13: 1625 | G13: 11 | H13: 599 | I13: 435 | J13: 1389 | K13: 523 | L13: =IFERROR(F13/D13*100000,"n/a") -> 4743.2791 | M13: =IFERROR(G13/D13*100000,"n/a") -> 32.108351 | N13: =IFERROR(H13/D13*100000,"n/a") -> 1748.4457 | O13: =IFERROR(I13/D13*100000,"n/a") -> 1269.7393 | P13: =IFERROR(F13/J13-1,"n/a") -> 0.16990641 | Q13: =IFERROR(H13/K13-1,"n/a") -> 0.14531549 | R13: Burglary at residential premises | S13: 344 | T13: =IFERROR(RANK(N13,$N$5:$N$13,1),"n/a") -> 9 | U13: =IF(T13<=5,"KEEP","AVOID") -> AVOID
A14: Umhlali | B14: iLembe | C14: Reference only (not ranked) | D14: 99741 | E14: ISS Crimehub precinct population (implied, 2024) | F14: 2869 | G14: 67 | H14: 1000 | I14: 370 | J14: 2746 | K14: 919 | L14: =IFERROR(F14/D14*100000,"n/a") -> 2876.45 | M14: =IFERROR(G14/D14*100000,"n/a") -> 67.173981 | N14: =IFERROR(H14/D14*100000,"n/a") -> 1002.5967 | O14: =IFERROR(I14/D14*100000,"n/a") -> 370.96079 | P14: =IFERROR(F14/J14-1,"n/a") -> 0.044792425 | Q14: =IFERROR(H14/K14-1,"n/a") -> 0.088139282 | R14: Commercial crime | S14: 527 | T14: n/a | U14: Reference
A15: Westville | B15: eThekwini | C15: Reference only (not ranked) | D15: 46623 | E15: ISS Crimehub precinct population (implied, 2024) | F15: 1742 | G15: 4 | H15: 235 | I15: 433 | J15: 2001 | K15: 298 | L15: =IFERROR(F15/D15*100000,"n/a") -> 3736.3533 | M15: =IFERROR(G15/D15*100000,"n/a") -> 8.5794565 | N15: =IFERROR(H15/D15*100000,"n/a") -> 504.04307 | O15: =IFERROR(I15/D15*100000,"n/a") -> 928.72617 | P15: =IFERROR(F15/J15-1,"n/a") -> -0.12943528 | Q15: =IFERROR(H15/K15-1,"n/a") -> -0.2114094 | R15: Commercial crime | S15: 424 | T15: n/a | U15: Reference
A16: Amanzimtoti | B16: eThekwini | C16: Reference only (not ranked) | D16: 81135 | E16: ISS Crimehub precinct population (implied, 2024) | F16: 2536 | G16: 15 | H16: 525 | I16: 516 | J16: 2701 | K16: 603 | L16: =IFERROR(F16/D16*100000,"n/a") -> 3125.6548 | M16: =IFERROR(G16/D16*100000,"n/a") -> 18.487706 | N16: =IFERROR(H16/D16*100000,"n/a") -> 647.0697 | O16: =IFERROR(I16/D16*100000,"n/a") -> 635.97708 | P16: =IFERROR(F16/J16-1,"n/a") -> -0.061088486 | Q16: =IFERROR(H16/K16-1,"n/a") -> -0.12935323 | R16: Commercial crime | S16: 455 | T16: n/a | U16: Reference
A17: Durban North | B17: eThekwini | C17: Reference only (not ranked) | D17: 57890 | E17: ISS Crimehub precinct population (implied, 2024) | F17: 3825 | G17: 3 | H17: 525 | I17: 588 | J17: 3812 | K17: 544 | L17: =IFERROR(F17/D17*100000,"n/a") -> 6607.3588 | M17: =IFERROR(G17/D17*100000,"n/a") -> 5.1822422 | N17: =IFERROR(H17/D17*100000,"n/a") -> 906.89238 | O17: =IFERROR(I17/D17*100000,"n/a") -> 1015.7195 | P17: =IFERROR(F17/J17-1,"n/a") -> 0.0034102833 | Q17: =IFERROR(H17/K17-1,"n/a") -> -0.034926471 | R17: Commercial crime | S17: 1052 | T17: n/a | U17: Reference
A18: Umbilo | B18: eThekwini | C18: Reference only (not ranked) | D18: 45393 | E18: ISS Crimehub precinct population (implied, 2024) | F18: 3146 | G18: 16 | H18: 891 | I18: 630 | J18: 4099 | K18: 1112 | L18: =IFERROR(F18/D18*100000,"n/a") -> 6930.584 | M18: =IFERROR(G18/D18*100000,"n/a") -> 35.247725 | N18: =IFERROR(H18/D18*100000,"n/a") -> 1962.8577 | O18: =IFERROR(I18/D18*100000,"n/a") -> 1387.8792 | P18: =IFERROR(F18/J18-1,"n/a") -> -0.23249573 | Q18: =IFERROR(H18/K18-1,"n/a") -> -0.19874101 | R18: All theft not mentioned elsewhere | S18: 395 | T18: n/a | U18: Reference
A19: Green = kept (rank 1-5). Red = avoid (rank 6+). Grey = reference precincts you supplied, not part of the corridor ranking. Rates and ranks are live formulas.
A21: Location -> precinct (kept locations only; removed areas are on the "Areas to avoid" tab)
A22: Location (Property24 community) | B22: Property24 area | C22: Precinct used | D22: Confidence | E22: Listings kept | F22: Violent per 100k | G22: Property per 100k | H22: Murder per 100k | I22: Total per 100k | J22: Rank (violent, 1 = best) | K22: Change in total vs 24/25
A23: Port Edward | B23: Port Edward | C23: Port Edward | D23: CONFIRMED | E23: =COUNTIF('Property options'!$B:$B,A23) -> 10 | F23: =IFERROR(INDEX($N$5:$N$18,MATCH($C23,$A$5:$A$18,0)),"n/a") -> 571.8582 | G23: =IFERROR(INDEX($O$5:$O$18,MATCH($C23,$A$5:$A$18,0)),"n/a") -> 596.91971 | H23: =IFERROR(INDEX($M$5:$M$18,MATCH($C23,$A$5:$A$18,0)),"n/a") -> 27.339834 | I23: =IFERROR(INDEX($L$5:$L$18,MATCH($C23,$A$5:$A$18,0)),"n/a") -> 2039.096 | J23: =IFERROR(INDEX($T$5:$T$18,MATCH($C23,$A$5:$A$18,0)),"n/a") -> 1 | K23: =IFERROR(INDEX($P$5:$P$18,MATCH($C23,$A$5:$A$18,0)),"n/a") -> 0.083535109
A24: Glenmore | B24: Port Edward | C24: Port Edward | D24: UNCONFIRMED - provisional (assumed Port Edward precinct) | E24: =COUNTIF('Property options'!$B:$B,A24) -> 6 | F24: =IFERROR(INDEX($N$5:$N$18,MATCH($C24,$A$5:$A$18,0)),"n/a") -> 571.8582 | G24: =IFERROR(INDEX($O$5:$O$18,MATCH($C24,$A$5:$A$18,0)),"n/a") -> 596.91971 | H24: =IFERROR(INDEX($M$5:$M$18,MATCH($C24,$A$5:$A$18,0)),"n/a") -> 27.339834 | I24: =IFERROR(INDEX($L$5:$L$18,MATCH($C24,$A$5:$A$18,0)),"n/a") -> 2039.096 | J24: =IFERROR(INDEX($T$5:$T$18,MATCH($C24,$A$5:$A$18,0)),"n/a") -> 1 | K24: =IFERROR(INDEX($P$5:$P$18,MATCH($C24,$A$5:$A$18,0)),"n/a") -> 0.083535109
A25: Palm Beach | C25: Port Edward | D25: UNCONFIRMED - provisional (assumed Port Edward precinct) | E25: =COUNTIF('Property options'!$B:$B,A25) -> 0 | F25: =IFERROR(INDEX($N$5:$N$18,MATCH($C25,$A$5:$A$18,0)),"n/a") -> 571.8582 | G25: =IFERROR(INDEX($O$5:$O$18,MATCH($C25,$A$5:$A$18,0)),"n/a") -> 596.91971 | H25: =IFERROR(INDEX($M$5:$M$18,MATCH($C25,$A$5:$A$18,0)),"n/a") -> 27.339834 | I25: =IFERROR(INDEX($L$5:$L$18,MATCH($C25,$A$5:$A$18,0)),"n/a") -> 2039.096 | J25: =IFERROR(INDEX($T$5:$T$18,MATCH($C25,$A$5:$A$18,0)),"n/a") -> 1 | K25: =IFERROR(INDEX($P$5:$P$18,MATCH($C25,$A$5:$A$18,0)),"n/a") -> 0.083535109
A26: Leisure Bay | B26: Port Edward | C26: Port Edward | D26: CONFIRMED | E26: =COUNTIF('Property options'!$B:$B,A26) -> 2 | F26: =IFERROR(INDEX($N$5:$N$18,MATCH($C26,$A$5:$A$18,0)),"n/a") -> 571.8582 | G26: =IFERROR(INDEX($O$5:$O$18,MATCH($C26,$A$5:$A$18,0)),"n/a") -> 596.91971 | H26: =IFERROR(INDEX($M$5:$M$18,MATCH($C26,$A$5:$A$18,0)),"n/a") -> 27.339834 | I26: =IFERROR(INDEX($L$5:$L$18,MATCH($C26,$A$5:$A$18,0)),"n/a") -> 2039.096 | J26: =IFERROR(INDEX($T$5:$T$18,MATCH($C26,$A$5:$A$18,0)),"n/a") -> 1 | K26: =IFERROR(INDEX($P$5:$P$18,MATCH($C26,$A$5:$A$18,0)),"n/a") -> 0.083535109
A27: Trafalgar | C27: Port Edward | D27: CONFIRMED (boundary disputed) | E27: =COUNTIF('Property options'!$B:$B,A27) -> 0 | F27: =IFERROR(INDEX($N$5:$N$18,MATCH($C27,$A$5:$A$18,0)),"n/a") -> 571.8582 | G27: =IFERROR(INDEX($O$5:$O$18,MATCH($C27,$A$5:$A$18,0)),"n/a") -> 596.91971 | H27: =IFERROR(INDEX($M$5:$M$18,MATCH($C27,$A$5:$A$18,0)),"n/a") -> 27.339834 | I27: =IFERROR(INDEX($L$5:$L$18,MATCH($C27,$A$5:$A$18,0)),"n/a") -> 2039.096 | J27: =IFERROR(INDEX($T$5:$T$18,MATCH($C27,$A$5:$A$18,0)),"n/a") -> 1 | K27: =IFERROR(INDEX($P$5:$P$18,MATCH($C27,$A$5:$A$18,0)),"n/a") -> 0.083535109
A28: Banners Rest | B28: Port Edward | C28: Port Edward | D28: UNCONFIRMED - provisional (assumed Port Edward precinct) | E28: =COUNTIF('Property options'!$B:$B,A28) -> 28 | F28: =IFERROR(INDEX($N$5:$N$18,MATCH($C28,$A$5:$A$18,0)),"n/a") -> 571.8582 | G28: =IFERROR(INDEX($O$5:$O$18,MATCH($C28,$A$5:$A$18,0)),"n/a") -> 596.91971 | H28: =IFERROR(INDEX($M$5:$M$18,MATCH($C28,$A$5:$A$18,0)),"n/a") -> 27.339834 | I28: =IFERROR(INDEX($L$5:$L$18,MATCH($C28,$A$5:$A$18,0)),"n/a") -> 2039.096 | J28: =IFERROR(INDEX($T$5:$T$18,MATCH($C28,$A$5:$A$18,0)),"n/a") -> 1 | K28: =IFERROR(INDEX($P$5:$P$18,MATCH($C28,$A$5:$A$18,0)),"n/a") -> 0.083535109
A29: Rennies Beach | B29: Port Edward | C29: Port Edward | D29: UNCONFIRMED - provisional (assumed Port Edward precinct) | E29: =COUNTIF('Property options'!$B:$B,A29) -> 4 | F29: =IFERROR(INDEX($N$5:$N$18,MATCH($C29,$A$5:$A$18,0)),"n/a") -> 571.8582 | G29: =IFERROR(INDEX($O$5:$O$18,MATCH($C29,$A$5:$A$18,0)),"n/a") -> 596.91971 | H29: =IFERROR(INDEX($M$5:$M$18,MATCH($C29,$A$5:$A$18,0)),"n/a") -> 27.339834 | I29: =IFERROR(INDEX($L$5:$L$18,MATCH($C29,$A$5:$A$18,0)),"n/a") -> 2039.096 | J29: =IFERROR(INDEX($T$5:$T$18,MATCH($C29,$A$5:$A$18,0)),"n/a") -> 1 | K29: =IFERROR(INDEX($P$5:$P$18,MATCH($C29,$A$5:$A$18,0)),"n/a") -> 0.083535109
A30: Ramsgate | B30: Margate | C30: Margate | D30: CONFIRMED | E30: =COUNTIF('Property options'!$B:$B,A30) -> 11 | F30: =IFERROR(INDEX($N$5:$N$18,MATCH($C30,$A$5:$A$18,0)),"n/a") -> 1154.5136 | G30: =IFERROR(INDEX($O$5:$O$18,MATCH($C30,$A$5:$A$18,0)),"n/a") -> 691.04551 | H30: =IFERROR(INDEX($M$5:$M$18,MATCH($C30,$A$5:$A$18,0)),"n/a") -> 23.900822 | I30: =IFERROR(INDEX($L$5:$L$18,MATCH($C30,$A$5:$A$18,0)),"n/a") -> 4980.7235 | J30: =IFERROR(INDEX($T$5:$T$18,MATCH($C30,$A$5:$A$18,0)),"n/a") -> 4 | K30: =IFERROR(INDEX($P$5:$P$18,MATCH($C30,$A$5:$A$18,0)),"n/a") -> 0.099059849
A31: Margate | B31: Margate | C31: Margate | D31: CONFIRMED | E31: =COUNTIF('Property options'!$B:$B,A31) -> 38 | F31: =IFERROR(INDEX($N$5:$N$18,MATCH($C31,$A$5:$A$18,0)),"n/a") -> 1154.5136 | G31: =IFERROR(INDEX($O$5:$O$18,MATCH($C31,$A$5:$A$18,0)),"n/a") -> 691.04551 | H31: =IFERROR(INDEX($M$5:$M$18,MATCH($C31,$A$5:$A$18,0)),"n/a") -> 23.900822 | I31: =IFERROR(INDEX($L$5:$L$18,MATCH($C31,$A$5:$A$18,0)),"n/a") -> 4980.7235 | J31: =IFERROR(INDEX($T$5:$T$18,MATCH($C31,$A$5:$A$18,0)),"n/a") -> 4 | K31: =IFERROR(INDEX($P$5:$P$18,MATCH($C31,$A$5:$A$18,0)),"n/a") -> 0.099059849
